Workbook

Sheet ⚙️ Assumptions
A1: ASSUMPTIONS & DRIVERS / GIẢ ĐỊNH & THÔNG SỐ ĐẦU VÀO
A5: Driver | B5: Value
A6: Start Month (Tháng bắt đầu) | B6: 46661
A7: Rent Area (Vị trí thuê địa điểm) | B7: Nearby Area(Cửa Nam, Nguyễn Hữu Huân, Triệu Việt Vương)
A8: Area (diện tích thuê) m2 | B8: 50
A9: Rent per m2 (Giá trên m2) | B9: =_xlfn.XLOOKUP(B7,'⚙️ Other Assumptions'!A8:A10,'⚙️ Other Assumptions'!B8:B10,1) -> 1150000
A10: Rent Price (Giá thuê) | B10: =B8*B9 -> 57500000
A11: Deposit month’s rent (Số tháng tiền cọc) | B11: 6
A12: Expected number of order sold per day (Công suất mục tiêu) | B12: 150
A13: Revenue Ramp-up Scenario (Kịch bản tăng trưởng doanh thu) | B13: Ramp-up Neutral
A14: Working Capital Buffer | B14: =_xlfn.LET( _xlpm.buffer_1,-SUM(OFFSET('💵 Cash Flow'!$C$11,0,0,1,_xlfn.XLOOKUP(1,SIGN('💵 Cash Flow'!$C$11:$BJ$11),'💵 Cash Flow'!$C$3:$BJ$3,"No Negative",0,1)-1)), _xlpm.Principal_buffer,-SUM(OFFSET('💵 Cash Flow'!$C$19,0,0,1,_xlfn.XLOOKUP(1,SIGN('💵 Cash Flow'!$C$11:$BJ$11),'💵 Cash Flow'!$C$3:$BJ$3,"No Negative",0,1)-1)), _xlpm.interest_buffer,-SUM(OFFSET('💵 Cash Flow'!$C$20,0,0,1,_xlfn.XLOOKUP(1,SIGN('💵 Cash Flow'!$C$11:$BJ$11),'💵 Cash Flow'!$C$3:$BJ$3,"No Negative",0,1)-1)), _xlpm.buffer_1 + _xlpm.Principal_buffer + _xlpm.interest_buffer) -> 2.6697327e+08
A16: Capital Expenditure (Chi phí đầu tư cố định) | B16: 300000000
A17: Deposit month’s rent $ (Cọc tiền thuê nhà) | B17: =$B$11*$B$10 -> 345000000
A18: Total | B18: =SUM(B16:B17) -> 645000000
A20: Capital Expenditure Breakdown (chi tiết Capex) | B20: % | C20: Qty | D20: Price
A21: Interior + concept design (Thiết kễ + nội thật quán) | B21: 0.23 | C21: 1 | D21: =$B$16*B21 -> 69000000
A22: Stove (Bếp điện) | B22: 0.17 | C22: 1 | D22: =$B$16*B22 -> 51000000
A23: Freezer (Tủ đông) | B23: 0.1 | C23: 1 | D23: =$B$16*B23 -> 30000000
A24: Refregerator (Tủ mát) | B24: 0.06 | C24: 1 | D24: =$B$16*B24 -> 18000000
A25: Shelf (Kệ inox đựng gia vị) | B25: 0.03 | C25: 1 | D25: =$B$16*B25 -> 9000000
A26: Others (Knives, cutting boards, pans) | B26: 0.04 | C26: 1 | D26: =$B$16*B26 -> 12000000
A27: SilverWare (Bát đũa, lọ gia vị) | B27: 0.05 | C27: 1 | D27: =$B$16*B27 -> 15000000
A28: Điều hòa ( 2 cái 1 chiều 9-12k BTU) | B28: 0.12 | C28: 2 | D28: =$B$16*B28 -> 36000000
A29: Electric (hệ thống điện 3 pha) | B29: 0.1 | C29: 1 | D29: =$B$16*B29 -> 30000000
A30: Water Line (Hệ thống nước + bể tách mỡ) | B30: 0.1 | C30: 1 | D30: =$B$16*B30 -> 30000000
A31: Total | B31: =SUM(B21:B30) -> 1 | D31: =SUM(D21:D30) -> 300000000
B37: First Year (Năm đầu tiên) | C37: Second Year (Năm thứ 2) | D37: Third Year (Năm thứ 3) | E37: Fourth Year (Năm thứ 4) | F37: Fifth Year (Năm thứ 5 )
B38: =YEAR(B6) -> 2027 | C38: =B38+1 -> 2028 | D38: =C38+1 -> 2029 | E38: =D38+1 -> 2030 | F38: =E38+1 -> 2031
A39: Raw Material % of Rev (tỷ trọng NVL/ Doanh thu) | B39: 0.35 | C39: 0.33 | D39: 0.3 | E39: 0.29 | F39: 0.29
A40: Electric Costs % of Rev (tỷ trọng chi phí điện/ Doanh thu) | B40: 0.04 | C40: 0.04 | D40: 0.04 | E40: 0.04 | F40: 0.04
A41: Water Cost % of Rev (tỷ trọng tiền nước/ Doanh thu) | B41: 0.015 | C41: 0.015 | D41: 0.015 | E41: 0.015 | F41: 0.015
A42: Maintainace Cost of Rev (Chi phí bảo trì bảo dưỡng) | B42: 0.01 | C42: 0.01 | D42: 0.03 | E42: 0.03 | F42: 0.04

Sheet 📋 Cover
A1: F&B RESTAURANT FP&A MODEL TEMPLATE
A4: Driver-Based Planning | Bilingual EN / VI | 36-Month Horizon
B6: PROJECT INFORMATION / THÔNG TIN DỰ ÁN
B7: Project Name / Tên dự án | C7: [Enter project name]
B8: Location / Địa điểm | C8: [Enter address]
B9: Concept / Mô hình | C9: [e.g. Casual Dining / Fine Dining / Fast Casual]
B10: Model Owner / Người lập | C10: [Name]
B11: Version / Phiên bản | C11: v1.0
B12: Date / Ngày | C12: [Date]
B13: Base Currency / Tiền tệ | C13: VNĐ
B14: Forecast Period | C14: 36 months / 3 years
B16: SHEET INDEX / DANH MỤC TRANG TÍNH | D16: PURPOSE / MỤC ĐÍCH
B17: 📋 Cover | C17: Project info, instructions, color legend
B18: ⚙️ Assumptions | C18: All input drivers – edit ONLY here / Tất cả giả định đầu vào
B19: 💰 Revenue | C19: Driver-based revenue forecast / Dự báo doanh thu
B20: 📦 COGS & OpEx | C20: Cost of goods + operating cost drivers / Chi phí biến đổi & cố định
B21: 👥 HR Plan | C21: Headcount plan & payroll budget / Kế hoạch nhân sự & lương
B22: 🏦 Loan Schedule | C22: Debt drawdown & amortisation / Lịch vay & trả nợ
B23: 📊 P&L Detail | C23: Monthly detailed P&L / Báo cáo KQHĐKD chi tiết
B24: 💵 Cash Flow | C24: Full 3-statement cash flow / Dòng tiền đầy đủ
B25: 🔄 Rolling Forecast | C25: 12-month rolling forecast vs actuals / Dự báo cuốn chiếu
B26: 🎯 Scenario Manager | C26: Bear / Base / Bull scenarios / Các kịch bản
B28: COLOR LEGEND / CHÚ THÍCH MÀU SẮC
B29: Blue text on yellow → Hardcoded INPUT – change these / Ô nhập liệu
B30: Green text → Formula pulling from another sheet / Liên kết sheet khác
B31: Black text → Formula / calculated cell / Công thức tính toán
B32: Red text → External link / Liên kết file ngoài
B33: Green background → Subtotal / sub-total row / Dòng tổng phụ
B34: Light green background → Alternating row / Hàng xen kẽ
B36: ⚠️ IMPORTANT / LƯU Ý: Only edit cells with BLUE text on YELLOW background in the Assumptions sheet. All other sheets are formula-driven and update automatically. / Chỉ chỉnh sửa các ô có chữ xanh dương nền vàng trong trang Assumptions. Tất cả trang còn lại được tính tự động.

Sheet ⚙️ Assumptions_1
A1: ASSUMPTIONS & DRIVERS / GIẢ ĐỊNH & THÔNG SỐ ĐẦU VÀO
A3: DRIVER / THÔNG SỐ | B3: VALUE / GIÁ TRỊ | C3: UNIT / ĐƠN VỊ | D3: YoY / TREND | E3: NOTES / GHI CHÚ
A4: A. VENUE & CAPACITY / MẶT BẰNG & CÔNG SUẤT
A5: Floor area / Diện tích sàn (m²) | C5: m² | E5: Total leased area
A6: Seating capacity / Số chỗ ngồi | C6: seats/chỗ | E6: Indoor + terrace
A7: Operating days/month / Ngày hoạt động TB | B7: 30 | C7: days/ngày | D7: —
A8: Floors / Tầng | E8: Floor number in building
A9: Opening month / Tháng khai trương | B9: M01 | E9: Enter M01–M36
A10: B. REVENUE DRIVERS / THÔNG SỐ DOANH THU
A11: Avg spend per cover – Yr1 / Giá xuất Năm 1 | C11: VNĐ | E11: Average revenue per diner
A12: Price increase YoY / Tăng giá mỗi năm | C12: %/year | D12: YoY | E12: Applied annually from Year 2
A13: Table turns (normal) / Vòng quay bàn TB | C13: turns/day | E13: e.g. 2.5
A14: Table turns (peak season) / Vòng quay cao điểm | C14: turns/day | E14: Tet, Christmas
A15: Target covers/day – Steady State / Lượng khách SS | C15: covers/khách | E15: Reference market analysis
A16: Ramp M01 / Tháng 1 (% SS) | B16: 0.05 | C16: % | D16: Ramp | E16: Opening month
A17: Ramp M02 (% SS) | B17: 0.1 | C17: % | D17: Ramp
A18: Ramp M03 (% SS) | B18: 0.2 | C18: % | D18: Ramp
A19: Ramp M04 (% SS) | B19: 0.35 | C19: % | D19: Ramp
A20: Ramp M05 (% SS) | B20: 0.5 | C20: % | D20: Ramp
A21: Ramp M06 (% SS) | B21: 0.7 | C21: % | D21: Ramp
A22: Steady state from / Đạt tốc độ bình thường từ | B22: M07 | D22: — | E22: Enter month code e.g. M07
A23: Seasonal peak multiplier / Hệ số mùa cao điểm | B23: 1.2 | C23: x | D23: — | E23: Applied to Tet/Christmas months
A24: Seasonal trough multiplier / Hệ số mùa thấp điểm | B24: 0.85 | C24: x | D24: — | E24: Applied to slow months (e.g. post-Tet)
A25: C. FOOD & BEVERAGE COST / CHI PHÍ THỰC PHẨM & ĐỒ UỐNG
A26: Food cost % revenue – Yr1 / Định mức TP Năm 1 | B26: 0.3 | C26: % rev | D26: YoY | E26: Typically 28–35% for F&B
A27: Beverage cost % revenue – Yr1 / Định mức đồ uống | B27: 0.2 | C27: % rev | D27: — | E27: Typically 18–25% for beverages
A28: Input price inflation YoY / Tăng giá nguyên liệu | B28: 0.1 | C28: %/year | D28: YoY | E28: Apply to COGS % from Year 2
A29: Food revenue mix / Tỷ lệ doanh thu thức ăn | B29: 0.65 | C29: % total rev | D29: — | E29: Remaining = beverage
A30: D. FIXED OPERATING COSTS / CHI PHÍ CỐ ĐỊNH VẬN HÀNH
A31: Base rent / Thuê mặt bằng (VNĐ/m²/month) | C31: VNĐ/m²/tháng | D31: — | E31: Monthly rent per m²
A32: FX rate / Tỷ giá (VNĐ/USD) | B32: 24000 | C32: VNĐ/USD | D32: — | E32: Update if rent quoted in USD
A33: Utilities / Điện nước (VNĐ/month) | C33: VNĐ/tháng | D33: YoY | E33: Electricity, water, gas
A34: Repairs & maintenance / Sửa chữa bảo trì | C34: VNĐ/tháng | D34: YoY
A35: Insurance / Bảo hiểm tài sản | C35: VNĐ/tháng | D35: —
A36: Fixed cost growth YoY / Tăng CP cố định | B36: 0.1 | C36: %/year | D36: YoY | E36: Applied from Year 2
A37: E. MARKETING & PROMOTIONS / MARKETING & KHUYẾN MẠI
A38: Monthly marketing budget / Ngân sách marketing/tháng | C38: VNĐ/tháng | D38: —
A39: Grand opening budget / Ngân sách khai trương | C39: VNĐ | D39: One-off
A40: Loyalty discount % / Giảm giá thành viên thân thiết | B40: 0.15 | C40: % | D40: — | E40: % discount on qualifying visits
A41: Loyalty member % of covers / % KH thành viên | B41: 0.05 | C41: % covers | D41: — | E41: % of covers receiving loyalty discount
A42: Promo campaign discount % / Giảm giá khuyến mại | B42: 0.2 | C42: % | D42: — | E42: Average discount for promotions
A43: Marketing growth YoY / Tăng ngân sách marketing | B43: 0.1 | C43: %/year | D43: YoY
A44: F. OVERHEAD RATIOS / TỶ LỆ CHI PHÍ CHUNG
A45: Contingency / Dự phòng phí (% opex) | B45: 0.02 | C45: % | D45: — | E45: Buffer on total operating cost
A46: Management fee / Phí quản lý (% opex) | B46: 0.03 | C46: % | D46: — | E46: HQ / owner management charge
A47: Other overhead / Chi phí khác (VNĐ/month) | C47: VNĐ/tháng | D47: —
A48: G. CAPITAL EXPENDITURE / CHI PHÍ ĐẦU TƯ
A49: Total capex / Tổng đầu tư | C49: VNĐ | D49: — | E49: From Investment Detail sheet
A50: Depreciation period / Thời gian khấu hao | B50: 36 | C50: months/tháng | D50: — | E50: Straight-line over 36 months
A51: Deposit paid / Đặt cọc mặt bằng | C51: VNĐ | D51: — | E51: Refundable at end of lease
A52: Working capital / Vốn lưu động | C52: VNĐ | D52: — | E52: Initial float; recovered at close
A53: Liquidation value / Giá trị thanh lý | C53: VNĐ | D53: — | E53: Estimated FF&E salvage value
A54: H. FINANCING / TÀI CHÍNH
A55: Equity contribution / Vốn chủ sở hữu | C55: VNĐ | D55: —
A56: Loan amount / Vốn vay | C56: VNĐ | D56: — | E56: → Also enter in Loan Schedule sheet
A57: Interest rate / Lãi suất vay | B57: 0.09 | C57: %/year | D57: — | E57: Annual interest rate
A58: Loan term / Thời hạn vay | B58: 36 | C58: months | D58: — | E58: Enter 12, 24, 36 or 60
A59: Grace period / Ân hạn | B59: 0 | C59: months | D59: — | E59: Interest-only months at start
A60: I. TAX / THUẾ
A61: Corporate income tax (CIT) / Thuế TNDN | B61: 0.2 | C61: % | D61: — | E61: 20% standard Vietnam CIT rate
A62: Tax holiday years / Miễn thuế số năm | B62: 2 | C62: years/năm | D62: — | E62: 0 if not applicable
A63: Tax reduction years / Giảm thuế số năm | B63: 2 | C63: years/năm | D63: — | E63: Years with 50% CIT reduction after holiday
A64: VAT rate / Thuế VAT | B64: 0.08 | C64: % | D64: — | E64: 8% F&B Vietnam 2024
A65: J. KPIs & BENCHMARKS / CHỈ TIÊU
A66: Target Food Cost % / Mục tiêu % chi phí TP | B66: 0.32 | C66: % | D66: —
A67: Target Gross Margin / Mục tiêu lợi nhuận gộp | B67: 0.45 | C67: % | D67: —
A68: Target EBITDA Margin | B68: 0.15 | C68: % | D68: —
A69: Target Payback / Mục tiêu hoàn vốn | B69: 24 | C69: months | D69: — | E69: Months to recover capex
A71: → Fill in all yellow cells above. The model will auto-populate all other sheets. / Điền vào tất cả ô nền vàng. Các trang khác sẽ tự động cập nhật.

Sheet 💰 Revenue
A1: REVENUE FORECAST / DỰ BÁO DOANH THU
D2: 1 | E2: 2 | F2: 3 | G2: 4 | H2: 5 | I2: 6 | J2: 7 | K2: 8 | L2: 9 | M2: 10 | N2: 11 | O2: 12 | P2: 13 | Q2: 14 | R2: 15 | S2: 16 | T2: 17 | U2: 18 | V2: 19 | W2: 20 | X2: 21 | Y2: 22 | Z2: 23 | AA2: 24 | AB2: 25 | AC2: 26 | AD2: 27 | AE2: 28 | AF2: 29 | AG2: 30 | AH2: 31 | AI2: 32 | AJ2: 33 | AK2: 34 | AL2: 35 | AM2: 36 | AN2: 37 | AO2: 38 | AP2: 39 | AQ2: 40 | AR2: 41 | AS2: 42 | AT2: 43 | AU2: 44 | AV2: 45 | AW2: 46 | AX2: 47 | AY2: 48 | AZ2: 49 | BA2: 50 | BB2: 51 | BC2: 52 | BD2: 53 | BE2: 54 | BF2: 55 | BG2: 56 | BH2: 57 | BI2: 58 | BJ2: 59
C3: =YEAR(C5)-YEAR('⚙️ Assumptions'!$B$6) + 1 -> 1 | D3: =YEAR(D5)-YEAR('⚙️ Assumptions'!$B$6) + 1 -> 1 | E3: =YEAR(E5)-YEAR('⚙️ Assumptions'!$B$6) + 1 -> 1 | F3: =YEAR(F5)-YEAR('⚙️ Assumptions'!$B$6) + 1 -> 2 | G3: =YEAR(G5)-YEAR('⚙️ Assumptions'!$B$6) + 1 -> 2 | H3: =YEAR(H5)-YEAR('⚙️ Assumptions'!$B$6) + 1 -> 2 | I3: =YEAR(I5)-YEAR('⚙️ Assumptions'!$B$6) + 1 -> 2 | J3: =YEAR(J5)-YEAR('⚙️ Assumptions'!$B$6) + 1 -> 2 | ... BJ3: =YEAR(BJ5)-YEAR('⚙️ Assumptions'!$B$6) + 1 -> 6
C4: 1 | D4: 2 | E4: 3 | F4: 4 | G4: 5 | H4: 6 | I4: 7 | J4: 8 | K4: 9 | L4: 10 | M4: 11 | N4: 12 | O4: 13 | P4: 14 | Q4: 15 | R4: 16 | S4: 17 | T4: 18 | U4: 19 | V4: 20 | W4: 21 | X4: 22 | Y4: 23 | Z4: 24 | AA4: 25 | AB4: 26 | AC4: 27 | AD4: 28 | AE4: 29 | AF4: 30 | AG4: 31 | AH4: 32 | AI4: 33 | AJ4: 34 | AK4: 35 | AL4: 36 | AM4: 37 | AN4: 38 | AO4: 39 | AP4: 40 | AQ4: 41 | AR4: 42 | AS4: 43 | AT4: 44 | AU4: 45 | AV4: 46 | AW4: 47 | AX4: 48 | AY4: 49 | AZ4: 50 | BA4: 51 | BB4: 52 | BC4: 53 | BD4: 54 | BE4: 55 | BF4: 56 | BG4: 57 | BH4: 58 | BI4: 59 | BJ4: 60
A5: LINE ITEM / CHỈ TIÊU | B5: 3-YEAR TOTAL / TỔNG 3 NĂM | C5: ='⚙️ Assumptions'!B6 -> 46661 | D5: =EDATE(C$5,$D$2) -> 46692 | E5: =EDATE($C$5,E2) -> 46722 | F5: =EDATE($C$5,F2) -> 46753 | G5: =EDATE($C$5,G2) -> 46784 | H5: =EDATE($C$5,H2) -> 46813 | I5: =EDATE($C$5,I2) -> 46844 | J5: =EDATE($C$5,J2) -> 46874 | K5: =EDATE($C$5,K2) -> 46905 | L5: =EDATE($C$5,L2) -> 46935 | ... BJ5: =EDATE($C$5,BJ2) -> 48458
A6: A. REVENUE DRIVERS / THÔNG SỐ DOANH THU
A7: Covers/day exclude seasonal index / Khách/ngày | B7: =AVERAGEA(C7:AL7) -> 144.16667 | C7: =_xlfn.LET( _xlpm.Ramp_up_Percentage, INDEX('⚙️ Other Assumptions'!$B$17:$Q$19,MATCH('⚙️ Assumptions'!$B$13,'⚙️ Other Assumptions'!$A$17:$A$19,0),MATCH(C4,'⚙️ Other Assumptions'!$B$14:$AI$14,0)), _xlpm.Default_max_val,INDEX('⚙️ Other Assumptions'!$B$24:$B$26,MATCH('⚙️ Assumptions'!$B$13,'⚙️ Other Assumptions'!$A$24:$A$26)), _xlpm.Expected_number_of_sales, '⚙️ Assumptions'!$B$12, IFERROR(_xlpm.Ramp_up_Percentage,_xlpm.Default_max_val)*_xlpm.Expected_number_of_sales) -> 0 | D7: =_xlfn.LET( _xlpm.Ramp_up_Percentage, INDEX('⚙️ Other Assumptions'!$B$17:$Q$19,MATCH('⚙️ Assumptions'!$B$13,'⚙️ Other Assumptions'!$A$17:$A$19,0),MATCH(D4,'⚙️ Other Assumptions'!$B$14:$AI$14,0)), _xlpm.Default_max_val,INDEX('⚙️ Other Assumptions'!$B$24:$B$26,MATCH('⚙️ Assumptions'!$B$13,'⚙️ Other Assumptions'!$A$24:$A$26)), _xlpm.Expected_number_of_sales, '⚙️ Assumptions'!$B$12, IFERROR(_xlpm.Ramp_up_Percentage,_xlpm.Default_max_val)*_xlpm.Expected_number_of_sales) -> 0 | E7: =_xlfn.LET( _xlpm.Ramp_up_Percentage, INDEX('⚙️ Other Assumptions'!$B$17:$Q$19,MATCH('⚙️ Assumptions'!$B$13,'⚙️ Other Assumptions'!$A$17:$A$19,0),MATCH(E4,'⚙️ Other Assumptions'!$B$14:$AI$14,0)), _xlpm.Default_max_val,INDEX('⚙️ Other Assumptions'!$B$24:$B$26,MATCH('⚙️ Assumptions'!$B$13,'⚙️ Other Assumptions'!$A$24:$A$26)), _xlpm.Expected_number_of_sales, '⚙️ Assumptions'!$B$12, IFERROR(_xlpm.Ramp_up_Percentage,_xlpm.Default_max_val)*_xlpm.Expected_number_of_sales) -> 45 | F7: =_xlfn.LET( _xlpm.Ramp_up_Percentage, INDEX('⚙️ Other Assumptions'!$B$17:$Q$19,MATCH('⚙️ Assumptions'!$B$13,'⚙️ Other Assumptions'!$A$17:$A$19,0),MATCH(F4,'⚙️ Other Assumptions'!$B$14:$AI$14,0)), _xlpm.Default_max_val,INDEX('⚙️ Other Assumptions'!$B$24:$B$26,MATCH('⚙️ Assumptions'!$B$13,'⚙️ Other Assumptions'!$A$24:$A$26)), _xlpm.Expected_number_of_sales, '⚙️ Assumptions'!$B$12, IFERROR(_xlpm.Ramp_up_Percentage,_xlpm.Default_max_val)*_xlpm.Expected_number_of_sales) -> 45 | G7: =_xlfn.LET( _xlpm.Ramp_up_Percentage, INDEX('⚙️ Other Assumptions'!$B$17:$Q$19,MATCH('⚙️ Assumptions'!$B$13,'⚙️ Other Assumptions'!$A$17:$A$19,0),MATCH(G4,'⚙️ Other Assumptions'!$B$14:$AI$14,0)), _xlpm.Default_max_val,INDEX('⚙️ Other Assumptions'!$B$24:$B$26,MATCH('⚙️ Assumptions'!$B$13,'⚙️ Other Assumptions'!$A$24:$A$26)), _xlpm.Expected_number_of_sales, '⚙️ Assumptions'!$B$12, IFERROR(_xlpm.Ramp_up_Percentage,_xlpm.Default_max_val)*_xlpm.Expected_number_of_sales) -> 75 | H7: =_xlfn.LET( _xlpm.Ramp_up_Percentage, INDEX('⚙️ Other Assumptions'!$B$17:$Q$19,MATCH('⚙️ Assumptions'!$B$13,'⚙️ Other Assumptions'!$A$17:$A$19,0),MATCH(H4,'⚙️ Other Assumptions'!$B$14:$AI$14,0)), _xlpm.Default_max_val,INDEX('⚙️ Other Assumptions'!$B$24:$B$26,MATCH('⚙️ Assumptions'!$B$13,'⚙️ Other Assumptions'!$A$24:$A$26)), _xlpm.Expected_number_of_sales, '⚙️ Assumptions'!$B$12, IFERROR(_xlpm.Ramp_up_Percentage,_xlpm.Default_max_val)*_xlpm.Expected_number_of_sales) -> 75 | I7: =_xlfn.LET( _xlpm.Ramp_up_Percentage, INDEX('⚙️ Other Assumptions'!$B$17:$Q$19,MATCH('⚙️ Assumptions'!$B$13,'⚙️ Other Assumptions'!$A$17:$A$19,0),MATCH(I4,'⚙️ Other Assumptions'!$B$14:$AI$14,0)), _xlpm.Default_max_val,INDEX('⚙️ Other Assumptions'!$B$24:$B$26,MATCH('⚙️ Assumptions'!$B$13,'⚙️ Other Assumptions'!$A$24:$A$26)), _xlpm.Expected_number_of_sales, '⚙️ Assumptions'!$B$12, IFERROR(_xlpm.Ramp_up_Percentage,_xlpm.Default_max_val)*_xlpm.Expected_number_of_sales) -> 112.5 | J7: =_xlfn.LET( _xlpm.Ramp_up_Percentage, INDEX('⚙️ Other Assumptions'!$B$17:$Q$19,MATCH('⚙️ Assumptions'!$B$13,'⚙️ Other Assumptions'!$A$17:$A$19,0),MATCH(J4,'⚙️ Other Assumptions'!$B$14:$AI$14,0)), _xlpm.Default_max_val,INDEX('⚙️ Other Assumptions'!$B$24:$B$26,MATCH('⚙️ Assumptions'!$B$13,'⚙️ Other Assumptions'!$A$24:$A$26)), _xlpm.Expected_number_of_sales, '⚙️ Assumptions'!$B$12, IFERROR(_xlpm.Ramp_up_Percentage,_xlpm.Default_max_val)*_xlpm.Expected_number_of_sales) -> 112.5 | ... BJ7: =_xlfn.LET( _xlpm.Ramp_up_Percentage, INDEX('⚙️ Other Assumptions'!$B$17:$Q$19,MATCH('⚙️ Assumptions'!$B$13,'⚙️ Other Assumptions'!$A$17:$A$19,0),MATCH(BJ4,'⚙️ Other Assumptions'!$B$14:$AI$14,0)), _xlpm.Default_max_val,INDEX('⚙️ Other Assumptions'!$B$24:$B$26,MATCH('⚙️ Assumptions'!$B$13,'⚙️ Other Assumptions'!$A$24:$A$26)), _xlpm.Expected_number_of_sales, '⚙️ Assumptions'!$B$12, IFERROR(_xlpm.Ramp_up_Percentage,_xlpm.Default_max_val)*_xlpm.Expected_number_of_sales) -> 180
A8: Operating days / Ngày hoạt động | B8: =AVERAGEA(C8:AL8) -> 30.444444 | C8: =DAY(DATE(YEAR(C5), MONTH(C5)+1, 0)) -> 31 | D8: =DAY(DATE(YEAR(D5), MONTH(D5)+1, 0)) -> 30 | E8: =DAY(DATE(YEAR(E5), MONTH(E5)+1, 0)) -> 31 | F8: =DAY(DATE(YEAR(F5), MONTH(F5)+1, 0)) -> 31 | G8: =DAY(DATE(YEAR(G5), MONTH(G5)+1, 0)) -> 29 | H8: =DAY(DATE(YEAR(H5), MONTH(H5)+1, 0)) -> 31 | I8: =DAY(DATE(YEAR(I5), MONTH(I5)+1, 0)) -> 30 | J8: =DAY(DATE(YEAR(J5), MONTH(J5)+1, 0)) -> 31 | ... BJ8: =DAY(DATE(YEAR(BJ5), MONTH(BJ5)+1, 0)) -> 30
A9: Seasonal index / Hệ số mùa vụ | B9: =SUM(C9:AL9) -> 38.1 | C9: =INDEX('⚙️ Other Assumptions'!$B$16:$M$16,MATCH(MONTH(C5),'⚙️ Other Assumptions'!$B$14:$M$14,0)) -> 0.95 | D9: =INDEX('⚙️ Other Assumptions'!$B$16:$M$16,MATCH(MONTH(D5),'⚙️ Other Assumptions'!$B$14:$M$14,0)) -> 1.05 | E9: =INDEX('⚙️ Other Assumptions'!$B$16:$M$16,MATCH(MONTH(E5),'⚙️ Other Assumptions'!$B$14:$M$14,0)) -> 1.2 | F9: =INDEX('⚙️ Other Assumptions'!$B$16:$M$16,MATCH(MONTH(F5),'⚙️ Other Assumptions'!$B$14:$M$14,0)) -> 1.2 | G9: =INDEX('⚙️ Other Assumptions'!$B$16:$M$16,MATCH(MONTH(G5),'⚙️ Other Assumptions'!$B$14:$M$14,0)) -> 0.85 | H9: =INDEX('⚙️ Other Assumptions'!$B$16:$M$16,MATCH(MONTH(H5),'⚙️ Other Assumptions'!$B$14:$M$14,0)) -> 0.95 | I9: =INDEX('⚙️ Other Assumptions'!$B$16:$M$16,MATCH(MONTH(I5),'⚙️ Other Assumptions'!$B$14:$M$14,0)) -> 1.15 | J9: =INDEX('⚙️ Other Assumptions'!$B$16:$M$16,MATCH(MONTH(J5),'⚙️ Other Assumptions'!$B$14:$M$14,0)) -> 1.05 | ... BJ9: =INDEX('⚙️ Other Assumptions'!$B$16:$M$16,MATCH(MONTH(BJ5),'⚙️ Other Assumptions'!$B$14:$M$14,0)) -> 0.95
A10: Avg spend/cover / Giá 1 xuất (VNĐ) | B10: =AVERAGEA(C10:AL10) -> 75000 | C10: 75000 | D10: 75000 | E10: 75000 | F10: 75000 | G10: 75000 | H10: 75000 | I10: 75000 | J10: 75000 | K10: 75000 | L10: 75000 | M10: 75000 | N10: 75000 | O10: 75000 | P10: 75000 | Q10: 75000 | R10: 75000 | S10: 75000 | T10: 75000 | U10: 75000 | V10: 75000 | W10: 75000 | X10: 75000 | Y10: 75000 | Z10: 75000 | AA10: 75000 | AB10: 75000 | AC10: 75000 | AD10: 75000 | AE10: 75000 | AF10: 75000 | AG10: 75000 | AH10: 75000 | AI10: 75000 | AJ10: 75000 | AK10: 75000 | AL10: 75000 | AM10: 75000 | AN10: 75000 | AO10: 75000 | AP10: 75000 | AQ10: 75000 | AR10: 75000 | AS10: 75000 | AT10: 75000 | AU10: 75000 | AV10: 75000 | AW10: 75000 | AX10: 75000 | AY10: 75000 | AZ10: 75000 | BA10: 75000 | BB10: 75000 | BC10: 75000 | BD10: 75000 | BE10: 75000 | BF10: 75000 | BG10: 75000 | BH10: 75000 | BI10: 75000 | BJ10: 75000
A11: Food revenue mix / Tỷ lệ DT thức ăn | B11: =AVERAGE(C11:AL11) -> 0.8 | C11: 0.8 | D11: 0.8 | E11: 0.8 | F11: 0.8 | G11: 0.8 | H11: 0.8 | I11: 0.8 | J11: 0.8 | K11: 0.8 | L11: 0.8 | M11: 0.8 | N11: 0.8 | O11: 0.8 | P11: 0.8 | Q11: 0.8 | R11: 0.8 | S11: 0.8 | T11: 0.8 | U11: 0.8 | V11: 0.8 | W11: 0.8 | X11: 0.8 | Y11: 0.8 | Z11: 0.8 | AA11: 0.8 | AB11: 0.8 | AC11: 0.8 | AD11: 0.8 | AE11: 0.8 | AF11: 0.8 | AG11: 0.8 | AH11: 0.8 | AI11: 0.8 | AJ11: 0.8 | AK11: 0.8 | AL11: 0.8 | AM11: 0.8 | AN11: 0.8 | AO11: 0.8 | AP11: 0.8 | AQ11: 0.8 | AR11: 0.8 | AS11: 0.8 | AT11: 0.8 | AU11: 0.8 | AV11: 0.8 | AW11: 0.8 | AX11: 0.8 | AY11: 0.8 | AZ11: 0.8 | BA11: 0.8 | BB11: 0.8 | BC11: 0.8 | BD11: 0.8 | BE11: 0.8 | BF11: 0.8 | BG11: 0.8 | BH11: 0.8 | BI11: 0.8 | BJ11: 0.8
A12: B. REVENUE CALCULATION / TÍNH DOANH THU
A13: Total covers / Tổng số suất ăn | B13: =AVERAGEA(C13:AL13) -> 4647.0625 | C13: =C7*C8*C9 -> 0 | D13: =D7*D8*D9 -> 0 | E13: =E7*E8*E9 -> 1674 | F13: =F7*F8*F9 -> 1674 | G13: =G7*G8*G9 -> 1848.75 | H13: =H7*H8*H9 -> 2208.75 | I13: =I7*I8*I9 -> 3881.25 | J13: =J7*J8*J9 -> 3661.875 | ... BJ13: =BJ7*BJ8*BJ9 -> 5130
A14: Gross Revenue / Doanh thu gộp (VNĐ) | B14: =SUM(C14:AL14) -> 12547068750 | C14: =_xlfn.LET( _xlpm.number_of_serves, C13, _xlpm.avg_spend, C10, _xlpm.avg_days_per_month,C8, _xlpm.number_of_serves*_xlpm.avg_spend) -> 0 | D14: =_xlfn.LET( _xlpm.number_of_serves, D13, _xlpm.avg_spend, D10, _xlpm.avg_days_per_month,D8, _xlpm.number_of_serves*_xlpm.avg_spend) -> 0 | E14: =_xlfn.LET( _xlpm.number_of_serves, E13, _xlpm.avg_spend, E10, _xlpm.avg_days_per_month,E8, _xlpm.number_of_serves*_xlpm.avg_spend) -> 125550000 | F14: =_xlfn.LET( _xlpm.number_of_serves, F13, _xlpm.avg_spend, F10, _xlpm.avg_days_per_month,F8, _xlpm.number_of_serves*_xlpm.avg_spend) -> 125550000 | G14: =_xlfn.LET( _xlpm.number_of_serves, G13, _xlpm.avg_spend, G10, _xlpm.avg_days_per_month,G8, _xlpm.number_of_serves*_xlpm.avg_spend) -> 138656250 | H14: =_xlfn.LET( _xlpm.number_of_serves, H13, _xlpm.avg_spend, H10, _xlpm.avg_days_per_month,H8, _xlpm.number_of_serves*_xlpm.avg_spend) -> 165656250 | I14: =_xlfn.LET( _xlpm.number_of_serves, I13, _xlpm.avg_spend, I10, _xlpm.avg_days_per_month,I8, _xlpm.number_of_serves*_xlpm.avg_spend) -> 291093750 | J14: =_xlfn.LET( _xlpm.number_of_serves, J13, _xlpm.avg_spend, J10, _xlpm.avg_days_per_month,J8, _xlpm.number_of_serves*_xlpm.avg_spend) -> 274640625 | ... BJ14: =_xlfn.LET( _xlpm.number_of_serves, BJ13, _xlpm.avg_spend, BJ10, _xlpm.avg_days_per_month,BJ8, _xlpm.number_of_serves*_xlpm.avg_spend) -> 384750000
A15: Food revenue / DT thức ăn (VNĐ) | B15: =SUM(C15:AL15) -> 10037655000 | C15: =C14*C11 -> 0 | D15: =D14*D11 -> 0 | E15: =E14*E11 -> 100440000 | F15: =F14*F11 -> 100440000 | G15: =G14*G11 -> 110925000 | H15: =H14*H11 -> 132525000 | I15: =I14*I11 -> 232875000 | J15: =J14*J11 -> 219712500 | ... BJ15: =BJ14*BJ11 -> 307800000
A16: Beverage revenue / DT đồ uống (VNĐ) | B16: =SUM(C16:AL16) -> 2509413750 | C16: =C14-C15 -> 0 | D16: =D14-D15 -> 0 | E16: =E14-E15 -> 25110000 | F16: =F14-F15 -> 25110000 | G16: =G14-G15 -> 27731250 | H16: =H14-H15 -> 33131250 | I16: =I14-I15 -> 58218750 | J16: =J14-J15 -> 54928125 | ... BJ16: =BJ14-BJ15 -> 76950000
A17: (-) Loyalty discount / Giảm giá thành viên (VNĐ) | B17: =SUM(C17:AL17) -> 0 | C17: =C14*0.15*0 -> 0 | D17: =D14*0.15*0 -> 0 | E17: =E14*0.15*0 -> 0 | F17: =F14*0.15*0 -> 0 | G17: =G14*0.15*0 -> 0 | H17: =H14*0.15*0 -> 0 | I17: =I14*0.15*0 -> 0 | J17: =J14*0.15*0 -> 0 | ... BJ17: =BJ14*0.15*0 -> 0
A18: (-) Promotion cost / Chi phí khuyến mại (VNĐ) | B18: =SUM(C18:AL18) -> 0
A19: NET REVENUE / DOANH THU THUẦN (VNĐ) | B19: =SUM(C19:AL19) -> 12547068750 | C19: =C14-C17-C18 -> 0 | D19: =D14-D17-D18 -> 0 | E19: =E14-E17-E18 -> 125550000 | F19: =F14-F17-F18 -> 125550000 | G19: =G14-G17-G18 -> 138656250 | H19: =H14-H17-H18 -> 165656250 | I19: =I14-I17-I18 -> 291093750 | J19: =J14-J17-J18 -> 274640625 | ... BJ19: =BJ14-BJ17-BJ18 -> 384750000
A20: C. ANNUAL SUMMARY / TÓM TẮT NĂM
A21: Year 1 Net Revenue / DT Thuần Năm 1 (VNĐ) | B21: =SUMIF($C$3:$BJ$3,1,$C$19:$BJ$19) -> 125550000
A22: Year 2 Net Revenue / DT Thuần Năm 2 (VNĐ) | B22: =SUMIF($C$3:$BJ$3,2,$C$19:$BJ$19) -> 3386643750
A23: Year 3 Net Revenue / DT Thuần Năm 3 (VNĐ) | B23: =SUMIF($C$3:$BJ$3,3,$C$19:$BJ$19) -> 5138100000
A24: Year 4 Net Revenue / DT Thuần Năm 4 (VNĐ) | B24: =SUMIF($C$3:$BJ$3,4,$C$19:$BJ$19) -> 5221800000
A25: Year 5 Net Revenue / DT Thuần Năm 5 (VNĐ) | B25: =SUMIF($C$3:$BJ$3,5,$C$19:$BJ$19) -> 5221800000
A26: D. PROJECT CLOSE-OUT / THU HỒI CUỐI DỰ ÁN
A27: Working capital recovery + Deposit + Liquidation (VNĐ) | B27: =SUM(C27:AL27) -> 0
A28: TOTAL REVENUE incl. close-out / TỔNG DT (VNĐ) | B28: =SUM(C28:AL28) -> 12547068750 | C28: =C19+C27 -> 0 | D28: =D19+D27 -> 0 | E28: =E19+E27 -> 125550000 | F28: =F19+F27 -> 125550000 | G28: =G19+G27 -> 138656250 | H28: =H19+H27 -> 165656250 | I28: =I19+I27 -> 291093750 | J28: =J19+J27 -> 274640625 | ... AL28: =AL19+AL27 -> 384750000

Sheet 📦 COGS & OpEx
A1: COGS & OPERATING COST FORECAST / CHI PHÍ HOẠT ĐỘNG
B2: TOTAL / TỔNG | C2: YEAR 1 / NĂM 1 | O2: YEAR 2 / NĂM 2 | AA2: YEAR 3 / NĂM 3
A3: LINE ITEM / CHỈ TIÊU | B3: 5-YEAR TOTAL / TỔNG 5 NĂM | C3: ='⚙️ Assumptions'!B6 -> 46661 | D3: =EDATE($C$3,'💰 Revenue'!D2) -> 46692 | E3: =EDATE($C$3,'💰 Revenue'!E2) -> 46722 | F3: =EDATE($C$3,'💰 Revenue'!F2) -> 46753 | G3: =EDATE($C$3,'💰 Revenue'!G2) -> 46784 | H3: =EDATE($C$3,'💰 Revenue'!H2) -> 46813 | I3: =EDATE($C$3,'💰 Revenue'!I2) -> 46844 | J3: =EDATE($C$3,'💰 Revenue'!J2) -> 46874 | K3: =EDATE($C$3,'💰 Revenue'!K2) -> 46905 | ... BJ3: =EDATE($C$3,'💰 Revenue'!BJ2) -> 48458
A4: A. COST OF GOODS SOLD / GIÁ VỐN HÀNG BÁN
A5: Raw Material % per Rev /Tỷ lệ NVL trên doanh thu | B5: =AVERAGEA(C5:AL5) -> 0.31166667 | C5: =_xlfn.IFNA(INDEX('⚙️ Assumptions'!$B$39:$F$39,MATCH(YEAR(C3),'⚙️ Assumptions'!$B$38:$F$38,0)),OFFSET(C5,,-1)) -> 0.35 | D5: =_xlfn.IFNA(INDEX('⚙️ Assumptions'!$B$39:$F$39,MATCH(YEAR(D3),'⚙️ Assumptions'!$B$38:$F$38,0)),OFFSET(D5,,-1)) -> 0.35 | E5: =_xlfn.IFNA(INDEX('⚙️ Assumptions'!$B$39:$F$39,MATCH(YEAR(E3),'⚙️ Assumptions'!$B$38:$F$38,0)),OFFSET(E5,,-1)) -> 0.35 | F5: =_xlfn.IFNA(INDEX('⚙️ Assumptions'!$B$39:$F$39,MATCH(YEAR(F3),'⚙️ Assumptions'!$B$38:$F$38,0)),OFFSET(F5,,-1)) -> 0.33 | G5: =_xlfn.IFNA(INDEX('⚙️ Assumptions'!$B$39:$F$39,MATCH(YEAR(G3),'⚙️ Assumptions'!$B$38:$F$38,0)),OFFSET(G5,,-1)) -> 0.33 | H5: =_xlfn.IFNA(INDEX('⚙️ Assumptions'!$B$39:$F$39,MATCH(YEAR(H3),'⚙️ Assumptions'!$B$38:$F$38,0)),OFFSET(H5,,-1)) -> 0.33 | I5: =_xlfn.IFNA(INDEX('⚙️ Assumptions'!$B$39:$F$39,MATCH(YEAR(I3),'⚙️ Assumptions'!$B$38:$F$38,0)),OFFSET(I5,,-1)) -> 0.33 | J5: =_xlfn.IFNA(INDEX('⚙️ Assumptions'!$B$39:$F$39,MATCH(YEAR(J3),'⚙️ Assumptions'!$B$38:$F$38,0)),OFFSET(J5,,-1)) -> 0.33 | ... BJ5: =_xlfn.IFNA(INDEX('⚙️ Assumptions'!$B$39:$F$39,MATCH(YEAR(BJ3),'⚙️ Assumptions'!$B$38:$F$38,0)),OFFSET(BJ5,,-1)) -> 0.29
A6: Raw Material / Giá vốn | B6: =SUM(C6:AL6) -> 3066423750 | C6: ='💰 Revenue'!C15*C5 -> 0 | D6: ='💰 Revenue'!D15*D5 -> 0 | E6: ='💰 Revenue'!E15*E5 -> 35154000 | F6: ='💰 Revenue'!F15*F5 -> 33145200 | G6: ='💰 Revenue'!G15*G5 -> 36605250 | H6: ='💰 Revenue'!H15*H5 -> 43733250 | I6: ='💰 Revenue'!I15*I5 -> 76848750 | J6: ='💰 Revenue'!J15*J5 -> 72505125 | ... BJ6: ='💰 Revenue'!BJ15*BJ5 -> 89262000
A7: TOTAL COGS / TỔNG GIÁ VỐN (VNĐ) | B7: =SUM(C7:AL7) -> 3066423750 | C7: =C6 -> 0 | D7: =D6 -> 0 | E7: =E6 -> 35154000 | F7: =F6 -> 33145200 | G7: =G6 -> 36605250 | H7: =H6 -> 43733250 | I7: =I6 -> 76848750 | J7: =J6 -> 72505125 | ... BJ7: =BJ6 -> 89262000
A8: B. FIXED OPERATING COSTS / CHI PHÍ CỐ ĐỊNH
A9: Rent / Thuê mặt bằng (VNĐ) | B9: =SUM(C9:AL9) -> 2070000000 | C9: ='⚙️ Assumptions'!$B$10 -> 57500000 | D9: ='⚙️ Assumptions'!$B$10 -> 57500000 | E9: ='⚙️ Assumptions'!$B$10 -> 57500000 | F9: ='⚙️ Assumptions'!$B$10 -> 57500000 | G9: ='⚙️ Assumptions'!$B$10 -> 57500000 | H9: ='⚙️ Assumptions'!$B$10 -> 57500000 | I9: ='⚙️ Assumptions'!$B$10 -> 57500000 | J9: ='⚙️ Assumptions'!$B$10 -> 57500000 | ... BJ9: ='⚙️ Assumptions'!$B$10 -> 57500000
A10: Utilities / Điện nước (VNĐ): | B10: =SUM(C10:AL10) -> 7.8973622e+08 | C10: =_xlfn.LET( _xlpm.Electric, C11, _xlpm.Water, C13, _xlpm.Electric + _xlpm.Water) -> 0 | D10: =_xlfn.LET( _xlpm.Electric, D11, _xlpm.Water, D13, _xlpm.Electric + _xlpm.Water) -> 0 | E10: =_xlfn.LET( _xlpm.Electric, E11, _xlpm.Water, E13, _xlpm.Electric + _xlpm.Water) -> 6403050 | F10: =_xlfn.LET( _xlpm.Electric, F11, _xlpm.Water, F13, _xlpm.Electric + _xlpm.Water) -> 6403050 | G10: =_xlfn.LET( _xlpm.Electric, G11, _xlpm.Water, G13, _xlpm.Electric + _xlpm.Water) -> 7626093.8 | H10: =_xlfn.LET( _xlpm.Electric, H11, _xlpm.Water, H13, _xlpm.Electric + _xlpm.Water) -> 9111093.8 | I10: =_xlfn.LET( _xlpm.Electric, I11, _xlpm.Water, I13, _xlpm.Electric + _xlpm.Water) -> 16010156 | J10: =_xlfn.LET( _xlpm.Electric, J11, _xlpm.Water, J13, _xlpm.Electric + _xlpm.Water) -> 15105234 | ... BJ10: =_xlfn.LET( _xlpm.Electric, BJ11, _xlpm.Water, BJ13, _xlpm.Electric + _xlpm.Water) -> 26547750
A11: - Tiền điện | B11: =SUM(C11:AL11) -> 6.0153019e+08 | C11: =_xlfn.LET( _xlpm.Electric_percent, _xlfn.IFNA(INDEX('⚙️ Assumptions'!$B$40:$F$40,MATCH(YEAR(C3),'⚙️ Assumptions'!$B$38:$F$38,0)),C12), _xlpm.Rev, INDEX('💰 Revenue'!$C$14:$BJ14,MATCH(C3,'💰 Revenue'!$C$5:$BJ$5,0)), _xlpm.Adj_ratio, INDEX('⚙️ Other Assumptions'!$B$15:$M$15,MATCH(MONTH(C3),'⚙️ Other Assumptions'!$B$14:$M$14)), _xlpm.Electric_percent * _xlpm.Rev * _xlpm.Adj_ratio) -> 0 | D11: =_xlfn.LET( _xlpm.Electric_percent, _xlfn.IFNA(INDEX('⚙️ Assumptions'!$B$40:$F$40,MATCH(YEAR(D3),'⚙️ Assumptions'!$B$38:$F$38,0)),D12), _xlpm.Rev, INDEX('💰 Revenue'!$C$14:$BJ14,MATCH(D3,'💰 Revenue'!$C$5:$BJ$5,0)), _xlpm.Adj_ratio, INDEX('⚙️ Other Assumptions'!$B$15:$M$15,MATCH(MONTH(D3),'⚙️ Other Assumptions'!$B$14:$M$14)), _xlpm.Electric_percent * _xlpm.Rev * _xlpm.Adj_ratio) -> 0 | E11: =_xlfn.LET( _xlpm.Electric_percent, _xlfn.IFNA(INDEX('⚙️ Assumptions'!$B$40:$F$40,MATCH(YEAR(E3),'⚙️ Assumptions'!$B$38:$F$38,0)),E12), _xlpm.Rev, INDEX('💰 Revenue'!$C$14:$BJ14,MATCH(E3,'💰 Revenue'!$C$5:$BJ$5,0)), _xlpm.Adj_ratio, INDEX('⚙️ Other Assumptions'!$B$15:$M$15,MATCH(MONTH(E3),'⚙️ Other Assumptions'!$B$14:$M$14)), _xlpm.Electric_percent * _xlpm.Rev * _xlpm.Adj_ratio) -> 4519800 | F11: =_xlfn.LET( _xlpm.Electric_percent, _xlfn.IFNA(INDEX('⚙️ Assumptions'!$B$40:$F$40,MATCH(YEAR(F3),'⚙️ Assumptions'!$B$38:$F$38,0)),F12), _xlpm.Rev, INDEX('💰 Revenue'!$C$14:$BJ14,MATCH(F3,'💰 Revenue'!$C$5:$BJ$5,0)), _xlpm.Adj_ratio, INDEX('⚙️ Other Assumptions'!$B$15:$M$15,MATCH(MONTH(F3),'⚙️ Other Assumptions'!$B$14:$M$14)), _xlpm.Electric_percent * _xlpm.Rev * _xlpm.Adj_ratio) -> 4519800 | G11: =_xlfn.LET( _xlpm.Electric_percent, _xlfn.IFNA(INDEX('⚙️ Assumptions'!$B$40:$F$40,MATCH(YEAR(G3),'⚙️ Assumptions'!$B$38:$F$38,0)),G12), _xlpm.Rev, INDEX('💰 Revenue'!$C$14:$BJ14,MATCH(G3,'💰 Revenue'!$C$5:$BJ$5,0)), _xlpm.Adj_ratio, INDEX('⚙️ Other Assumptions'!$B$15:$M$15,MATCH(MONTH(G3),'⚙️ Other Assumptions'!$B$14:$M$14)), _xlpm.Electric_percent * _xlpm.Rev * _xlpm.Adj_ratio) -> 5546250 | H11: =_xlfn.LET( _xlpm.Electric_percent, _xlfn.IFNA(INDEX('⚙️ Assumptions'!$B$40:$F$40,MATCH(YEAR(H3),'⚙️ Assumptions'!$B$38:$F$38,0)),H12), _xlpm.Rev, INDEX('💰 Revenue'!$C$14:$BJ14,MATCH(H3,'💰 Revenue'!$C$5:$BJ$5,0)), _xlpm.Adj_ratio, INDEX('⚙️ Other Assumptions'!$B$15:$M$15,MATCH(MONTH(H3),'⚙️ Other Assumptions'!$B$14:$M$14)), _xlpm.Electric_percent * _xlpm.Rev * _xlpm.Adj_ratio) -> 6626250 | I11: =_xlfn.LET( _xlpm.Electric_percent, _xlfn.IFNA(INDEX('⚙️ Assumptions'!$B$40:$F$40,MATCH(YEAR(I3),'⚙️ Assumptions'!$B$38:$F$38,0)),I12), _xlpm.Rev, INDEX('💰 Revenue'!$C$14:$BJ14,MATCH(I3,'💰 Revenue'!$C$5:$BJ$5,0)), _xlpm.Adj_ratio, INDEX('⚙️ Other Assumptions'!$B$15:$M$15,MATCH(MONTH(I3),'⚙️ Other Assumptions'!$B$14:$M$14)), _xlpm.Electric_percent * _xlpm.Rev * _xlpm.Adj_ratio) -> 11643750 | J11: =_xlfn.LET( _xlpm.Electric_percent, _xlfn.IFNA(INDEX('⚙️ Assumptions'!$B$40:$F$40,MATCH(YEAR(J3),'⚙️ Assumptions'!$B$38:$F$38,0)),J12), _xlpm.Rev, INDEX('💰 Revenue'!$C$14:$BJ14,MATCH(J3,'💰 Revenue'!$C$5:$BJ$5,0)), _xlpm.Adj_ratio, INDEX('⚙️ Other Assumptions'!$B$15:$M$15,MATCH(MONTH(J3),'⚙️ Other Assumptions'!$B$14:$M$14)), _xlpm.Electric_percent * _xlpm.Rev * _xlpm.Adj_ratio) -> 10985625 | ... BJ11: =_xlfn.LET( _xlpm.Electric_percent, _xlfn.IFNA(INDEX('⚙️ Assumptions'!$B$40:$F$40,MATCH(YEAR(BJ3),'⚙️ Assumptions'!$B$38:$F$38,0)),BJ12), _xlpm.Rev, INDEX('💰 Revenue'!$C$14:$BJ14,MATCH(BJ3,'💰 Revenue'!$C$5:$BJ$5,0)), _xlpm.Adj_ratio, INDEX('⚙️ Other Assumptions'!$B$15:$M$15,MATCH(MONTH(BJ3),'⚙️ Other Assumptions'!$B$14:$M$14)), _xlpm.Electric_percent * _xlpm.Rev * _xlpm.Adj_ratio) -> 20776500
A12: Tiền điện/ doanh thu | C12: =IF(_xlfn.IFNA(INDEX('⚙️ Assumptions'!$B$40:$F$40,MATCH(YEAR(C3),'⚙️ Assumptions'!$B$38:$F$38,0)),1)<>1,C11/INDEX('💰 Revenue'!$C$14:$BJ14,MATCH(C3,'💰 Revenue'!$C$5:$BJ$5,0)),OFFSET(C12,,-1)) -> #DIV/0! | D12: =IF(_xlfn.IFNA(INDEX('⚙️ Assumptions'!$B$40:$F$40,MATCH(YEAR(D3),'⚙️ Assumptions'!$B$38:$F$38,0)),1)<>1,D11/INDEX('💰 Revenue'!$C$14:$BJ14,MATCH(D3,'💰 Revenue'!$C$5:$BJ$5,0)),OFFSET(D12,,-1)) -> #DIV/0! | E12: =IF(_xlfn.IFNA(INDEX('⚙️ Assumptions'!$B$40:$F$40,MATCH(YEAR(E3),'⚙️ Assumptions'!$B$38:$F$38,0)),1)<>1,E11/INDEX('💰 Revenue'!$C$14:$BJ14,MATCH(E3,'💰 Revenue'!$C$5:$BJ$5,0)),OFFSET(E12,,-1)) -> 0.036 | F12: =IF(_xlfn.IFNA(INDEX('⚙️ Assumptions'!$B$40:$F$40,MATCH(YEAR(F3),'⚙️ Assumptions'!$B$38:$F$38,0)),1)<>1,F11/INDEX('💰 Revenue'!$C$14:$BJ14,MATCH(F3,'💰 Revenue'!$C$5:$BJ$5,0)),OFFSET(F12,,-1)) -> 0.036 | G12: =IF(_xlfn.IFNA(INDEX('⚙️ Assumptions'!$B$40:$F$40,MATCH(YEAR(G3),'⚙️ Assumptions'!$B$38:$F$38,0)),1)<>1,G11/INDEX('💰 Revenue'!$C$14:$BJ14,MATCH(G3,'💰 Revenue'!$C$5:$BJ$5,0)),OFFSET(G12,,-1)) -> 0.04 | H12: =IF(_xlfn.IFNA(INDEX('⚙️ Assumptions'!$B$40:$F$40,MATCH(YEAR(H3),'⚙️ Assumptions'!$B$38:$F$38,0)),1)<>1,H11/INDEX('💰 Revenue'!$C$14:$BJ14,MATCH(H3,'💰 Revenue'!$C$5:$BJ$5,0)),OFFSET(H12,,-1)) -> 0.04 | I12: =IF(_xlfn.IFNA(INDEX('⚙️ Assumptions'!$B$40:$F$40,MATCH(YEAR(I3),'⚙️ Assumptions'!$B$38:$F$38,0)),1)<>1,I11/INDEX('💰 Revenue'!$C$14:$BJ14,MATCH(I3,'💰 Revenue'!$C$5:$BJ$5,0)),OFFSET(I12,,-1)) -> 0.04 | J12: =IF(_xlfn.IFNA(INDEX('⚙️ Assumptions'!$B$40:$F$40,MATCH(YEAR(J3),'⚙️ Assumptions'!$B$38:$F$38,0)),1)<>1,J11/INDEX('💰 Revenue'!$C$14:$BJ14,MATCH(J3,'💰 Revenue'!$C$5:$BJ$5,0)),OFFSET(J12,,-1)) -> 0.04 | ... BJ12: =IF(_xlfn.IFNA(INDEX('⚙️ Assumptions'!$B$40:$F$40,MATCH(YEAR(BJ3),'⚙️ Assumptions'!$B$38:$F$38,0)),1)<>1,BJ11/INDEX('💰 Revenue'!$C$14:$BJ14,MATCH(BJ3,'💰 Revenue'!$C$5:$BJ$5,0)),OFFSET(BJ12,,-1)) -> 0.036
A13: - Tiền nước | B13: =SUM(C13:AL13) -> 1.8820603e+08 | C13: =_xlfn.LET( _xlpm.Water_percent,_xlfn.IFNA(INDEX('⚙️ Assumptions'!$B$41:$F$41,MATCH(YEAR(C3),'⚙️ Assumptions'!$B$38:$F$38,0)),OFFSET(C14,,-1)), _xlpm.rev,INDEX('💰 Revenue'!$C$14:$BJ$14,MATCH(C3,'💰 Revenue'!$C$5:$BJ$5,0)), _xlpm.Water_percent*_xlpm.rev) -> 0 | D13: =_xlfn.LET(_xlpm.Water_percent,_xlfn.IFNA(INDEX('⚙️ Assumptions'!$B$41:$F$41,MATCH(YEAR(D3),'⚙️ Assumptions'!$B$38:$F$38,0)),OFFSET(D14,,-1)),_xlpm.rev,INDEX('💰 Revenue'!$C$14:$BJ$14,MATCH(D3,'💰 Revenue'!$C$5:$BJ$5,0)),_xlpm.Water_percent*_xlpm.rev) -> 0 | E13: =_xlfn.LET(_xlpm.Water_percent,_xlfn.IFNA(INDEX('⚙️ Assumptions'!$B$41:$F$41,MATCH(YEAR(E3),'⚙️ Assumptions'!$B$38:$F$38,0)),OFFSET(E14,,-1)),_xlpm.rev,INDEX('💰 Revenue'!$C$14:$BJ$14,MATCH(E3,'💰 Revenue'!$C$5:$BJ$5,0)),_xlpm.Water_percent*_xlpm.rev) -> 1883250 | F13: =_xlfn.LET(_xlpm.Water_percent,_xlfn.IFNA(INDEX('⚙️ Assumptions'!$B$41:$F$41,MATCH(YEAR(F3),'⚙️ Assumptions'!$B$38:$F$38,0)),OFFSET(F14,,-1)),_xlpm.rev,INDEX('💰 Revenue'!$C$14:$BJ$14,MATCH(F3,'💰 Revenue'!$C$5:$BJ$5,0)),_xlpm.Water_percent*_xlpm.rev) -> 1883250 | G13: =_xlfn.LET(_xlpm.Water_percent,_xlfn.IFNA(INDEX('⚙️ Assumptions'!$B$41:$F$41,MATCH(YEAR(G3),'⚙️ Assumptions'!$B$38:$F$38,0)),OFFSET(G14,,-1)),_xlpm.rev,INDEX('💰 Revenue'!$C$14:$BJ$14,MATCH(G3,'💰 Revenue'!$C$5:$BJ$5,0)),_xlpm.Water_percent*_xlpm.rev) -> 2079843.8 | H13: =_xlfn.LET(_xlpm.Water_percent,_xlfn.IFNA(INDEX('⚙️ Assumptions'!$B$41:$F$41,MATCH(YEAR(H3),'⚙️ Assumptions'!$B$38:$F$38,0)),OFFSET(H14,,-1)),_xlpm.rev,INDEX('💰 Revenue'!$C$14:$BJ$14,MATCH(H3,'💰 Revenue'!$C$5:$BJ$5,0)),_xlpm.Water_percent*_xlpm.rev) -> 2484843.8 | I13: =_xlfn.LET(_xlpm.Water_percent,_xlfn.IFNA(INDEX('⚙️ Assumptions'!$B$41:$F$41,MATCH(YEAR(I3),'⚙️ Assumptions'!$B$38:$F$38,0)),OFFSET(I14,,-1)),_xlpm.rev,INDEX('💰 Revenue'!$C$14:$BJ$14,MATCH(I3,'💰 Revenue'!$C$5:$BJ$5,0)),_xlpm.Water_percent*_xlpm.rev) -> 4366406.2 | J13: =_xlfn.LET(_xlpm.Water_percent,_xlfn.IFNA(INDEX('⚙️ Assumptions'!$B$41:$F$41,MATCH(YEAR(J3),'⚙️ Assumptions'!$B$38:$F$38,0)),OFFSET(J14,,-1)),_xlpm.rev,INDEX('💰 Revenue'!$C$14:$BJ$14,MATCH(J3,'💰 Revenue'!$C$5:$BJ$5,0)),_xlpm.Water_percent*_xlpm.rev) -> 4119609.4 | K13: =_xlfn.LET(_xlpm.Water_percent,_xlfn.IFNA(INDEX('⚙️ Assumptions'!$B$41:$F$41,MATCH(YEAR(K3),'⚙️ Assumptions'!$B$38:$F$38,0)),OFFSET(K14,,-1)),_xlpm.rev,INDEX('💰 Revenue'!$C$14:$BJ$14,MATCH(K3,'💰 Revenue'!$C$5:$BJ$5,0)),_xlpm.Water_percent*_xlpm.rev) -> 4860000 | ... BJ13: =_xlfn.LET(_xlpm.Water_percent,_xlfn.IFNA(INDEX('⚙️ Assumptions'!$B$41:$F$41,MATCH(YEAR(BJ3),'⚙️ Assumptions'!$B$38:$F$38,0)),OFFSET(BJ14,,-1)),_xlpm.rev,INDEX('💰 Revenue'!$C$14:$BJ$14,MATCH(BJ3,'💰 Revenue'!$C$5:$BJ$5,0)),_xlpm.Water_percent*_xlpm.rev) -> 5771250
A14: Tiền nước/ doanh thu | C14: =IF(_xlfn.IFNA(INDEX('⚙️ Assumptions'!$B$40:$F$40,MATCH(YEAR(C3),'⚙️ Assumptions'!$B$38:$F$38,0)),1)<>1,C13/INDEX('💰 Revenue'!$C$14:$BJ14,MATCH(C3,'💰 Revenue'!$C$5:$BJ$5,0)),OFFSET(C14,,-1)) -> #DIV/0! | D14: =IF(_xlfn.IFNA(INDEX('⚙️ Assumptions'!$B$40:$F$40,MATCH(YEAR(D3),'⚙️ Assumptions'!$B$38:$F$38,0)),1)<>1,D13/INDEX('💰 Revenue'!$C$14:$BJ14,MATCH(D3,'💰 Revenue'!$C$5:$BJ$5,0)),OFFSET(D14,,-1)) -> #DIV/0! | E14: =IF(_xlfn.IFNA(INDEX('⚙️ Assumptions'!$B$40:$F$40,MATCH(YEAR(E3),'⚙️ Assumptions'!$B$38:$F$38,0)),1)<>1,E13/INDEX('💰 Revenue'!$C$14:$BJ14,MATCH(E3,'💰 Revenue'!$C$5:$BJ$5,0)),OFFSET(E14,,-1)) -> 0.015 | F14: =IF(_xlfn.IFNA(INDEX('⚙️ Assumptions'!$B$40:$F$40,MATCH(YEAR(F3),'⚙️ Assumptions'!$B$38:$F$38,0)),1)<>1,F13/INDEX('💰 Revenue'!$C$14:$BJ14,MATCH(F3,'💰 Revenue'!$C$5:$BJ$5,0)),OFFSET(F14,,-1)) -> 0.015 | G14: =IF(_xlfn.IFNA(INDEX('⚙️ Assumptions'!$B$40:$F$40,MATCH(YEAR(G3),'⚙️ Assumptions'!$B$38:$F$38,0)),1)<>1,G13/INDEX('💰 Revenue'!$C$14:$BJ14,MATCH(G3,'💰 Revenue'!$C$5:$BJ$5,0)),OFFSET(G14,,-1)) -> 0.015 | H14: =IF(_xlfn.IFNA(INDEX('⚙️ Assumptions'!$B$40:$F$40,MATCH(YEAR(H3),'⚙️ Assumptions'!$B$38:$F$38,0)),1)<>1,H13/INDEX('💰 Revenue'!$C$14:$BJ14,MATCH(H3,'💰 Revenue'!$C$5:$BJ$5,0)),OFFSET(H14,,-1)) -> 0.015 | I14: =IF(_xlfn.IFNA(INDEX('⚙️ Assumptions'!$B$40:$F$40,MATCH(YEAR(I3),'⚙️ Assumptions'!$B$38:$F$38,0)),1)<>1,I13/INDEX('💰 Revenue'!$C$14:$BJ14,MATCH(I3,'💰 Revenue'!$C$5:$BJ$5,0)),OFFSET(I14,,-1)) -> 0.015 | J14: =IF(_xlfn.IFNA(INDEX('⚙️ Assumptions'!$B$40:$F$40,MATCH(YEAR(J3),'⚙️ Assumptions'!$B$38:$F$38,0)),1)<>1,J13/INDEX('💰 Revenue'!$C$14:$BJ14,MATCH(J3,'💰 Revenue'!$C$5:$BJ$5,0)),OFFSET(J14,,-1)) -> 0.015 | ... BJ14: =IF(_xlfn.IFNA(INDEX('⚙️ Assumptions'!$B$40:$F$40,MATCH(YEAR(BJ3),'⚙️ Assumptions'!$B$38:$F$38,0)),1)<>1,BJ13/INDEX('💰 Revenue'!$C$14:$BJ14,MATCH(BJ3,'💰 Revenue'!$C$5:$BJ$5,0)),OFFSET(BJ14,,-1)) -> 0.015
A15: Maintainace / Sửa chữa (VNĐ) | B15: =SUM(C15:AL15) -> 3.0616819e+08 | C15: =_xlfn.LET( _xlpm.Maintainance_ratio,_xlfn.IFNA(INDEX('⚙️ Assumptions'!$B$42:$F$42,MATCH(YEAR(C3),'⚙️ Assumptions'!$B$38:F$38,0)),OFFSET(C16,,-1)), _xlpm.rev,INDEX('💰 Revenue'!$C$14:$BJ$14,MATCH(C3,'💰 Revenue'!$C$5:$BJ$5,0)), _xlpm.Maintainance_ratio*_xlpm.rev) -> 0 | D15: =_xlfn.LET(_xlpm.Maintainance_ratio,_xlfn.IFNA(INDEX('⚙️ Assumptions'!$B$42:$F$42,MATCH(YEAR(D3),'⚙️ Assumptions'!$B$38:G$38,0)),OFFSET(D16,,-1)),_xlpm.rev,INDEX('💰 Revenue'!$C$14:$BJ$14,MATCH(D3,'💰 Revenue'!$C$5:$BJ$5,0)),_xlpm.Maintainance_ratio*_xlpm.rev) -> 0 | E15: =_xlfn.LET(_xlpm.Maintainance_ratio,_xlfn.IFNA(INDEX('⚙️ Assumptions'!$B$42:$F$42,MATCH(YEAR(E3),'⚙️ Assumptions'!$B$38:H$38,0)),OFFSET(E16,,-1)),_xlpm.rev,INDEX('💰 Revenue'!$C$14:$BJ$14,MATCH(E3,'💰 Revenue'!$C$5:$BJ$5,0)),_xlpm.Maintainance_ratio*_xlpm.rev) -> 1255500 | F15: =_xlfn.LET(_xlpm.Maintainance_ratio,_xlfn.IFNA(INDEX('⚙️ Assumptions'!$B$42:$F$42,MATCH(YEAR(F3),'⚙️ Assumptions'!$B$38:I$38,0)),OFFSET(F16,,-1)),_xlpm.rev,INDEX('💰 Revenue'!$C$14:$BJ$14,MATCH(F3,'💰 Revenue'!$C$5:$BJ$5,0)),_xlpm.Maintainance_ratio*_xlpm.rev) -> 1255500 | G15: =_xlfn.LET(_xlpm.Maintainance_ratio,_xlfn.IFNA(INDEX('⚙️ Assumptions'!$B$42:$F$42,MATCH(YEAR(G3),'⚙️ Assumptions'!$B$38:J$38,0)),OFFSET(G16,,-1)),_xlpm.rev,INDEX('💰 Revenue'!$C$14:$BJ$14,MATCH(G3,'💰 Revenue'!$C$5:$BJ$5,0)),_xlpm.Maintainance_ratio*_xlpm.rev) -> 1386562.5 | H15: =_xlfn.LET(_xlpm.Maintainance_ratio,_xlfn.IFNA(INDEX('⚙️ Assumptions'!$B$42:$F$42,MATCH(YEAR(H3),'⚙️ Assumptions'!$B$38:K$38,0)),OFFSET(H16,,-1)),_xlpm.rev,INDEX('💰 Revenue'!$C$14:$BJ$14,MATCH(H3,'💰 Revenue'!$C$5:$BJ$5,0)),_xlpm.Maintainance_ratio*_xlpm.rev) -> 1656562.5 | I15: =_xlfn.LET(_xlpm.Maintainance_ratio,_xlfn.IFNA(INDEX('⚙️ Assumptions'!$B$42:$F$42,MATCH(YEAR(I3),'⚙️ Assumptions'!$B$38:L$38,0)),OFFSET(I16,,-1)),_xlpm.rev,INDEX('💰 Revenue'!$C$14:$BJ$14,MATCH(I3,'💰 Revenue'!$C$5:$BJ$5,0)),_xlpm.Maintainance_ratio*_xlpm.rev) -> 2910937.5 | J15: =_xlfn.LET(_xlpm.Maintainance_ratio,_xlfn.IFNA(INDEX('⚙️ Assumptions'!$B$42:$F$42,MATCH(YEAR(J3),'⚙️ Assumptions'!$B$38:M$38,0)),OFFSET(J16,,-1)),_xlpm.rev,INDEX('💰 Revenue'!$C$14:$BJ$14,MATCH(J3,'💰 Revenue'!$C$5:$BJ$5,0)),_xlpm.Maintainance_ratio*_xlpm.rev) -> 2746406.2 | K15: =_xlfn.LET(_xlpm.Maintainance_ratio,_xlfn.IFNA(INDEX('⚙️ Assumptions'!$B$42:$F$42,MATCH(YEAR(K3),'⚙️ Assumptions'!$B$38:N$38,0)),OFFSET(K16,,-1)),_xlpm.rev,INDEX('💰 Revenue'!$C$14:$BJ$14,MATCH(K3,'💰 Revenue'!$C$5:$BJ$5,0)),_xlpm.Maintainance_ratio*_xlpm.rev) -> 3240000 | ... BJ15: =_xlfn.LET(_xlpm.Maintainance_ratio,_xlfn.IFNA(INDEX('⚙️ Assumptions'!$B$42:$F$42,MATCH(YEAR(BJ3),'⚙️ Assumptions'!$B$38:BM$38,0)),OFFSET(BJ16,,-1)),_xlpm.rev,INDEX('💰 Revenue'!$C$14:$BJ$14,MATCH(BJ3,'💰 Revenue'!$C$5:$BJ$5,0)),_xlpm.Maintainance_ratio*_xlpm.rev) -> 15390000
A16: Maintainance/doanh thu | C16: =IF(_xlfn.IFNA(INDEX('⚙️ Assumptions'!$B$40:$F$40,MATCH(YEAR(C3),'⚙️ Assumptions'!$B$38:$F$38,0)),1)<>1,C15/INDEX('💰 Revenue'!$C$14:$BJ14,MATCH(C3,'💰 Revenue'!$C$5:$BJ$5,0)),OFFSET(C16,,-1)) -> #DIV/0! | D16: =IF(_xlfn.IFNA(INDEX('⚙️ Assumptions'!$B$40:$F$40,MATCH(YEAR(D3),'⚙️ Assumptions'!$B$38:$F$38,0)),1)<>1,D15/INDEX('💰 Revenue'!$C$14:$BJ14,MATCH(D3,'💰 Revenue'!$C$5:$BJ$5,0)),OFFSET(D16,,-1)) -> #DIV/0! | E16: =IF(_xlfn.IFNA(INDEX('⚙️ Assumptions'!$B$40:$F$40,MATCH(YEAR(E3),'⚙️ Assumptions'!$B$38:$F$38,0)),1)<>1,E15/INDEX('💰 Revenue'!$C$14:$BJ14,MATCH(E3,'💰 Revenue'!$C$5:$BJ$5,0)),OFFSET(E16,,-1)) -> 0.01 | F16: =IF(_xlfn.IFNA(INDEX('⚙️ Assumptions'!$B$40:$F$40,MATCH(YEAR(F3),'⚙️ Assumptions'!$B$38:$F$38,0)),1)<>1,F15/INDEX('💰 Revenue'!$C$14:$BJ14,MATCH(F3,'💰 Revenue'!$C$5:$BJ$5,0)),OFFSET(F16,,-1)) -> 0.01 | G16: =IF(_xlfn.IFNA(INDEX('⚙️ Assumptions'!$B$40:$F$40,MATCH(YEAR(G3),'⚙️ Assumptions'!$B$38:$F$38,0)),1)<>1,G15/INDEX('💰 Revenue'!$C$14:$BJ14,MATCH(G3,'💰 Revenue'!$C$5:$BJ$5,0)),OFFSET(G16,,-1)) -> 0.01 | H16: =IF(_xlfn.IFNA(INDEX('⚙️ Assumptions'!$B$40:$F$40,MATCH(YEAR(H3),'⚙️ Assumptions'!$B$38:$F$38,0)),1)<>1,H15/INDEX('💰 Revenue'!$C$14:$BJ14,MATCH(H3,'💰 Revenue'!$C$5:$BJ$5,0)),OFFSET(H16,,-1)) -> 0.01 | I16: =IF(_xlfn.IFNA(INDEX('⚙️ Assumptions'!$B$40:$F$40,MATCH(YEAR(I3),'⚙️ Assumptions'!$B$38:$F$38,0)),1)<>1,I15/INDEX('💰 Revenue'!$C$14:$BJ14,MATCH(I3,'💰 Revenue'!$C$5:$BJ$5,0)),OFFSET(I16,,-1)) -> 0.01 | J16: =IF(_xlfn.IFNA(INDEX('⚙️ Assumptions'!$B$40:$F$40,MATCH(YEAR(J3),'⚙️ Assumptions'!$B$38:$F$38,0)),1)<>1,J15/INDEX('💰 Revenue'!$C$14:$BJ14,MATCH(J3,'💰 Revenue'!$C$5:$BJ$5,0)),OFFSET(J16,,-1)) -> 0.01 | ... BJ16: =IF(_xlfn.IFNA(INDEX('⚙️ Assumptions'!$B$40:$F$40,MATCH(YEAR(BJ3),'⚙️ Assumptions'!$B$38:$F$38,0)),1)<>1,BJ15/INDEX('💰 Revenue'!$C$14:$BJ14,MATCH(BJ3,'💰 Revenue'!$C$5:$BJ$5,0)),OFFSET(BJ16,,-1)) -> 0.04
A17: Payroll / Lương (VNĐ) — from HR Plan | B17: =SUM(C17:AL17) -> 1254820000 | C17: =INDEX('👥 HR Plan'!$B$18:$BI$18,MATCH(C3,'👥 HR Plan'!$B$11:$BI$11,0)) -> 0 | D17: =INDEX('👥 HR Plan'!$B$18:$BI$18,MATCH(D3,'👥 HR Plan'!$B$11:$BI$11,0)) -> 0 | E17: =INDEX('👥 HR Plan'!$B$18:$BI$18,MATCH(E3,'👥 HR Plan'!$B$11:$BI$11,0)) -> 28276000 | F17: =INDEX('👥 HR Plan'!$B$18:$BI$18,MATCH(F3,'👥 HR Plan'!$B$11:$BI$11,0)) -> 28276000 | G17: =INDEX('👥 HR Plan'!$B$18:$BI$18,MATCH(G3,'👥 HR Plan'!$B$11:$BI$11,0)) -> 27484000 | H17: =INDEX('👥 HR Plan'!$B$18:$BI$18,MATCH(H3,'👥 HR Plan'!$B$11:$BI$11,0)) -> 28276000 | I17: =INDEX('👥 HR Plan'!$B$18:$BI$18,MATCH(I3,'👥 HR Plan'!$B$11:$BI$11,0)) -> 33820000 | J17: =INDEX('👥 HR Plan'!$B$18:$BI$18,MATCH(J3,'👥 HR Plan'!$B$11:$BI$11,0)) -> 34414000 | ... BJ17: =INDEX('👥 HR Plan'!$B$18:$BI$18,MATCH(BJ3,'👥 HR Plan'!$B$11:$BI$11,0)) -> 39760000
A18: Marketing / Quảng cáo (VNĐ) | B18: =SUM(C18:AL18) -> 491743125 | C18: =IFERROR(INDEX('⚙️ Other Assumptions'!$C$20:$AJ$20,MATCH('💰 Revenue'!C4,'⚙️ Other Assumptions'!$B$14:$AI$14,0)),'⚙️ Other Assumptions'!$B$23) * INDEX('💰 Revenue'!$C$14:$BJ$14,MATCH(C3,'💰 Revenue'!$C$5:$BJ$5,0)) -> 0 | D18: =IFERROR(INDEX('⚙️ Other Assumptions'!$C$20:$AJ$20,MATCH('💰 Revenue'!D4,'⚙️ Other Assumptions'!$B$14:$AI$14,0)),'⚙️ Other Assumptions'!$B$23) * INDEX('💰 Revenue'!$C$14:$BJ$14,MATCH(D3,'💰 Revenue'!$C$5:$BJ$5,0)) -> 0 | E18: =IFERROR(INDEX('⚙️ Other Assumptions'!$C$20:$AJ$20,MATCH('💰 Revenue'!E4,'⚙️ Other Assumptions'!$B$14:$AI$14,0)),'⚙️ Other Assumptions'!$B$23) * INDEX('💰 Revenue'!$C$14:$BJ$14,MATCH(E3,'💰 Revenue'!$C$5:$BJ$5,0)) -> 25110000 | F18: =IFERROR(INDEX('⚙️ Other Assumptions'!$C$20:$AJ$20,MATCH('💰 Revenue'!F4,'⚙️ Other Assumptions'!$B$14:$AI$14,0)),'⚙️ Other Assumptions'!$B$23) * INDEX('💰 Revenue'!$C$14:$BJ$14,MATCH(F3,'💰 Revenue'!$C$5:$BJ$5,0)) -> 25110000 | G18: =IFERROR(INDEX('⚙️ Other Assumptions'!$C$20:$AJ$20,MATCH('💰 Revenue'!G4,'⚙️ Other Assumptions'!$B$14:$AI$14,0)),'⚙️ Other Assumptions'!$B$23) * INDEX('💰 Revenue'!$C$14:$BJ$14,MATCH(G3,'💰 Revenue'!$C$5:$BJ$5,0)) -> 11092500 | H18: =IFERROR(INDEX('⚙️ Other Assumptions'!$C$20:$AJ$20,MATCH('💰 Revenue'!H4,'⚙️ Other Assumptions'!$B$14:$AI$14,0)),'⚙️ Other Assumptions'!$B$23) * INDEX('💰 Revenue'!$C$14:$BJ$14,MATCH(H3,'💰 Revenue'!$C$5:$BJ$5,0)) -> 13252500 | I18: =IFERROR(INDEX('⚙️ Other Assumptions'!$C$20:$AJ$20,MATCH('💰 Revenue'!I4,'⚙️ Other Assumptions'!$B$14:$AI$14,0)),'⚙️ Other Assumptions'!$B$23) * INDEX('💰 Revenue'!$C$14:$BJ$14,MATCH(I3,'💰 Revenue'!$C$5:$BJ$5,0)) -> 23287500 | J18: =IFERROR(INDEX('⚙️ Other Assumptions'!$C$20:$AJ$20,MATCH('💰 Revenue'!J4,'⚙️ Other Assumptions'!$B$14:$AI$14,0)),'⚙️ Other Assumptions'!$B$23) * INDEX('💰 Revenue'!$C$14:$BJ$14,MATCH(J3,'💰 Revenue'!$C$5:$BJ$5,0)) -> 21971250 | ... BJ18: =IFERROR(INDEX('⚙️ Other Assumptions'!$C$20:$AJ$20,MATCH('💰 Revenue'!BJ4,'⚙️ Other Assumptions'!$B$14:$AI$14,0)),'⚙️ Other Assumptions'!$B$23) * INDEX('💰 Revenue'!$C$14:$BJ$14,MATCH(BJ3,'💰 Revenue'!$C$5:$BJ$5,0)) -> 11542500
A19: Other fixed / Chi phí cố định khác (VNĐ) | B19: =SUM(C19:AL19) -> 0
A20: TOTAL FIXED COSTS / TỔNG CP CỐ ĐỊNH (VNĐ) | B20: =SUM(C20:AL20) -> 4.9124675e+09 | C20: =C9+C10+C15+C17+C18+C19 -> 57500000 | D20: =D9+D10+D15+D17+D18+D19 -> 57500000 | E20: =E9+E10+E15+E17+E18+E19 -> 118544550 | F20: =F9+F10+F15+F17+F18+F19 -> 118544550 | G20: =G9+G10+G15+G17+G18+G19 -> 1.0508916e+08 | H20: =H9+H10+H15+H17+H18+H19 -> 1.0979616e+08 | I20: =I9+I10+I15+I17+I18+I19 -> 1.3352859e+08 | J20: =J9+J10+J15+J17+J18+J19 -> 1.3173689e+08 | ... BJ20: =BJ9+BJ10+BJ15+BJ17+BJ18+BJ19 -> 150740250
A21: C. VARIABLE OVERHEAD / CHI PHÍ BIẾN ĐỔI CHUNG
A22: Loyalty program cost / CP chương trình thành viên (VNĐ) | B22: =SUM(C22:AL22) -> 0
A23: Promotions / Khuyến mãi (VNĐ) | B23: =SUM(C23:AL23) -> 0
A24: Opex sub-total (before contingency) | B24: =SUM(C24:AL24) -> 4.9124675e+09 | C24: =C20+C22+C23 -> 57500000 | D24: =D20+D22+D23 -> 57500000 | E24: =E20+E22+E23 -> 118544550 | F24: =F20+F22+F23 -> 118544550 | G24: =G20+G22+G23 -> 1.0508916e+08 | H24: =H20+H22+H23 -> 1.0979616e+08 | I24: =I20+I22+I23 -> 1.3352859e+08 | J24: =J20+J22+J23 -> 1.3173689e+08 | ... BJ24: =BJ20+BJ22+BJ23 -> 150740250
A25: Contingency 2% / Dự phòng phí (VNĐ) | B25: =SUM(C25:AL25) -> 98249351 | C25: =C24*0.02 -> 1150000 | D25: =D24*0.02 -> 1150000 | E25: =E24*0.02 -> 2370891 | F25: =F24*0.02 -> 2370891 | G25: =G24*0.02 -> 2101783.1 | H25: =H24*0.02 -> 2195923.1 | I25: =I24*0.02 -> 2670571.9 | J25: =J24*0.02 -> 2634737.8 | ... BJ25: =BJ24*0.02 -> 3014805
A26: Management fee 3% / Phí quản lý (VNĐ) | B26: =SUM(C26:AL26) -> 1.4737403e+08 | C26: =C24*0.03 -> 1725000 | D26: =D24*0.03 -> 1725000 | E26: =E24*0.03 -> 3556336.5 | F26: =F24*0.03 -> 3556336.5 | G26: =G24*0.03 -> 3152674.7 | H26: =H24*0.03 -> 3293884.7 | I26: =I24*0.03 -> 4005857.8 | J26: =J24*0.03 -> 3952106.7 | ... BJ26: =BJ24*0.03 -> 4522207.5
A27: TOTAL VARIABLE OVERHEAD / TỔNG CP BIẾN ĐỔI (VNĐ) | B27: =SUM(C27:AL27) -> 2.4562338e+08 | C27: =C22+C23+C25+C26 -> 2875000 | D27: =D22+D23+D25+D26 -> 2875000 | E27: =E22+E23+E25+E26 -> 5927227.5 | F27: =F22+F23+F25+F26 -> 5927227.5 | G27: =G22+G23+G25+G26 -> 5254457.8 | H27: =H22+H23+H25+H26 -> 5489807.8 | I27: =I22+I23+I25+I26 -> 6676429.7 | J27: =J22+J23+J25+J26 -> 6586844.5 | ... BJ27: =BJ22+BJ23+BJ25+BJ26 -> 7537012.5
A28: D. CAPEX & DEPRECIATION / ĐẦU TƯ & KHẤU HAO
A29: Capital expenditure / Chi phí đầu tư (VNĐ) | B29: =SUM(C29:AL29) -> 300000000 | C29: ='⚙️ Assumptions'!$B$16 -> 300000000
A30: Monthly depreciation / Khấu hao hàng tháng (VNĐ) | B30: =SUM(C30:AL30) -> 180000000 | C30: =$C$29/12/5 -> 5000000 | D30: =$C$29/12/5 -> 5000000 | E30: =$C$29/12/5 -> 5000000 | F30: =$C$29/12/5 -> 5000000 | G30: =$C$29/12/5 -> 5000000 | H30: =$C$29/12/5 -> 5000000 | I30: =$C$29/12/5 -> 5000000 | J30: =$C$29/12/5 -> 5000000 | ... BJ30: =$C$29/12/5 -> 5000000
A31: E. TOTAL COST SUMMARY / TỔNG CHI PHÍ
A32: TOTAL OPEX (excl. Capex) / TỔNG CP VH (VNĐ) | B32: =SUM(C32:AL32) -> 8.2245147e+09 | C32: =C7+C20+C27 -> 60375000 | D32: =D7+D20+D27 -> 60375000 | E32: =E7+E20+E27 -> 1.5962578e+08 | F32: =F7+F20+F27 -> 1.5761698e+08 | G32: =G7+G20+G27 -> 1.4694886e+08 | H32: =H7+H20+H27 -> 1.5901921e+08 | I32: =I7+I20+I27 -> 2.1705377e+08 | J32: =J7+J20+J27 -> 2.1082886e+08 | ... BJ32: =BJ7+BJ20+BJ27 -> 2.4753926e+08
A33: TOTAL COST incl. Capex / TỔNG CHI PHÍ (VNĐ) | B33: =SUM(C33:AL33) -> 8.5245147e+09 | C33: =C32+C29 -> 360375000 | D33: =D32+D29 -> 60375000 | E33: =E32+E29 -> 1.5962578e+08 | F33: =F32+F29 -> 1.5761698e+08 | G33: =G32+G29 -> 1.4694886e+08 | H33: =H32+H29 -> 1.5901921e+08 | I33: =I32+I29 -> 2.1705377e+08 | J33: =J32+J29 -> 2.1082886e+08 | ... BJ33: =BJ32+BJ29 -> 2.4753926e+08
A34: Total opex % revenue / Tổng CP % DT | B34: ="" | C34: =IFERROR(C32/INDEX('💰 Revenue'!$C$19:$BJ$19,MATCH(C3,'💰 Revenue'!$C$5:BJ5,0)),"-") -> - | D34: =IFERROR(D32/INDEX('💰 Revenue'!$C$19:$BJ$19,MATCH(D3,'💰 Revenue'!$C$5:BK5,0)),"-") -> - | E34: =IFERROR(E32/INDEX('💰 Revenue'!$C$19:$BJ$19,MATCH(E3,'💰 Revenue'!$C$5:BL5,0)),"-") -> 1.271412 | F34: =IFERROR(F32/INDEX('💰 Revenue'!$C$19:$BJ$19,MATCH(F3,'💰 Revenue'!$C$5:BM5,0)),"-") -> 1.255412 | G34: =IFERROR(G32/INDEX('💰 Revenue'!$C$19:$BJ$19,MATCH(G3,'💰 Revenue'!$C$5:BN5,0)),"-") -> 1.059807 | H34: =IFERROR(H32/INDEX('💰 Revenue'!$C$19:$BJ$19,MATCH(H3,'💰 Revenue'!$C$5:BO5,0)),"-") -> 0.95993489 | I34: =IFERROR(I32/INDEX('💰 Revenue'!$C$19:$BJ$19,MATCH(I3,'💰 Revenue'!$C$5:BP5,0)),"-") -> 0.74564903 | J34: =IFERROR(J32/INDEX('💰 Revenue'!$C$19:$BJ$19,MATCH(J3,'💰 Revenue'!$C$5:BQ5,0)),"-") -> 0.76765358 | ... BJ34: =IFERROR(BJ32/INDEX('💰 Revenue'!$C$19:$BJ$19,MATCH(BJ3,'💰 Revenue'!$C$5:DQ5,0)),"-") -> 0.6433769

Sheet 👥 HR Plan
A1: HR PLAN & PAYROLL BUDGET / KẾ HOẠCH NHÂN SỰ & LƯƠNG
A2: POSITION / CHỨC VỤ | B2: Qty/ Số lượng | C2: SALARY Incl Insurance (Lương đã bao gồm bảo hiểm) | D2: Hourly Rate (Lương trên giờ) | F2: SHIFTS SỐ CA | G2: NOTES / GHI CHÚ
A3: General Manager / Quản lý nhà hàng | B3: 1 | C3: =12*10^6 -> 12000000
A4: Waiter/Waitress / Phục vụ bàn | D4: 33000 | F4: 2 shifts per day
A5: Security / Bảo vệ (outsouce) | B5: 0 | C5: 8500000
A6: Accountant / Kế toán (Outsource) | C6: =4*10^6 -> 4000000
A8: TOTAL HEADCOUNT / TỔNG NHÂN VIÊN | B8: =SUMPRODUCT((LEN(A3:A6)>0)*(B3:B6)) -> 1 | C8: =SUMPRODUCT((LEN(A3:A6)>0)*(C3:C6)) -> 24500000 | D8: =SUMPRODUCT((LEN(A3:A6)>0)*(D3:D6)) -> 33000
B10: 1 | C10: 2 | D10: 3 | E10: 4 | F10: 5 | G10: 6 | H10: 7 | I10: 8 | J10: 9 | K10: 10 | L10: 11 | M10: 12 | N10: 13 | O10: 14 | P10: 15 | Q10: 16 | R10: 17 | S10: 18 | T10: 19 | U10: 20 | V10: 21 | W10: 22 | X10: 23 | Y10: 24 | Z10: 25 | AA10: 26 | AB10: 27 | AC10: 28 | AD10: 29 | AE10: 30 | AF10: 31 | AG10: 32 | AH10: 33 | AI10: 34 | AJ10: 35 | AK10: 36 | AL10: 37 | AM10: 38 | AN10: 39 | AO10: 40 | AP10: 41 | AQ10: 42 | AR10: 43 | AS10: 44 | AT10: 45 | AU10: 46 | AV10: 47 | AW10: 48 | AX10: 49 | AY10: 50 | AZ10: 51 | BA10: 52 | BB10: 53 | BC10: 54 | BD10: 55 | BE10: 56 | BF10: 57 | BG10: 58 | BH10: 59 | BI10: 60
B11: ='⚙️ Assumptions'!B6 -> 46661 | C11: =EDATE($B$11,'💰 Revenue'!D2) -> 46692 | D11: =EDATE($B$11,'💰 Revenue'!E2) -> 46722 | E11: =EDATE($B$11,'💰 Revenue'!F2) -> 46753 | F11: =EDATE($B$11,'💰 Revenue'!G2) -> 46784 | G11: =EDATE($B$11,'💰 Revenue'!H2) -> 46813 | H11: =EDATE($B$11,'💰 Revenue'!I2) -> 46844 | I11: =EDATE($B$11,'💰 Revenue'!J2) -> 46874 | J11: =EDATE($B$11,'💰 Revenue'!K2) -> 46905 | ... BI11: =EDATE($B$11,'💰 Revenue'!BJ2) -> 48458
A12: General Manager/ Main Cook | B12: =_xlfn.LET( _xlpm.prep_month, INDEX('⚙️ Other Assumptions'!$B$18:$AK$18,MATCH(B$10,'⚙️ Other Assumptions'!$B$14:$AK$14,0)), IF(B$10> 10, $C$3, IF( _xlpm.prep_month >0, $C$3,0))) -> 0 | C12: =_xlfn.LET( _xlpm.prep_month, INDEX('⚙️ Other Assumptions'!$B$18:$AK$18,MATCH(C$10,'⚙️ Other Assumptions'!$B$14:$AK$14,0)), IF(C$10> 10, $C$3, IF( _xlpm.prep_month >0, $C$3,0))) -> 0 | D12: =_xlfn.LET( _xlpm.prep_month, INDEX('⚙️ Other Assumptions'!$B$18:$AK$18,MATCH(D$10,'⚙️ Other Assumptions'!$B$14:$AK$14,0)), IF(D$10> 10, $C$3, IF( _xlpm.prep_month >0, $C$3,0))) -> 12000000 | E12: =_xlfn.LET( _xlpm.prep_month, INDEX('⚙️ Other Assumptions'!$B$18:$AK$18,MATCH(E$10,'⚙️ Other Assumptions'!$B$14:$AK$14,0)), IF(E$10> 10, $C$3, IF( _xlpm.prep_month >0, $C$3,0))) -> 12000000 | F12: =_xlfn.LET( _xlpm.prep_month, INDEX('⚙️ Other Assumptions'!$B$18:$AK$18,MATCH(F$10,'⚙️ Other Assumptions'!$B$14:$AK$14,0)), IF(F$10> 10, $C$3, IF( _xlpm.prep_month >0, $C$3,0))) -> 12000000 | G12: =_xlfn.LET( _xlpm.prep_month, INDEX('⚙️ Other Assumptions'!$B$18:$AK$18,MATCH(G$10,'⚙️ Other Assumptions'!$B$14:$AK$14,0)), IF(G$10> 10, $C$3, IF( _xlpm.prep_month >0, $C$3,0))) -> 12000000 | H12: =_xlfn.LET( _xlpm.prep_month, INDEX('⚙️ Other Assumptions'!$B$18:$AK$18,MATCH(H$10,'⚙️ Other Assumptions'!$B$14:$AK$14,0)), IF(H$10> 10, $C$3, IF( _xlpm.prep_month >0, $C$3,0))) -> 12000000 | I12: =_xlfn.LET( _xlpm.prep_month, INDEX('⚙️ Other Assumptions'!$B$18:$AK$18,MATCH(I$10,'⚙️ Other Assumptions'!$B$14:$AK$14,0)), IF(I$10> 10, $C$3, IF( _xlpm.prep_month >0, $C$3,0))) -> 12000000 | ... BI12: =_xlfn.LET( _xlpm.prep_month, INDEX('⚙️ Other Assumptions'!$B$18:$AK$18,MATCH(BI$10,'⚙️ Other Assumptions'!$B$14:$AK$14,0)), IF(BI$10> 10, $C$3, IF( _xlpm.prep_month >0, $C$3,0))) -> 12000000
A13: # of Waiter/Waitress / Phục vụ bàn | B13: =IF(B14>150,4,IF(B14>100,3,IF(B14>0,2,0))) -> 0 | C13: =IF(C14>150,4,IF(C14>100,3,IF(C14>0,2,0))) -> 0 | D13: =IF(D14>150,4,IF(D14>100,3,IF(D14>0,2,0))) -> 2 | E13: =IF(E14>150,4,IF(E14>100,3,IF(E14>0,2,0))) -> 2 | F13: =IF(F14>150,4,IF(F14>100,3,IF(F14>0,2,0))) -> 2 | G13: =IF(G14>150,4,IF(G14>100,3,IF(G14>0,2,0))) -> 2 | H13: =IF(H14>150,4,IF(H14>100,3,IF(H14>0,2,0))) -> 3 | I13: =IF(I14>150,4,IF(I14>100,3,IF(I14>0,2,0))) -> 3 | ... BI13: =IF(BI14>150,4,IF(BI14>100,3,IF(BI14>0,2,0))) -> 4
A14: Number of covers | B14: =INDEX('💰 Revenue'!$C$7:$BJ$7, MATCH(B11,'💰 Revenue'!$C$5:$BJ$5,0)) -> 0 | C14: =INDEX('💰 Revenue'!$C$7:$BJ$7, MATCH(C11,'💰 Revenue'!$C$5:$BJ$5,0)) -> 0 | D14: =INDEX('💰 Revenue'!$C$7:$BJ$7, MATCH(D11,'💰 Revenue'!$C$5:$BJ$5,0)) -> 45 | E14: =INDEX('💰 Revenue'!$C$7:$BJ$7, MATCH(E11,'💰 Revenue'!$C$5:$BJ$5,0)) -> 45 | F14: =INDEX('💰 Revenue'!$C$7:$BJ$7, MATCH(F11,'💰 Revenue'!$C$5:$BJ$5,0)) -> 75 | G14: =INDEX('💰 Revenue'!$C$7:$BJ$7, MATCH(G11,'💰 Revenue'!$C$5:$BJ$5,0)) -> 75 | H14: =INDEX('💰 Revenue'!$C$7:$BJ$7, MATCH(H11,'💰 Revenue'!$C$5:$BJ$5,0)) -> 112.5 | I14: =INDEX('💰 Revenue'!$C$7:$BJ$7, MATCH(I11,'💰 Revenue'!$C$5:$BJ$5,0)) -> 112.5 | ... BI14: =INDEX('💰 Revenue'!$C$7:$BJ$7, MATCH(BI11,'💰 Revenue'!$C$5:$BJ$5,0)) -> 180
A15: Waiter/Waitress / Phục vụ bàn Salary | B15: =_xlfn.LET( _xlpm.prep_month, INDEX('⚙️ Other Assumptions'!$B$18:$AK$18,MATCH(B$10,'⚙️ Other Assumptions'!$B$14:$AK$14,0)), _xlpm.days_per_month, INDEX('💰 Revenue'!$C$8:$BJ$8,MATCH(B11,'💰 Revenue'!$C$5:$BJ5,0)), _xlpm.number_of_worker, B13, _xlpm.hourly_rate,$D$4, _xlpm.6hrs_pershift, 6 , _xlpm.waiter_sal, _xlpm.days_per_month * _xlpm.number_of_worker * _xlpm.hourly_rate * _xlpm.6hrs_pershift, IF(B$10> 10, _xlpm.waiter_sal, IF(_xlpm.prep_month > 0, _xlpm.waiter_sal,0))) -> 0 | C15: =_xlfn.LET( _xlpm.prep_month, INDEX('⚙️ Other Assumptions'!$B$18:$AK$18,MATCH(C$10,'⚙️ Other Assumptions'!$B$14:$AK$14,0)), _xlpm.days_per_month, INDEX('💰 Revenue'!$C$8:$BJ$8,MATCH(C11,'💰 Revenue'!$C$5:$BJ5,0)), _xlpm.number_of_worker, C13, _xlpm.hourly_rate,$D$4, _xlpm.6hrs_pershift, 6 , _xlpm.waiter_sal, _xlpm.days_per_month * _xlpm.number_of_worker * _xlpm.hourly_rate * _xlpm.6hrs_pershift, IF(C$10> 10, _xlpm.waiter_sal, IF(_xlpm.prep_month > 0, _xlpm.waiter_sal,0))) -> 0 | D15: =_xlfn.LET( _xlpm.prep_month, INDEX('⚙️ Other Assumptions'!$B$18:$AK$18,MATCH(D$10,'⚙️ Other Assumptions'!$B$14:$AK$14,0)), _xlpm.days_per_month, INDEX('💰 Revenue'!$C$8:$BJ$8,MATCH(D11,'💰 Revenue'!$C$5:$BJ5,0)), _xlpm.number_of_worker, D13, _xlpm.hourly_rate,$D$4, _xlpm.6hrs_pershift, 6 , _xlpm.waiter_sal, _xlpm.days_per_month * _xlpm.number_of_worker * _xlpm.hourly_rate * _xlpm.6hrs_pershift, IF(D$10> 10, _xlpm.waiter_sal, IF(_xlpm.prep_month > 0, _xlpm.waiter_sal,0))) -> 12276000 | E15: =_xlfn.LET( _xlpm.prep_month, INDEX('⚙️ Other Assumptions'!$B$18:$AK$18,MATCH(E$10,'⚙️ Other Assumptions'!$B$14:$AK$14,0)), _xlpm.days_per_month, INDEX('💰 Revenue'!$C$8:$BJ$8,MATCH(E11,'💰 Revenue'!$C$5:$BJ5,0)), _xlpm.number_of_worker, E13, _xlpm.hourly_rate,$D$4, _xlpm.6hrs_pershift, 6 , _xlpm.waiter_sal, _xlpm.days_per_month * _xlpm.number_of_worker * _xlpm.hourly_rate * _xlpm.6hrs_pershift, IF(E$10> 10, _xlpm.waiter_sal, IF(_xlpm.prep_month > 0, _xlpm.waiter_sal,0))) -> 12276000 | F15: =_xlfn.LET( _xlpm.prep_month, INDEX('⚙️ Other Assumptions'!$B$18:$AK$18,MATCH(F$10,'⚙️ Other Assumptions'!$B$14:$AK$14,0)), _xlpm.days_per_month, INDEX('💰 Revenue'!$C$8:$BJ$8,MATCH(F11,'💰 Revenue'!$C$5:$BJ5,0)), _xlpm.number_of_worker, F13, _xlpm.hourly_rate,$D$4, _xlpm.6hrs_pershift, 6 , _xlpm.waiter_sal, _xlpm.days_per_month * _xlpm.number_of_worker * _xlpm.hourly_rate * _xlpm.6hrs_pershift, IF(F$10> 10, _xlpm.waiter_sal, IF(_xlpm.prep_month > 0, _xlpm.waiter_sal,0))) -> 11484000 | G15: =_xlfn.LET( _xlpm.prep_month, INDEX('⚙️ Other Assumptions'!$B$18:$AK$18,MATCH(G$10,'⚙️ Other Assumptions'!$B$14:$AK$14,0)), _xlpm.days_per_month, INDEX('💰 Revenue'!$C$8:$BJ$8,MATCH(G11,'💰 Revenue'!$C$5:$BJ5,0)), _xlpm.number_of_worker, G13, _xlpm.hourly_rate,$D$4, _xlpm.6hrs_pershift, 6 , _xlpm.waiter_sal, _xlpm.days_per_month * _xlpm.number_of_worker * _xlpm.hourly_rate * _xlpm.6hrs_pershift, IF(G$10> 10, _xlpm.waiter_sal, IF(_xlpm.prep_month > 0, _xlpm.waiter_sal,0))) -> 12276000 | H15: =_xlfn.LET( _xlpm.prep_month, INDEX('⚙️ Other Assumptions'!$B$18:$AK$18,MATCH(H$10,'⚙️ Other Assumptions'!$B$14:$AK$14,0)), _xlpm.days_per_month, INDEX('💰 Revenue'!$C$8:$BJ$8,MATCH(H11,'💰 Revenue'!$C$5:$BJ5,0)), _xlpm.number_of_worker, H13, _xlpm.hourly_rate,$D$4, _xlpm.6hrs_pershift, 6 , _xlpm.waiter_sal, _xlpm.days_per_month * _xlpm.number_of_worker * _xlpm.hourly_rate * _xlpm.6hrs_pershift, IF(H$10> 10, _xlpm.waiter_sal, IF(_xlpm.prep_month > 0, _xlpm.waiter_sal,0))) -> 17820000 | I15: =_xlfn.LET( _xlpm.prep_month, INDEX('⚙️ Other Assumptions'!$B$18:$AK$18,MATCH(I$10,'⚙️ Other Assumptions'!$B$14:$AK$14,0)), _xlpm.days_per_month, INDEX('💰 Revenue'!$C$8:$BJ$8,MATCH(I11,'💰 Revenue'!$C$5:$BJ5,0)), _xlpm.number_of_worker, I13, _xlpm.hourly_rate,$D$4, _xlpm.6hrs_pershift, 6 , _xlpm.waiter_sal, _xlpm.days_per_month * _xlpm.number_of_worker * _xlpm.hourly_rate * _xlpm.6hrs_pershift, IF(I$10> 10, _xlpm.waiter_sal, IF(_xlpm.prep_month > 0, _xlpm.waiter_sal,0))) -> 18414000 | ... BI15: =_xlfn.LET( _xlpm.prep_month, INDEX('⚙️ Other Assumptions'!$B$18:$AK$18,MATCH(BI$10,'⚙️ Other Assumptions'!$B$14:$AK$14,0)), _xlpm.days_per_month, INDEX('💰 Revenue'!$C$8:$BJ$8,MATCH(BI11,'💰 Revenue'!$C$5:$BJ5,0)), _xlpm.number_of_worker, BI13, _xlpm.hourly_rate,$D$4, _xlpm.6hrs_pershift, 6 , _xlpm.waiter_sal, _xlpm.days_per_month * _xlpm.number_of_worker * _xlpm.hourly_rate * _xlpm.6hrs_pershift, IF(BI$10> 10, _xlpm.waiter_sal, IF(_xlpm.prep_month > 0, _xlpm.waiter_sal,0))) -> 23760000
A16: Security / Bảo vệ | B16: =_xlfn.LET( _xlpm.prep_month, INDEX('⚙️ Other Assumptions'!$B$18:$AK$18,MATCH(B$10,'⚙️ Other Assumptions'!$B$14:$AK$14,0)), _xlpm.security_sal, $C$5*$B$5, IF(B$10 > 10, _xlpm.security_sal, IF(_xlpm.prep_month > 0, _xlpm.security_sal,0))) -> 0 | C16: =_xlfn.LET( _xlpm.prep_month, INDEX('⚙️ Other Assumptions'!$B$18:$AK$18,MATCH(C$10,'⚙️ Other Assumptions'!$B$14:$AK$14,0)), _xlpm.security_sal, $C$5*$B$5, IF(C$10 > 10, _xlpm.security_sal, IF(_xlpm.prep_month > 0, _xlpm.security_sal,0))) -> 0 | D16: =_xlfn.LET( _xlpm.prep_month, INDEX('⚙️ Other Assumptions'!$B$18:$AK$18,MATCH(D$10,'⚙️ Other Assumptions'!$B$14:$AK$14,0)), _xlpm.security_sal, $C$5*$B$5, IF(D$10 > 10, _xlpm.security_sal, IF(_xlpm.prep_month > 0, _xlpm.security_sal,0))) -> 0 | E16: =_xlfn.LET( _xlpm.prep_month, INDEX('⚙️ Other Assumptions'!$B$18:$AK$18,MATCH(E$10,'⚙️ Other Assumptions'!$B$14:$AK$14,0)), _xlpm.security_sal, $C$5*$B$5, IF(E$10 > 10, _xlpm.security_sal, IF(_xlpm.prep_month > 0, _xlpm.security_sal,0))) -> 0 | F16: =_xlfn.LET( _xlpm.prep_month, INDEX('⚙️ Other Assumptions'!$B$18:$AK$18,MATCH(F$10,'⚙️ Other Assumptions'!$B$14:$AK$14,0)), _xlpm.security_sal, $C$5*$B$5, IF(F$10 > 10, _xlpm.security_sal, IF(_xlpm.prep_month > 0, _xlpm.security_sal,0))) -> 0 | G16: =_xlfn.LET( _xlpm.prep_month, INDEX('⚙️ Other Assumptions'!$B$18:$AK$18,MATCH(G$10,'⚙️ Other Assumptions'!$B$14:$AK$14,0)), _xlpm.security_sal, $C$5*$B$5, IF(G$10 > 10, _xlpm.security_sal, IF(_xlpm.prep_month > 0, _xlpm.security_sal,0))) -> 0 | H16: =_xlfn.LET( _xlpm.prep_month, INDEX('⚙️ Other Assumptions'!$B$18:$AK$18,MATCH(H$10,'⚙️ Other Assumptions'!$B$14:$AK$14,0)), _xlpm.security_sal, $C$5*$B$5, IF(H$10 > 10, _xlpm.security_sal, IF(_xlpm.prep_month > 0, _xlpm.security_sal,0))) -> 0 | I16: =_xlfn.LET( _xlpm.prep_month, INDEX('⚙️ Other Assumptions'!$B$18:$AK$18,MATCH(I$10,'⚙️ Other Assumptions'!$B$14:$AK$14,0)), _xlpm.security_sal, $C$5*$B$5, IF(I$10 > 10, _xlpm.security_sal, IF(_xlpm.prep_month > 0, _xlpm.security_sal,0))) -> 0 | ... BI16: =_xlfn.LET( _xlpm.prep_month, INDEX('⚙️ Other Assumptions'!$B$18:$AK$18,MATCH(BI$10,'⚙️ Other Assumptions'!$B$14:$AK$14,0)), _xlpm.security_sal, $C$5*$B$5, IF(BI$10 > 10, _xlpm.security_sal, IF(_xlpm.prep_month > 0, _xlpm.security_sal,0))) -> 0
A17: Accountant / Kế toán (Outsource) | B17: =_xlfn.LET( _xlpm.prep_month, INDEX('⚙️ Other Assumptions'!$B$18:$AK$18,MATCH(B$10,'⚙️ Other Assumptions'!$B$14:$AK$14,0)), IF(B10 > 10, $C$6, IF(_xlpm.prep_month >0, $C$6,0))) -> 0 | C17: =_xlfn.LET( _xlpm.prep_month, INDEX('⚙️ Other Assumptions'!$B$18:$AK$18,MATCH(C$10,'⚙️ Other Assumptions'!$B$14:$AK$14,0)), IF(C10 > 10, $C$6, IF(_xlpm.prep_month >0, $C$6,0))) -> 0 | D17: =_xlfn.LET( _xlpm.prep_month, INDEX('⚙️ Other Assumptions'!$B$18:$AK$18,MATCH(D$10,'⚙️ Other Assumptions'!$B$14:$AK$14,0)), IF(D10 > 10, $C$6, IF(_xlpm.prep_month >0, $C$6,0))) -> 4000000 | E17: =_xlfn.LET( _xlpm.prep_month, INDEX('⚙️ Other Assumptions'!$B$18:$AK$18,MATCH(E$10,'⚙️ Other Assumptions'!$B$14:$AK$14,0)), IF(E10 > 10, $C$6, IF(_xlpm.prep_month >0, $C$6,0))) -> 4000000 | F17: =_xlfn.LET( _xlpm.prep_month, INDEX('⚙️ Other Assumptions'!$B$18:$AK$18,MATCH(F$10,'⚙️ Other Assumptions'!$B$14:$AK$14,0)), IF(F10 > 10, $C$6, IF(_xlpm.prep_month >0, $C$6,0))) -> 4000000 | G17: =_xlfn.LET( _xlpm.prep_month, INDEX('⚙️ Other Assumptions'!$B$18:$AK$18,MATCH(G$10,'⚙️ Other Assumptions'!$B$14:$AK$14,0)), IF(G10 > 10, $C$6, IF(_xlpm.prep_month >0, $C$6,0))) -> 4000000 | H17: =_xlfn.LET( _xlpm.prep_month, INDEX('⚙️ Other Assumptions'!$B$18:$AK$18,MATCH(H$10,'⚙️ Other Assumptions'!$B$14:$AK$14,0)), IF(H10 > 10, $C$6, IF(_xlpm.prep_month >0, $C$6,0))) -> 4000000 | I17: =_xlfn.LET( _xlpm.prep_month, INDEX('⚙️ Other Assumptions'!$B$18:$AK$18,MATCH(I$10,'⚙️ Other Assumptions'!$B$14:$AK$14,0)), IF(I10 > 10, $C$6, IF(_xlpm.prep_month >0, $C$6,0))) -> 4000000 | ... BI17: =_xlfn.LET( _xlpm.prep_month, INDEX('⚙️ Other Assumptions'!$B$18:$AK$18,MATCH(BI$10,'⚙️ Other Assumptions'!$B$14:$AK$14,0)), IF(BI10 > 10, $C$6, IF(_xlpm.prep_month >0, $C$6,0))) -> 4000000
A18: Total (Tổng cộng) | B18: =SUM(B15:B17,B12) -> 0 | C18: =SUM(C15:C17,C12) -> 0 | D18: =SUM(D15:D17,D12) -> 28276000 | E18: =SUM(E15:E17,E12) -> 28276000 | F18: =SUM(F15:F17,F12) -> 27484000 | G18: =SUM(G15:G17,G12) -> 28276000 | H18: =SUM(H15:H17,H12) -> 33820000 | I18: =SUM(I15:I17,I12) -> 34414000 | ... BI18: =SUM(BI15:BI17,BI12) -> 39760000

Sheet 📊 P&L Detail
A1: DETAILED PROFIT & LOSS / BÁO CÁO KQHĐKD CHI TIẾT
B2: TOTAL / TỔNG | C2: YEAR 1 / NĂM 1 | O2: YEAR 2 / NĂM 2 | AA2: YEAR 3 / NĂM 3
C3: M01 | D3: M02 | E3: M03 | F3: M04 | G3: M05 | H3: M06 | I3: M07 | J3: M08 | K3: M09 | L3: M10 | M3: M11 | N3: M12 | O3: M13 | P3: M14 | Q3: M15 | R3: M16 | S3: M17 | T3: M18 | U3: M19 | V3: M20 | W3: M21 | X3: M22 | Y3: M23 | Z3: M24 | AA3: M25 | AB3: M26 | AC3: M27 | AD3: M28 | AE3: M29 | AF3: M30 | AG3: M31 | AH3: M32 | AI3: M33 | AJ3: M34 | AK3: M35 | AL3: M36 | AM3: M37 | AN3: M38 | AO3: M39 | AP3: M40 | AQ3: M41 | AR3: M42 | AS3: M43 | AT3: M44 | AU3: M45 | AV3: M46 | AW3: M47 | AX3: M48 | AY3: M49 | AZ3: M50 | BA3: M51 | BB3: M52 | BC3: M53 | BD3: M54 | BE3: M55 | BF3: M56 | BG3: M57 | BH3: M58 | BI3: M59 | BJ3: M60
A4: LINE ITEM / CHỈ TIÊU | B4: 5-YEAR TOTAL / TỔNG 5 NĂM | C4: ='⚙️ Assumptions'!B6 -> 46661 | D4: =EDATE($C$4,'💰 Revenue'!D2) -> 46692 | E4: =EDATE($C$4,'💰 Revenue'!E2) -> 46722 | F4: =EDATE($C$4,'💰 Revenue'!F2) -> 46753 | G4: =EDATE($C$4,'💰 Revenue'!G2) -> 46784 | H4: =EDATE($C$4,'💰 Revenue'!H2) -> 46813 | I4: =EDATE($C$4,'💰 Revenue'!I2) -> 46844 | J4: =EDATE($C$4,'💰 Revenue'!J2) -> 46874 | K4: =EDATE($C$4,'💰 Revenue'!K2) -> 46905 | ... BJ4: =EDATE($C$4,'💰 Revenue'!BJ2) -> 48458
A5: ── REVENUE / DOANH THU ──
A6: Gross Revenue / Doanh thu gộp (VNĐ) | B6: =SUM(C6:BJ6) -> 23002143750 | C6: ='💰 Revenue'!C14 -> 0 | D6: ='💰 Revenue'!D14 -> 0 | E6: ='💰 Revenue'!E14 -> 125550000 | F6: ='💰 Revenue'!F14 -> 125550000 | G6: ='💰 Revenue'!G14 -> 138656250 | H6: ='💰 Revenue'!H14 -> 165656250 | I6: ='💰 Revenue'!I14 -> 291093750 | J6: ='💰 Revenue'!J14 -> 274640625 | ... BJ6: ='💰 Revenue'!BJ14 -> 384750000
A7: (-) Loyalty & promo / Giảm giá (VNĐ) | B7: =SUM(C7:AL7) -> 0 | C7: =-('💰 Revenue'!C17+'💰 Revenue'!C18) -> 0 | D7: =-('💰 Revenue'!D17+'💰 Revenue'!D18) -> 0 | E7: =-('💰 Revenue'!E17+'💰 Revenue'!E18) -> 0 | F7: =-('💰 Revenue'!F17+'💰 Revenue'!F18) -> 0 | G7: =-('💰 Revenue'!G17+'💰 Revenue'!G18) -> 0 | H7: =-('💰 Revenue'!H17+'💰 Revenue'!H18) -> 0 | I7: =-('💰 Revenue'!I17+'💰 Revenue'!I18) -> 0 | J7: =-('💰 Revenue'!J17+'💰 Revenue'!J18) -> 0 | ... BJ7: =-('💰 Revenue'!BJ17+'💰 Revenue'!BJ18) -> 0
A8: Net Revenue / Doanh thu thuần (VNĐ) | B8: =SUM(C8:BJ8) -> 23002143750 | C8: ='💰 Revenue'!C19 -> 0 | D8: ='💰 Revenue'!D19 -> 0 | E8: ='💰 Revenue'!E19 -> 125550000 | F8: ='💰 Revenue'!F19 -> 125550000 | G8: ='💰 Revenue'!G19 -> 138656250 | H8: ='💰 Revenue'!H19 -> 165656250 | I8: ='💰 Revenue'!I19 -> 291093750 | J8: ='💰 Revenue'!J19 -> 274640625 | ... BJ8: ='💰 Revenue'!BJ19 -> 384750000
A9: ── COST OF GOODS SOLD / GIÁ VỐN ──
A10: Raw Material / CP thực phẩm (VNĐ) | B10: =SUM(C10:BJ10) -> 5492001150 | C10: ='📦 COGS & OpEx'!C6 -> 0 | D10: ='📦 COGS & OpEx'!D6 -> 0 | E10: ='📦 COGS & OpEx'!E6 -> 35154000 | F10: ='📦 COGS & OpEx'!F6 -> 33145200 | G10: ='📦 COGS & OpEx'!G6 -> 36605250 | H10: ='📦 COGS & OpEx'!H6 -> 43733250 | I10: ='📦 COGS & OpEx'!I6 -> 76848750 | J10: ='📦 COGS & OpEx'!J6 -> 72505125 | ... BJ10: ='📦 COGS & OpEx'!BJ6 -> 89262000
A11: TOTAL COGS / TỔNG GIÁ VỐN (VNĐ) | B11: =SUM(C11:BJ11) -> 5492001150 | C11: ='📦 COGS & OpEx'!C7 -> 0 | D11: ='📦 COGS & OpEx'!D7 -> 0 | E11: ='📦 COGS & OpEx'!E7 -> 35154000 | F11: ='📦 COGS & OpEx'!F7 -> 33145200 | G11: ='📦 COGS & OpEx'!G7 -> 36605250 | H11: ='📦 COGS & OpEx'!H7 -> 43733250 | I11: ='📦 COGS & OpEx'!I7 -> 76848750 | J11: ='📦 COGS & OpEx'!J7 -> 72505125 | ... BJ11: ='📦 COGS & OpEx'!BJ7 -> 89262000
A12: GROSS PROFIT / LỢI NHUẬN GỘP (VNĐ) | B12: =SUM(C12:BJ12) -> 17510142600 | C12: =C8-C11 -> 0 | D12: =D8-D11 -> 0 | E12: =E8-E11 -> 90396000 | F12: =F8-F11 -> 92404800 | G12: =G8-G11 -> 102051000 | H12: =H8-H11 -> 121923000 | I12: =I8-I11 -> 214245000 | J12: =J8-J11 -> 202135500 | ... BJ12: =BJ8-BJ11 -> 295488000
A13: Gross Margin % | B13: =AVERAGE(C13:BJ13) -> 0.75889655 | C13: =IFERROR(C12/C8,"-") -> - | D13: =IFERROR(D12/D8,"-") -> - | E13: =IFERROR(E12/E8,"-") -> 0.72 | F13: =IFERROR(F12/F8,"-") -> 0.736 | G13: =IFERROR(G12/G8,"-") -> 0.736 | H13: =IFERROR(H12/H8,"-") -> 0.736 | I13: =IFERROR(I12/I8,"-") -> 0.736 | J13: =IFERROR(J12/J8,"-") -> 0.736 | ... BJ13: =IFERROR(BJ12/BJ8,"-") -> 0.768
A14: ── OPERATING EXPENSES / CHI PHÍ VẬN HÀNH ──
A15: Rent / Thuê mặt bằng (VNĐ) | B15: =SUM(C15:BJ15) -> 3392500000 | C15: ='📦 COGS & OpEx'!D8 -> 0 | D15: ='📦 COGS & OpEx'!D9 -> 57500000 | E15: ='📦 COGS & OpEx'!E9 -> 57500000 | F15: ='📦 COGS & OpEx'!F9 -> 57500000 | G15: ='📦 COGS & OpEx'!G9 -> 57500000 | H15: ='📦 COGS & OpEx'!H9 -> 57500000 | I15: ='📦 COGS & OpEx'!I9 -> 57500000 | J15: ='📦 COGS & OpEx'!J9 -> 57500000 | K15: ='📦 COGS & OpEx'!K9 -> 57500000 | ... BJ15: ='📦 COGS & OpEx'!BJ9 -> 57500000
A16: Payroll / Lương (VNĐ) | B16: =SUM(C16:BJ16) -> 2217772000 | C16: ='📦 COGS & OpEx'!C17 -> 0 | D16: ='📦 COGS & OpEx'!D17 -> 0 | E16: ='📦 COGS & OpEx'!E17 -> 28276000 | F16: ='📦 COGS & OpEx'!F17 -> 28276000 | G16: ='📦 COGS & OpEx'!G17 -> 27484000 | H16: ='📦 COGS & OpEx'!H17 -> 28276000 | I16: ='📦 COGS & OpEx'!I17 -> 33820000 | J16: ='📦 COGS & OpEx'!J17 -> 34414000 | ... BJ16: ='📦 COGS & OpEx'!BJ17 -> 39760000
A17: Utilities / Điện nước (VNĐ) | B17: =SUM(C17:BJ17) -> 1.478579e+09 | C17: ='📦 COGS & OpEx'!D9 -> 57500000 | D17: ='📦 COGS & OpEx'!D10 -> 0 | E17: ='📦 COGS & OpEx'!E10 -> 6403050 | F17: ='📦 COGS & OpEx'!F10 -> 6403050 | G17: ='📦 COGS & OpEx'!G10 -> 7626093.8 | H17: ='📦 COGS & OpEx'!H10 -> 9111093.8 | I17: ='📦 COGS & OpEx'!I10 -> 16010156 | J17: ='📦 COGS & OpEx'!J10 -> 15105234 | K17: ='📦 COGS & OpEx'!K10 -> 24300000 | ... BJ17: ='📦 COGS & OpEx'!BJ10 -> 26547750
A18: Repairs / Sửa chữa (VNĐ) | B18: =SUM(C18:BJ18) -> 7.1112094e+08 | C18: ='📦 COGS & OpEx'!C15 -> 0 | D18: ='📦 COGS & OpEx'!D15 -> 0 | E18: ='📦 COGS & OpEx'!E15 -> 1255500 | F18: ='📦 COGS & OpEx'!F15 -> 1255500 | G18: ='📦 COGS & OpEx'!G15 -> 1386562.5 | H18: ='📦 COGS & OpEx'!H15 -> 1656562.5 | I18: ='📦 COGS & OpEx'!I15 -> 2910937.5 | J18: ='📦 COGS & OpEx'!J15 -> 2746406.2 | ... BJ18: ='📦 COGS & OpEx'!BJ15 -> 15390000
A19: Marketing (VNĐ) | B19: =SUM(C19:BJ19) -> 805395375 | C19: ='📦 COGS & OpEx'!C18 -> 0 | D19: ='📦 COGS & OpEx'!D18 -> 0 | E19: ='📦 COGS & OpEx'!E18 -> 25110000 | F19: ='📦 COGS & OpEx'!F18 -> 25110000 | G19: ='📦 COGS & OpEx'!G18 -> 11092500 | H19: ='📦 COGS & OpEx'!H18 -> 13252500 | I19: ='📦 COGS & OpEx'!I18 -> 23287500 | J19: ='📦 COGS & OpEx'!J18 -> 21971250 | ... BJ19: ='📦 COGS & OpEx'!BJ18 -> 11542500
A20: Loyalty & promo cost / CP khuyến mại (VNĐ) | B20: =SUM(C20:AL20) -> 0 | C20: ='📦 COGS & OpEx'!C22 -> 0 | D20: ='📦 COGS & OpEx'!D22 -> 0 | E20: ='📦 COGS & OpEx'!E22 -> 0 | F20: ='📦 COGS & OpEx'!F22 -> 0 | G20: ='📦 COGS & OpEx'!G22 -> 0 | H20: ='📦 COGS & OpEx'!H22 -> 0 | I20: ='📦 COGS & OpEx'!I22 -> 0 | J20: ='📦 COGS & OpEx'!J22 -> 0 | ... BJ20: ='📦 COGS & OpEx'!BJ22 -> 0
A21: Contingency / Dự phòng (VNĐ) | B21: =SUM(C21:BJ21) -> 1.7210735e+08 | C21: ='📦 COGS & OpEx'!C25 -> 1150000 | D21: ='📦 COGS & OpEx'!D25 -> 1150000 | E21: ='📦 COGS & OpEx'!E25 -> 2370891 | F21: ='📦 COGS & OpEx'!F25 -> 2370891 | G21: ='📦 COGS & OpEx'!G25 -> 2101783.1 | H21: ='📦 COGS & OpEx'!H25 -> 2195923.1 | I21: ='📦 COGS & OpEx'!I25 -> 2670571.9 | J21: ='📦 COGS & OpEx'!J25 -> 2634737.8 | ... BJ21: ='📦 COGS & OpEx'!BJ25 -> 3014805
A22: Management fee / Phí quản lý (VNĐ) | B22: =SUM(C22:BJ22) -> 2.5816102e+08 | C22: ='📦 COGS & OpEx'!C26 -> 1725000 | D22: ='📦 COGS & OpEx'!D26 -> 1725000 | E22: ='📦 COGS & OpEx'!E26 -> 3556336.5 | F22: ='📦 COGS & OpEx'!F26 -> 3556336.5 | G22: ='📦 COGS & OpEx'!G26 -> 3152674.7 | H22: ='📦 COGS & OpEx'!H26 -> 3293884.7 | I22: ='📦 COGS & OpEx'!I26 -> 4005857.8 | J22: ='📦 COGS & OpEx'!J26 -> 3952106.7 | ... BJ22: ='📦 COGS & OpEx'!BJ26 -> 4522207.5
A23: Depreciation / Khấu hao (VNĐ) | B23: =SUM(C23:BJ23) -> 300000000 | C23: ='📦 COGS & OpEx'!C30 -> 5000000 | D23: ='📦 COGS & OpEx'!D30 -> 5000000 | E23: ='📦 COGS & OpEx'!E30 -> 5000000 | F23: ='📦 COGS & OpEx'!F30 -> 5000000 | G23: ='📦 COGS & OpEx'!G30 -> 5000000 | H23: ='📦 COGS & OpEx'!H30 -> 5000000 | I23: ='📦 COGS & OpEx'!I30 -> 5000000 | J23: ='📦 COGS & OpEx'!J30 -> 5000000 | ... BJ23: ='📦 COGS & OpEx'!BJ30 -> 5000000
A24: Interest expense / Chi phí lãi vay (VNĐ) | B24: =SUM(C24:BJ24) -> 93981133 | C24: ='🏦 Loan Schedule'!D14 -> 3386250 | D24: ='🏦 Loan Schedule'!D15 -> 3303965 | E24: ='🏦 Loan Schedule'!D16 -> 3221062.9 | F24: ='🏦 Loan Schedule'!D17 -> 3137539.1 | G24: ='🏦 Loan Schedule'!D18 -> 3053388.7 | H24: ='🏦 Loan Schedule'!D19 -> 2968607.3 | I24: ='🏦 Loan Schedule'!D20 -> 2883190 | J24: ='🏦 Loan Schedule'!D21 -> 2797132.1 | K24: ='🏦 Loan Schedule'!D22 -> 2710428.8 | L24: ='🏦 Loan Schedule'!D23 -> 2623075.1 | M24: ='🏦 Loan Schedule'!D24 -> 2535066.3 | N24: ='🏦 Loan Schedule'!D25 -> 2446397.5 | O24: ='🏦 Loan Schedule'!D26 -> 2357063.6 | P24: ='🏦 Loan Schedule'!D27 -> 2267059.8 | Q24: ='🏦 Loan Schedule'!D28 -> 2176380.9 | R24: ='🏦 Loan Schedule'!D29 -> 2085021.9 | S24: ='🏦 Loan Schedule'!D30 -> 1992977.7 | T24: ='🏦 Loan Schedule'!D31 -> 1900243.2 | U24: ='🏦 Loan Schedule'!D32 -> 1806813.2 | V24: ='🏦 Loan Schedule'!D33 -> 1712682.4 | W24: ='🏦 Loan Schedule'!D34 -> 1617845.7 | X24: ='🏦 Loan Schedule'!D35 -> 1522297.7 | Y24: ='🏦 Loan Schedule'!D36 -> 1426033.1 | Z24: ='🏦 Loan Schedule'!D37 -> 1329046.5 | AA24: ='🏦 Loan Schedule'!D38 -> 1231332.5 | AB24: ='🏦 Loan Schedule'!D39 -> 1132885.6 | AC24: ='🏦 Loan Schedule'!D40 -> 1033700.4 | AD24: ='🏦 Loan Schedule'!D41 -> 933771.35 | AE24: ='🏦 Loan Schedule'!D42 -> 833092.79 | AF24: ='🏦 Loan Schedule'!D43 -> 731659.14 | AG24: ='🏦 Loan Schedule'!D44 -> 629464.74 | AH24: ='🏦 Loan Schedule'!D45 -> 526503.88 | AI24: ='🏦 Loan Schedule'!D46 -> 422770.81 | AJ24: ='🏦 Loan Schedule'!D47 -> 318259.75 | AK24: ='🏦 Loan Schedule'!D48 -> 212964.85 | AL24: ='🏦 Loan Schedule'!D49 -> 106880.24 | AM24: ='🏦 Loan Schedule'!E49 -> 14250699 | AN24: ='🏦 Loan Schedule'!F49 -> 14357579 | AO24: ='🏦 Loan Schedule'!G49 -> 0 | AP24: ='🏦 Loan Schedule'!H49 -> 0 | AQ24: ='🏦 Loan Schedule'!I49 -> 0 | AR24: ='🏦 Loan Schedule'!J49 -> 0 | AS24: ='🏦 Loan Schedule'!K49 -> 0 | ... BJ24: ='🏦 Loan Schedule'!AB49 -> 0
A25: TOTAL OPEX / TỔNG CP VẬN HÀNH (VNĐ) | B25: =SUM(C25:BJ25) -> 9.4296168e+09 | C25: =C15+C16+C17+C18+C19+C20+C21+C22+C23+C24 -> 68761250 | D25: =D15+D16+D17+D18+D19+D20+D21+D22+D23+D24 -> 68678965 | E25: =E15+E16+E17+E18+E19+E20+E21+E22+E23+E24 -> 1.3269284e+08 | F25: =F15+F16+F17+F18+F19+F20+F21+F22+F23+F24 -> 1.3260932e+08 | G25: =G15+G16+G17+G18+G19+G20+G21+G22+G23+G24 -> 1.18397e+08 | H25: =H15+H16+H17+H18+H19+H20+H21+H22+H23+H24 -> 1.2325457e+08 | I25: =I15+I16+I17+I18+I19+I20+I21+I22+I23+I24 -> 1.4808821e+08 | J25: =J15+J16+J17+J18+J19+J20+J21+J22+J23+J24 -> 1.4612087e+08 | ... BJ25: =BJ15+BJ16+BJ17+BJ18+BJ19+BJ20+BJ21+BJ22+BJ23+BJ24 -> 1.6327726e+08
A26: EBITDA (VNĐ) | B26: =SUM(C26:BJ26) -> 8.4745069e+09 | C26: =C12-C25+C23+C24 -> -60375000 | D26: =D12-D25+D23+D24 -> -60375000 | E26: =E12-E25+E23+E24 -> -34075778 | F26: =F12-F25+F23+F24 -> -32066978 | G26: =G12-G25+G23+G24 -> -8292614.1 | H26: =H12-H25+H23+H24 -> 6637035.9 | I26: =I12-I25+I23+I24 -> 74039977 | J26: =J12-J25+J23+J24 -> 63811765 | ... BJ26: =BJ12-BJ25+BJ23+BJ24 -> 1.3721074e+08
A27: EBITDA Margin % | B27: ="" | C27: =IFERROR(C26/C8,"-") -> - | D27: =IFERROR(D26/D8,"-") -> - | E27: =IFERROR(E26/E8,"-") -> -0.27141201 | F27: =IFERROR(F26/F8,"-") -> -0.25541201 | G27: =IFERROR(G26/G8,"-") -> -0.059806998 | H27: =IFERROR(H26/H8,"-") -> 0.04006511 | I27: =IFERROR(I26/I8,"-") -> 0.25435097 | J27: =IFERROR(J26/J8,"-") -> 0.23234642 | ... BJ27: =IFERROR(BJ26/BJ8,"-") -> 0.3566231
A28: EBIT (VNĐ) | B28: =SUM(C28:BJ28) -> 8.0805258e+09 | C28: =C12-C25 -> -68761250 | D28: =D12-D25 -> -68678965 | E28: =E12-E25 -> -42296840 | F28: =F12-F25 -> -40204517 | G28: =G12-G25 -> -16346003 | H28: =H12-H25 -> -1331571.4 | I28: =I12-I25 -> 66156787 | J28: =J12-J25 -> 56014633 | ... BJ28: =BJ12-BJ25 -> 1.3221074e+08
A29: EBIT Margin % | B29: ="" | C29: =IFERROR(C28/C8,"-") -> - | D29: =IFERROR(D28/D8,"-") -> - | E29: =IFERROR(E28/E8,"-") -> -0.3368924 | F29: =IFERROR(F28/F8,"-") -> -0.32022713 | G29: =IFERROR(G28/G8,"-") -> -0.11788868 | H29: =IFERROR(H28/H8,"-") -> -0.0080381596 | I29: =IFERROR(I28/I8,"-") -> 0.22726969 | J29: =IFERROR(J28/J8,"-") -> 0.20395611 | ... BJ29: =IFERROR(BJ28/BJ8,"-") -> 0.34362765
A30: ── TAX & NET INCOME / THUẾ & LỢI NHUẬN SAU THUẾ ──
A31: (-) Income Tax / Thuế TNDN (VNĐ) | B31: =SUM(C31:BJ31) -> 8.318145e+08 | C31: =MAX(0,C28)*0.1 -> 0 | D31: =MAX(0,D28)*0.1 -> 0 | E31: =MAX(0,E28)*0.1 -> 0 | F31: =MAX(0,F28)*0.1 -> 0 | G31: =MAX(0,G28)*0.1 -> 0 | H31: =MAX(0,H28)*0.1 -> 0 | I31: =MAX(0,I28)*0.1 -> 6615678.7 | J31: =MAX(0,J28)*0.1 -> 5601463.3 | ... BJ31: =MAX(0,BJ28)*0.1 -> 13221074
A32: NET PROFIT AFTER TAX / LNST (VNĐ) | B32: =SUM(C32:BJ32) -> 7.2487113e+09 | C32: =C28-C31 -> -68761250 | D32: =D28-D31 -> -68678965 | E32: =E28-E31 -> -42296840 | F32: =F28-F31 -> -40204517 | G32: =G28-G31 -> -16346003 | H32: =H28-H31 -> -1331571.4 | I32: =I28-I31 -> 59541108 | J32: =J28-J31 -> 50413169 | ... BJ32: =BJ28-BJ31 -> 1.1898966e+08
A33: Net Margin % | B33: =AVERAGE(C33:BJ33) -> 0.29062043 | C33: =IFERROR(C32/C8,"-") -> - | D33: =IFERROR(D32/D8,"-") -> - | E33: =IFERROR(E32/E8,"-") -> -0.3368924 | F33: =IFERROR(F32/F8,"-") -> -0.32022713 | G33: =IFERROR(G32/G8,"-") -> -0.11788868 | H33: =IFERROR(H32/H8,"-") -> -0.0080381596 | I33: =IFERROR(I32/I8,"-") -> 0.20454272 | J33: =IFERROR(J32/J8,"-") -> 0.1835605 | ... BJ33: =IFERROR(BJ32/BJ8,"-") -> 0.30926488
A35: ── ANNUAL SUMMARY / TÓM TẮT THEO NĂM ──
A36: Year 1 – Revenue / DT | B36: =SUM(C8:N8) -> 2424571875
A37: Year 1 – Gross Profit / LN Gộp | B37: =SUM(C12:N12) -> 1782476100
A38: Year 1 – EBITDA | B38: =SUM(C26:N26) -> 3.3915028e+08
A39: Year 1 – EBIT | B39: =SUM(C28:N28) -> 2.4408417e+08
A40: Year 1 – NPAT / LNST | B40: =SUM(C32:N32) -> 1.9591384e+08
A41: Year 2 – Revenue / DT | B41: =SUM(O8:Z8) -> 4900696875
A42: Year 2 – Gross Profit / LN Gộp | B42: =SUM(O12:Z12) -> 3698426700
A43: Year 2 – EBITDA | B43: =SUM(O26:Z26) -> 1.8833535e+09
A44: Year 2 – EBIT | B44: =SUM(O28:Z28) -> 1.8011601e+09
A45: Year 2 – NPAT / LNST | B45: =SUM(O32:Z32) -> 1.6210441e+09
A46: Year 3 – Revenue / DT | B46: =SUM(AA8:AL8) -> 5221800000
A47: Year 3 – Gross Profit / LN Gộp | B47: =SUM(AA12:AL12) -> 3999742200
A48: Year 3 – EBITDA | B48: =SUM(AA26:AL26) -> 2100050280
A49: Year 3 – EBIT | B49: =SUM(AA28:AL28) -> 2.031937e+09
A50: Year 3 – NPAT / LNST | B50: =SUM(AA32:AL32) -> 1.8287433e+09

Sheet 💵 Cash Flow
A1: CASH FLOW STATEMENT / BÁO CÁO DÒNG TIỀN
B2: TOTAL / TỔNG | C2: YEAR 1 / NĂM 1 | O2: YEAR 2 / NĂM 2 | AA2: YEAR 3 / NĂM 3
C3: 1 | D3: 2 | E3: 3 | F3: 4 | G3: 5 | H3: 6 | I3: 7 | J3: 8 | K3: 9 | L3: 10 | M3: 11 | N3: 12 | O3: 13 | P3: 14 | Q3: 15 | R3: 16 | S3: 17 | T3: 18 | U3: 19 | V3: 20 | W3: 21 | X3: 22 | Y3: 23 | Z3: 24 | AA3: 25 | AB3: 26 | AC3: 27 | AD3: 28 | AE3: 29 | AF3: 30 | AG3: 31 | AH3: 32 | AI3: 33 | AJ3: 34 | AK3: 35 | AL3: 36 | AM3: 37 | AN3: 38 | AO3: 39 | AP3: 40 | AQ3: 41 | AR3: 42 | AS3: 43 | AT3: 44 | AU3: 45 | AV3: 46 | AW3: 47 | AX3: 48 | AY3: 49 | AZ3: 50 | BA3: 51 | BB3: 52 | BC3: 53 | BD3: 54 | BE3: 55 | BF3: 56 | BG3: 57 | BH3: 58 | BI3: 59 | BJ3: 60
C4: M01 | D4: M02 | E4: M03 | F4: M04 | G4: M05 | H4: M06 | I4: M07 | J4: M08 | K4: M09 | L4: M10 | M4: M11 | N4: M12 | O4: M13 | P4: M14 | Q4: M15 | R4: M16 | S4: M17 | T4: M18 | U4: M19 | V4: M20 | W4: M21 | X4: M22 | Y4: M23 | Z4: M24 | AA4: M25 | AB4: M26 | AC4: M27 | AD4: M28 | AE4: M29 | AF4: M30 | AG4: M31 | AH4: M32 | AI4: M33 | AJ4: M34 | AK4: M35 | AL4: M36 | AM4: M37 | AN4: M38 | AO4: M39 | AP4: M40 | AQ4: M41 | AR4: M42 | AS4: M43 | AT4: M44 | AU4: M45 | AV4: M46 | AW4: M47 | AX4: M48 | AY4: M49 | AZ4: M50 | BA4: M51 | BB4: M52 | BC4: M53 | BD4: M54 | BE4: M55 | BF4: M56 | BG4: M57 | BH4: M58 | BI4: M59 | BJ4: M60
A5: LINE ITEM / CHỈ TIÊU | B5: 5-YEAR TOTAL / TỔNG 5 NĂM | C5: ='⚙️ Assumptions'!B6 -> 46661 | D5: =EDATE($C$5,'💰 Revenue'!D2) -> 46692 | E5: =EDATE($C$5,'💰 Revenue'!E2) -> 46722 | F5: =EDATE($C$5,'💰 Revenue'!F2) -> 46753 | G5: =EDATE($C$5,'💰 Revenue'!G2) -> 46784 | H5: =EDATE($C$5,'💰 Revenue'!H2) -> 46813 | I5: =EDATE($C$5,'💰 Revenue'!I2) -> 46844 | J5: =EDATE($C$5,'💰 Revenue'!J2) -> 46874 | K5: =EDATE($C$5,'💰 Revenue'!K2) -> 46905 | ... BJ5: =EDATE($C$5,'💰 Revenue'!BJ2) -> 48458
A6: ── A. OPERATING ACTIVITIES / HOẠT ĐỘNG KINH DOANH ──
A7: Net Profit After Tax / LNST (VNĐ) | B7: =SUM(C7:BJ7) -> 7.2487113e+09 | C7: ='📊 P&L Detail'!C32 -> -68761250 | D7: ='📊 P&L Detail'!D32 -> -68678965 | E7: ='📊 P&L Detail'!E32 -> -42296840 | F7: ='📊 P&L Detail'!F32 -> -40204517 | G7: ='📊 P&L Detail'!G32 -> -16346003 | H7: ='📊 P&L Detail'!H32 -> -1331571.4 | I7: ='📊 P&L Detail'!I32 -> 59541108 | J7: ='📊 P&L Detail'!J32 -> 50413169 | ... BJ7: ='📊 P&L Detail'!BJ32 -> 1.1898966e+08
A8: (+) Add-back: Depreciation / Cộng lại Khấu hao (VNĐ) | B8: =SUM(C8:AL8) -> 180000000 | C8: ='📦 COGS & OpEx'!C30 -> 5000000 | D8: ='📦 COGS & OpEx'!D30 -> 5000000 | E8: ='📦 COGS & OpEx'!E30 -> 5000000 | F8: ='📦 COGS & OpEx'!F30 -> 5000000 | G8: ='📦 COGS & OpEx'!G30 -> 5000000 | H8: ='📦 COGS & OpEx'!H30 -> 5000000 | I8: ='📦 COGS & OpEx'!I30 -> 5000000 | J8: ='📦 COGS & OpEx'!J30 -> 5000000 | ... BJ8: ='📦 COGS & OpEx'!BJ30 -> 5000000
A9: (+) Add-back: Interest (net) / Cộng lại lãi vay (VNĐ) | B9: =SUM(C9:AL9) -> 65372855 | C9: ='📊 P&L Detail'!C24 -> 3386250 | D9: ='📊 P&L Detail'!D24 -> 3303965 | E9: ='📊 P&L Detail'!E24 -> 3221062.9 | F9: ='📊 P&L Detail'!F24 -> 3137539.1 | G9: ='📊 P&L Detail'!G24 -> 3053388.7 | H9: ='📊 P&L Detail'!H24 -> 2968607.3 | I9: ='📊 P&L Detail'!I24 -> 2883190 | J9: ='📊 P&L Detail'!J24 -> 2797132.1 | ... BJ9: ='📊 P&L Detail'!BJ24 -> 0
A10: Changes in working capital / Thay đổi vốn lưu động (VNĐ) | B10: =SUM(C10:AL10) -> 0
A11: OPERATING CASH FLOW / DÒNG TIỀN HOẠT ĐỘNG (VNĐ) | B11: =SUM(C11:AL11) -> 3.8910741e+09 | C11: =C7+C8+C9+C10 -> -60375000 | D11: =D7+D8+D9+D10 -> -60375000 | E11: =E7+E8+E9+E10 -> -34075778 | F11: =F7+F8+F9+F10 -> -32066978 | G11: =G7+G8+G9+G10 -> -8292614.1 | H11: =H7+H8+H9+H10 -> 6637035.9 | I11: =I7+I8+I9+I10 -> 67424298 | J11: =J7+J8+J9+J10 -> 58210302 | ... BJ11: =BJ7+BJ8+BJ9+BJ10 -> 1.2398966e+08
A12: ── B. INVESTING ACTIVITIES / HOẠT ĐỘNG ĐẦU TƯ ──
A13: (-) Capex / Chi đầu tư (VNĐ) | B13: =SUM(C13:AL13) -> -300000000 | C13: =-'📦 COGS & OpEx'!$C$29 -> -300000000 | E13: =-'📦 COGS & OpEx'!E29 -> 0 | F13: =-'📦 COGS & OpEx'!F29 -> 0 | G13: =-'📦 COGS & OpEx'!G29 -> 0 | H13: =-'📦 COGS & OpEx'!H29 -> 0 | I13: =-'📦 COGS & OpEx'!I29 -> 0 | J13: =-'📦 COGS & OpEx'!J29 -> 0 | K13: =-'📦 COGS & OpEx'!K29 -> 0 | L13: =-'📦 COGS & OpEx'!L29 -> 0 | ... BJ13: =-'📦 COGS & OpEx'!BJ29 -> 0
A14: =" (-) Deposit " & '⚙️ Assumptions'!B11& " month rent" -> (-) Deposit 6 month rent | C14: =-'⚙️ Assumptions'!$B$17 -> -345000000
A15: (+) Asset disposal / Thu hồi cuối dự án (VNĐ) | B15: =SUM(C15:AL15) -> 0 | C15: ='💰 Revenue'!C27 -> 0 | D15: ='💰 Revenue'!D27 -> 0 | E15: ='💰 Revenue'!E27 -> 0 | F15: ='💰 Revenue'!F27 -> 0 | G15: ='💰 Revenue'!G27 -> 0 | H15: ='💰 Revenue'!H27 -> 0 | I15: ='💰 Revenue'!I27 -> 0 | J15: ='💰 Revenue'!J27 -> 0 | ... AK15: ='💰 Revenue'!AK27 -> 0
A16: INVESTING CASH FLOW / DÒNG TIỀN ĐẦU TƯ (VNĐ) | B16: =SUM(C16:AL16) -> -645000000 | C16: =C13+C14+C15 -> -645000000 | D16: =D13+D15 -> 0 | E16: =E13+E15 -> 0 | F16: =F13+F15 -> 0 | G16: =G13+G15 -> 0 | H16: =H13+H15 -> 0 | I16: =I13+I15 -> 0 | J16: =J13+J15 -> 0 | K16: =K13+K15 -> 0 | ... BJ16: =BJ13+BJ15 -> 0
A17: ── C. FINANCING ACTIVITIES / HOẠT ĐỘNG TÀI CHÍNH ──
A18: (+) Loan drawdown / Giải ngân vay (VNĐ) | B18: =SUM(C18:AL18) -> 451500000 | C18: ='🏦 Loan Schedule'!B6 -> 451500000
A19: (-) Loan repayment / Trả nợ gốc (VNĐ) | B19: =SUM(C19:AL19) -> -451500000 | C19: =-'🏦 Loan Schedule'!E14 -> -10971329 | D19: =-'🏦 Loan Schedule'!E15 -> -11053614 | E19: =-'🏦 Loan Schedule'!E16 -> -11136516 | F19: =-'🏦 Loan Schedule'!E17 -> -11220040 | G19: =-'🏦 Loan Schedule'!E18 -> -11304191 | H19: =-'🏦 Loan Schedule'!E19 -> -11388972 | I19: =-'🏦 Loan Schedule'!E20 -> -11474389 | J19: =-'🏦 Loan Schedule'!E21 -> -11560447 | K19: =-'🏦 Loan Schedule'!E22 -> -11647151 | L19: =-'🏦 Loan Schedule'!E23 -> -11734504 | M19: =-'🏦 Loan Schedule'!E24 -> -11822513 | N19: =-'🏦 Loan Schedule'!E25 -> -11911182 | O19: =-'🏦 Loan Schedule'!E26 -> -12000516 | P19: =-'🏦 Loan Schedule'!E27 -> -12090520 | Q19: =-'🏦 Loan Schedule'!E28 -> -12181198 | R19: =-'🏦 Loan Schedule'!E29 -> -12272557 | S19: =-'🏦 Loan Schedule'!E30 -> -12364602 | T19: =-'🏦 Loan Schedule'!E31 -> -12457336 | U19: =-'🏦 Loan Schedule'!E32 -> -12550766 | V19: =-'🏦 Loan Schedule'!E33 -> -12644897 | W19: =-'🏦 Loan Schedule'!E34 -> -12739734 | X19: =-'🏦 Loan Schedule'!E35 -> -12835282 | Y19: =-'🏦 Loan Schedule'!E36 -> -12931546 | Z19: =-'🏦 Loan Schedule'!E37 -> -13028533 | AA19: =-'🏦 Loan Schedule'!E38 -> -13126247 | AB19: =-'🏦 Loan Schedule'!E39 -> -13224694 | AC19: =-'🏦 Loan Schedule'!E40 -> -13323879 | AD19: =-'🏦 Loan Schedule'!E41 -> -13423808 | AE19: =-'🏦 Loan Schedule'!E42 -> -13524487 | AF19: =-'🏦 Loan Schedule'!E43 -> -13625920 | AG19: =-'🏦 Loan Schedule'!E44 -> -13728115 | AH19: =-'🏦 Loan Schedule'!E45 -> -13831075 | AI19: =-'🏦 Loan Schedule'!E46 -> -13934808 | AJ19: =-'🏦 Loan Schedule'!E47 -> -14039320 | AK19: =-'🏦 Loan Schedule'!E48 -> -14144614 | AL19: =-'🏦 Loan Schedule'!E49 -> -14250699 | AM19: =-'🏦 Loan Schedule'!F49 -> -14357579 | AN19: =-'🏦 Loan Schedule'!G49 -> 0 | AO19: =-'🏦 Loan Schedule'!H49 -> 0 | AP19: =-'🏦 Loan Schedule'!I49 -> 0 | AQ19: =-'🏦 Loan Schedule'!J49 -> 0 | AR19: =-'🏦 Loan Schedule'!K49 -> 0 | AS19: =-'🏦 Loan Schedule'!L49 -> 0 | ... BJ19: =-'🏦 Loan Schedule'!AC49 -> 0
A20: (-) Interest paid / Trả lãi vay (VNĐ) | B20: =SUM(C20:AL20) -> -65372855 | C20: =-'🏦 Loan Schedule'!D14 -> -3386250 | D20: =-'🏦 Loan Schedule'!D15 -> -3303965 | E20: =-'🏦 Loan Schedule'!D16 -> -3221062.9 | F20: =-'🏦 Loan Schedule'!D17 -> -3137539.1 | G20: =-'🏦 Loan Schedule'!D18 -> -3053388.7 | H20: =-'🏦 Loan Schedule'!D19 -> -2968607.3 | I20: =-'🏦 Loan Schedule'!D20 -> -2883190 | J20: =-'🏦 Loan Schedule'!D21 -> -2797132.1 | K20: =-'🏦 Loan Schedule'!D22 -> -2710428.8 | L20: =-'🏦 Loan Schedule'!D23 -> -2623075.1 | M20: =-'🏦 Loan Schedule'!D24 -> -2535066.3 | N20: =-'🏦 Loan Schedule'!D25 -> -2446397.5 | O20: =-'🏦 Loan Schedule'!D26 -> -2357063.6 | P20: =-'🏦 Loan Schedule'!D27 -> -2267059.8 | Q20: =-'🏦 Loan Schedule'!D28 -> -2176380.9 | R20: =-'🏦 Loan Schedule'!D29 -> -2085021.9 | S20: =-'🏦 Loan Schedule'!D30 -> -1992977.7 | T20: =-'🏦 Loan Schedule'!D31 -> -1900243.2 | U20: =-'🏦 Loan Schedule'!D32 -> -1806813.2 | V20: =-'🏦 Loan Schedule'!D33 -> -1712682.4 | W20: =-'🏦 Loan Schedule'!D34 -> -1617845.7 | X20: =-'🏦 Loan Schedule'!D35 -> -1522297.7 | Y20: =-'🏦 Loan Schedule'!D36 -> -1426033.1 | Z20: =-'🏦 Loan Schedule'!D37 -> -1329046.5 | AA20: =-'🏦 Loan Schedule'!D38 -> -1231332.5 | AB20: =-'🏦 Loan Schedule'!D39 -> -1132885.6 | AC20: =-'🏦 Loan Schedule'!D40 -> -1033700.4 | AD20: =-'🏦 Loan Schedule'!D41 -> -933771.35 | AE20: =-'🏦 Loan Schedule'!D42 -> -833092.79 | AF20: =-'🏦 Loan Schedule'!D43 -> -731659.14 | AG20: =-'🏦 Loan Schedule'!D44 -> -629464.74 | AH20: =-'🏦 Loan Schedule'!D45 -> -526503.88 | AI20: =-'🏦 Loan Schedule'!D46 -> -422770.81 | AJ20: =-'🏦 Loan Schedule'!D47 -> -318259.75 | AK20: =-'🏦 Loan Schedule'!D48 -> -212964.85 | AL20: =-'🏦 Loan Schedule'!D49 -> -106880.24 | AM20: =-'🏦 Loan Schedule'!E49 -> -14250699 | AN20: =-'🏦 Loan Schedule'!F49 -> -14357579 | AO20: =-'🏦 Loan Schedule'!G49 -> 0 | AP20: =-'🏦 Loan Schedule'!H49 -> 0 | AQ20: =-'🏦 Loan Schedule'!I49 -> 0 | AR20: =-'🏦 Loan Schedule'!J49 -> 0 | AS20: =-'🏦 Loan Schedule'!K49 -> 0 | ... BJ20: =-'🏦 Loan Schedule'!AB49 -> 0
A21: (+) Equity injection / Vốn chủ góp (VNĐ) | B21: =SUM(C21:AL21) -> 4.6047327e+08 | C21: =IF(C18=0,'⚙️ Assumptions'!$B$18 *1,('⚙️ Assumptions'!$B$18*(1-'🏦 Loan Schedule'!B5))) +'⚙️ Assumptions'!B14 -> 4.6047327e+08
A22: FINANCING CASH FLOW / DÒNG TIỀN TÀI CHÍNH (VNĐ) | B22: =SUM(C22:AL22) -> 3.9510041e+08 | C22: =C18+C19+C20+C21 -> 8.9761569e+08 | D22: =D18+D19+D20+D21 -> -14357579 | E22: =E18+E19+E20+E21 -> -14357579 | F22: =F18+F19+F20+F21 -> -14357579 | G22: =G18+G19+G20+G21 -> -14357579 | H22: =H18+H19+H20+H21 -> -14357579 | I22: =I18+I19+I20+I21 -> -14357579 | J22: =J18+J19+J20+J21 -> -14357579 | ... BJ22: =BJ18+BJ19+BJ20+BJ21 -> 0
A23: ── D. NET CASH POSITION / DÒNG TIỀN THUẦN ──
A24: NET CASH FLOW / DÒNG TIỀN THUẦN (VNĐ) | B24: =SUM(C24:AL24) -> 3.6411745e+09 | C24: =C11+C16+C22 -> 1.9224069e+08 | D24: =D11+D16+D22 -> -74732579 | E24: =E11+E16+E22 -> -48433357 | F24: =F11+F16+F22 -> -46424557 | G24: =G11+G16+G22 -> -22650193 | H24: =H11+H16+H22 -> -7720543.4 | I24: =I11+I16+I22 -> 53066719 | J24: =J11+J16+J22 -> 43852722 | ... BJ24: =BJ11+BJ16+BJ22 -> 1.2398966e+08
A25: Cumulative Cash Flow / Dòng tiền luỹ kế (VNĐ) | B25: =AL25 -> 3.6411745e+09 | C25: =C24 -> 1.9224069e+08 | D25: =D24+C25 -> 1.1750811e+08 | E25: =E24+D25 -> 69074750 | F25: =F24+E25 -> 22650193 | G25: =G24+F25 -> 0 | H25: =H24+G25 -> -7720543.4 | I25: =I24+H25 -> 45346175 | J25: =J24+I25 -> 89198898 | K25: =K24+J25 -> 1.5341286e+08 | ... BJ25: =BJ24+BI25 -> 7.349827e+09
A26: ── E. RETURNS SUMMARY / TÓM TẮT LỢI NHUẬN ĐẦU TƯ ──
A27: Total Capex invested / Tổng vốn bỏ ra (VNĐ) | B27: =B21 -> 4.6047327e+08
A28: Total NPAT 5Y / Tổng LNST 5 năm (VNĐ) | B28: =SUM(C7:BJ7) -> 7.2487113e+09
A29: Total Net Cash Flow / Tổng dòng tiền thuần (VNĐ)
A30: ROI cumulative | B30: =($B$7 * 0.8 + $B$8 - $B$27)/B27 -> 11.9844
A31: Annualized ROI | B31: =(1 + B30)^(1/5)-1 -> 0.66987659
A32: Payback month / Tháng hoàn vốn | B32: =_xlfn.LET( _xlpm.Last_neg_month, _xlfn.XLOOKUP(-1,SIGN($C$25:$BJ$25),$C$3:$BJ$3,"No Negative",0,-1), _xlpm.Last_neg_month_val, _xlfn.XLOOKUP(-1,SIGN($C$25:$BJ$25),$C$25:$BJ$25,"No Negative",0,-1), _xlpm.First_turn_pos_month_val, _xlfn.XLOOKUP(1,SIGN($C$25:$BJ$25),$C$24:$BJ$24,"No Negative",0,1), _xlpm.Last_neg_month + (_xlpm.Last_neg_month_val*-1)/_xlpm.First_turn_pos_month_val ) -> 6.0401608
A33: IRR | B33: =IRR($C$24:$BJ$24,0.1) -> #N/A
A34: Break-even
A37: CASH POSITION
B38: M00 | C38: M01 | D38: M02 | E38: M03 | F38: M04 | G38: M05 | H38: M06 | I38: M07 | J38: M08 | K38: M09 | L38: M10 | M38: M11 | N38: M12 | O38: M13 | P38: M14 | Q38: M15 | R38: M16 | S38: M17 | T38: M18 | U38: M19 | V38: M20 | W38: M21 | X38: M22 | Y38: M23 | Z38: M24 | AA38: M25 | AB38: M26 | AC38: M27 | AD38: M28 | AE38: M29 | AF38: M30 | AG38: M31 | AH38: M32 | AI38: M33 | AJ38: M34 | AK38: M35 | AL38: M36 | AM38: M37 | AN38: M38 | AO38: M39 | AP38: M40 | AQ38: M41 | AR38: M42 | AS38: M43 | AT38: M44 | AU38: M45 | AV38: M46 | AW38: M47 | AX38: M48 | AY38: M49 | AZ38: M50 | BA38: M51 | BB38: M52 | BC38: M53 | BD38: M54 | BE38: M55 | BF38: M56 | BG38: M57 | BH38: M58 | BI38: M59 | BJ38: M60
A39: Cash Opening | B39: =C21 -> 4.6047327e+08 | C39: =B50 -> 4.6047327e+08 | D39: =C50 -> 1.9224069e+08 | E39: =D50 -> 1.1750811e+08 | F39: =E50 -> 69074750 | G39: =F50 -> 22650193 | H39: =G50 -> 0 | I39: =H50 -> -7720543.4 | J39: =I50 -> 45346175 | ... BJ39: =BI50 -> 7.2544456e+09
A40: - From Operating (Thu từ bán hàng) | C40: =INDEX('💰 Revenue'!$C$14:$BJ$14,MATCH(C5,'💰 Revenue'!$C$5:$BJ$5,0)) -> 0 | D40: =INDEX('💰 Revenue'!$C$14:$BJ$14,MATCH(D5,'💰 Revenue'!$C$5:$BJ$5,0)) -> 0 | E40: =INDEX('💰 Revenue'!$C$14:$BJ$14,MATCH(E5,'💰 Revenue'!$C$5:$BJ$5,0)) -> 125550000 | F40: =INDEX('💰 Revenue'!$C$14:$BJ$14,MATCH(F5,'💰 Revenue'!$C$5:$BJ$5,0)) -> 125550000 | G40: =INDEX('💰 Revenue'!$C$14:$BJ$14,MATCH(G5,'💰 Revenue'!$C$5:$BJ$5,0)) -> 138656250 | H40: =INDEX('💰 Revenue'!$C$14:$BJ$14,MATCH(H5,'💰 Revenue'!$C$5:$BJ$5,0)) -> 165656250 | I40: =INDEX('💰 Revenue'!$C$14:$BJ$14,MATCH(I5,'💰 Revenue'!$C$5:$BJ$5,0)) -> 291093750 | J40: =INDEX('💰 Revenue'!$C$14:$BJ$14,MATCH(J5,'💰 Revenue'!$C$5:$BJ$5,0)) -> 274640625 | ... BJ40: =INDEX('💰 Revenue'!$C$14:$BJ$14,MATCH(BJ5,'💰 Revenue'!$C$5:$BJ$5,0)) -> 384750000
A41: - Loan (Thu từ tiền vay) | C41: ='🏦 Loan Schedule'!B6 -> 451500000
A42: Total Inflow (Tiền thu) | C42: =SUM(C40:C41) -> 451500000 | D42: =D40+D41 -> 0 | E42: =E40+E41 -> 125550000 | F42: =F40+F41 -> 125550000 | G42: =G40+G41 -> 138656250 | H42: =H40+H41 -> 165656250 | I42: =I40+I41 -> 291093750 | J42: =J40+J41 -> 274640625 | K42: =K40+K41 -> 324000000 | ... BJ42: =BJ40+BJ41 -> 384750000
A43: ="Deposit " & '⚙️ Assumptions'!B11& " month rent" -> Deposit 6 month rent | C43: =-'⚙️ Assumptions'!$B$17 -> -345000000
A44: Chi mua CAPEX | C44: =-'⚙️ Assumptions'!$B$16 -> -300000000
A45: Operating outflows (Tiền chi vận hành) | C45: =INDEX('📦 COGS & OpEx'!$C$32:$BJ$32,MATCH(C5,'📦 COGS & OpEx'!$C$3:$BJ$3,0))*-1 -> -60375000 | D45: =INDEX('📦 COGS & OpEx'!$C$32:$BJ$32,MATCH(D5,'📦 COGS & OpEx'!$C$3:$BJ$3,0))*-1 -> -60375000 | E45: =INDEX('📦 COGS & OpEx'!$C$32:$BJ$32,MATCH(E5,'📦 COGS & OpEx'!$C$3:$BJ$3,0))*-1 -> -1.5962578e+08 | F45: =INDEX('📦 COGS & OpEx'!$C$32:$BJ$32,MATCH(F5,'📦 COGS & OpEx'!$C$3:$BJ$3,0))*-1 -> -1.5761698e+08 | G45: =INDEX('📦 COGS & OpEx'!$C$32:$BJ$32,MATCH(G5,'📦 COGS & OpEx'!$C$3:$BJ$3,0))*-1 -> -1.4694886e+08 | H45: =INDEX('📦 COGS & OpEx'!$C$32:$BJ$32,MATCH(H5,'📦 COGS & OpEx'!$C$3:$BJ$3,0))*-1 -> -1.5901921e+08 | I45: =INDEX('📦 COGS & OpEx'!$C$32:$BJ$32,MATCH(I5,'📦 COGS & OpEx'!$C$3:$BJ$3,0))*-1 -> -2.1705377e+08 | J45: =INDEX('📦 COGS & OpEx'!$C$32:$BJ$32,MATCH(J5,'📦 COGS & OpEx'!$C$3:$BJ$3,0))*-1 -> -2.1082886e+08 | ... BJ45: =INDEX('📦 COGS & OpEx'!$C$32:$BJ$32,MATCH(BJ5,'📦 COGS & OpEx'!$C$3:$BJ$3,0))*-1 -> -2.4753926e+08
A46: Interest Payment (Tiền lãi) | C46: =_xlfn.IFNA(INDEX('🏦 Loan Schedule'!$D$14:$D$49,MATCH(C5,'🏦 Loan Schedule'!$B$14:$B$49,0))*-1,0) -> -3386250 | D46: =_xlfn.IFNA(INDEX('🏦 Loan Schedule'!$D$14:$D$49,MATCH(D5,'🏦 Loan Schedule'!$B$14:$B$49,0))*-1,0) -> -3303965 | E46: =_xlfn.IFNA(INDEX('🏦 Loan Schedule'!$D$14:$D$49,MATCH(E5,'🏦 Loan Schedule'!$B$14:$B$49,0))*-1,0) -> -3221062.9 | F46: =_xlfn.IFNA(INDEX('🏦 Loan Schedule'!$D$14:$D$49,MATCH(F5,'🏦 Loan Schedule'!$B$14:$B$49,0))*-1,0) -> -3137539.1 | G46: =_xlfn.IFNA(INDEX('🏦 Loan Schedule'!$D$14:$D$49,MATCH(G5,'🏦 Loan Schedule'!$B$14:$B$49,0))*-1,0) -> -3053388.7 | H46: =_xlfn.IFNA(INDEX('🏦 Loan Schedule'!$D$14:$D$49,MATCH(H5,'🏦 Loan Schedule'!$B$14:$B$49,0))*-1,0) -> -2968607.3 | I46: =_xlfn.IFNA(INDEX('🏦 Loan Schedule'!$D$14:$D$49,MATCH(I5,'🏦 Loan Schedule'!$B$14:$B$49,0))*-1,0) -> -2883190 | J46: =_xlfn.IFNA(INDEX('🏦 Loan Schedule'!$D$14:$D$49,MATCH(J5,'🏦 Loan Schedule'!$B$14:$B$49,0))*-1,0) -> -2797132.1 | ... BJ46: =_xlfn.IFNA(INDEX('🏦 Loan Schedule'!$D$14:$D$49,MATCH(BJ5,'🏦 Loan Schedule'!$B$14:$B$49,0))*-1,0) -> 0
A47: Principal (Tiền gốc) | C47: =C19 -> -10971329 | D47: =D19 -> -11053614 | E47: =E19 -> -11136516 | F47: =F19 -> -11220040 | G47: =G19 -> -11304191 | H47: =H19 -> -11388972 | I47: =I19 -> -11474389 | J47: =J19 -> -11560447 | ... BJ47: =BJ19 -> 0
A48: Thuế | C48: =INDEX('📊 P&L Detail'!$C$31:$BJ$31,MATCH(C5,'📊 P&L Detail'!$C$4:$BJ$4,0))*-1 -> 0 | D48: =INDEX('📊 P&L Detail'!$C$31:$BJ$31,MATCH(D5,'📊 P&L Detail'!$C$4:$BJ$4,0))*-1 -> 0 | E48: =INDEX('📊 P&L Detail'!$C$31:$BJ$31,MATCH(E5,'📊 P&L Detail'!$C$4:$BJ$4,0))*-1 -> 0 | F48: =INDEX('📊 P&L Detail'!$C$31:$BJ$31,MATCH(F5,'📊 P&L Detail'!$C$4:$BJ$4,0))*-1 -> 0 | G48: =INDEX('📊 P&L Detail'!$C$31:$BJ$31,MATCH(G5,'📊 P&L Detail'!$C$4:$BJ$4,0))*-1 -> 0 | H48: =INDEX('📊 P&L Detail'!$C$31:$BJ$31,MATCH(H5,'📊 P&L Detail'!$C$4:$BJ$4,0))*-1 -> 0 | I48: =INDEX('📊 P&L Detail'!$C$31:$BJ$31,MATCH(I5,'📊 P&L Detail'!$C$4:$BJ$4,0))*-1 -> -6615678.7 | J48: =INDEX('📊 P&L Detail'!$C$31:$BJ$31,MATCH(J5,'📊 P&L Detail'!$C$4:$BJ$4,0))*-1 -> -5601463.3 | ... BJ48: =INDEX('📊 P&L Detail'!$C$31:$BJ$31,MATCH(BJ5,'📊 P&L Detail'!$C$4:$BJ$4,0))*-1 -> -13221074
A49: Total Outflows | C49: =SUM(C43:C48) -> -7.1973258e+08 | D49: =D45+D46+D47+D48 -> -74732579 | E49: =E45+E46+E47+E48 -> -1.7398336e+08 | F49: =F45+F46+F47+F48 -> -1.7197456e+08 | G49: =G45+G46+G47+G48 -> -1.6130644e+08 | H49: =H45+H46+H47+H48 -> -1.7337679e+08 | I49: =I45+I46+I47+I48 -> -2.3802703e+08 | J49: =J45+J46+J47+J48 -> -2.307879e+08 | K49: =K45+K46+K47+K48 -> -2.5978604e+08 | ... BJ49: =BJ45+BJ46+BJ47+BJ48 -> -2.6076034e+08
A50: Closing Balance | B50: =B39 -> 4.6047327e+08 | C50: =C39+C42+C49 -> 1.9224069e+08 | D50: =D39+D42+D49 -> 1.1750811e+08 | E50: =E39+E42+E49 -> 69074750 | F50: =F39+F42+F49 -> 22650193 | G50: =G39+G42+G49 -> 0 | H50: =H39+H42+H49 -> -7720543.4 | I50: =I39+I42+I49 -> 45346175 | J50: =J39+J42+J49 -> 89198898 | ... BJ50: =BJ39+BJ42+BJ49 -> 7.3784353e+09
A51: Equity

Sheet 🔄 Rolling Forecast
A1: ROLLING FORECAST – 12-MONTH WINDOW / DỰ BÁO CUỐN CHIẾU 12 THÁNG
A2: Enter current period in B3, then fill Actuals (yellow) as months close. Forecast (white) auto-links from P&L Detail. Variance = Actual – Forecast. / Nhập kỳ hiện tại vào B3. Điền Thực tế (vàng) khi tháng kết thúc. Phần còn lại tự động từ P&L.
A3: Current period (start) / Kỳ hiện tại (bắt đầu): | B3: M04 | C3: ← Enter M01 to M36 / Nhập từ M01 đến M36
A5: LINE ITEM / CHỈ TIÊU | B5: ANNUAL BUDGET NGÂN SÁCH NĂM | C5: M+00 | D5: M+01 | E5: M+02 | F5: M+03 | G5: M+04 | H5: M+05 | I5: M+06 | J5: M+07 | K5: M+08 | L5: M+09 | M5: M+10 | N5: M+11 | O5: 12M TOTAL TỔNG 12T | P5: vs BUDGET SO VỚI NS
C6: ACT / FCST | D6: ACT / FCST | E6: ACT / FCST | F6: ACT / FCST | G6: ACT / FCST | H6: ACT / FCST | I6: ACT / FCST | J6: ACT / FCST | K6: ACT / FCST | L6: ACT / FCST | M6: ACT / FCST | N6: ACT / FCST
A7: Net Revenue / DT Thuần (VNĐ) | B7: =SUM('📊 P&L Detail'!C8:N8) -> 2424571875 | O7: =SUM(C7:N7) -> 0 | P7: =IFERROR(O7-B7,"-") -> -2424571875
A8: COGS (VNĐ) | B8: =SUM('📊 P&L Detail'!C11:N11) -> 642095775 | O8: =SUM(C8:N8) -> 0 | P8: =IFERROR(O8-B8,"-") -> -642095775
A9: Gross Profit / LN Gộp (VNĐ) | B9: =SUM('📊 P&L Detail'!C12:N12) -> 1782476100 | O9: =SUM(C9:N9) -> 0 | P9: =IFERROR(O9-B9,"-") -> -1782476100
A10: Gross Margin % | B10: ="" | O10: ="" | P10: =""
A11: Total OpEx (VNĐ) | B11: =SUM('📊 P&L Detail'!C25:N25) -> 1.5383919e+09 | O11: =SUM(C11:N11) -> 0 | P11: =IFERROR(O11-B11,"-") -> -1.5383919e+09
A12: EBITDA (VNĐ) | B12: =SUM('📊 P&L Detail'!C26:N26) -> 3.3915028e+08 | O12: =SUM(C12:N12) -> 0 | P12: =IFERROR(O12-B12,"-") -> -3.3915028e+08
A13: EBITDA Margin % | B13: ="" | O13: ="" | P13: =""
A14: EBIT (VNĐ) | B14: =SUM('📊 P&L Detail'!C28:N28) -> 2.4408417e+08 | O14: =SUM(C14:N14) -> 0 | P14: =IFERROR(O14-B14,"-") -> -2.4408417e+08
A15: NPAT / LNST (VNĐ) | B15: =SUM('📊 P&L Detail'!C32:N32) -> 1.9591384e+08 | O15: =SUM(C15:N15) -> 0 | P15: =IFERROR(O15-B15,"-") -> -1.9591384e+08
A16: Net Margin % | B16: ="" | O16: ="" | P16: =""
A17: Operating Cash Flow (VNĐ) | B17: =SUM('💵 Cash Flow'!C11:N11) -> 2.9097995e+08 | O17: =SUM(C17:N17) -> 0 | P17: =IFERROR(O17-B17,"-") -> -2.9097995e+08
A18: Net Cash Flow (VNĐ) | B18: =SUM('💵 Cash Flow'!C24:N24) -> 3.8566226e+08 | O18: =SUM(C18:N18) -> 0 | P18: =IFERROR(O18-B18,"-") -> -3.8566226e+08
A19: Cumulative CF (VNĐ) | B19: =SUM('💵 Cash Flow'!C25:N25) -> 1.6365815e+09 | O19: =SUM(C19:N19) -> 0 | P19: =IFERROR(O19-B19,"-") -> -1.6365815e+09
A20: Total Covers / Lượt phục vụ | B20: =SUM('💰 Revenue'!C13:N13) -> 32327.625 | O20: =SUM(C20:N20) -> 0 | P20: =IFERROR(O20-B20,"-") -> -32327.625
A21: Avg spend/cover / Giá xuất | B21: =SUM('💰 Revenue'!C10:N10) -> 900000 | O21: =SUM(C21:N21) -> 0 | P21: =IFERROR(O21-B21,"-") -> -900000
A23: 📝 HOW TO USE / CÁCH SỬ DỤNG: 1) Update 'Current period' in B3 each month. 2) Fill yellow actuals cells as months close. 3) Variances calculate automatically. 4) To advance the window, copy this sheet and shift period by 1. / Cập nhật B3 mỗi tháng. Điền ô vàng khi tháng kết thúc. Biến động tính tự động.

Sheet 🎯 Scenario Manager
A1: SCENARIO MANAGER / PHÂN TÍCH CÁC KỊCH BẢN
A3: Adjust yellow cells to define each scenario, then paste values into Assumptions. / Điều chỉnh ô vàng để xác định kịch bản, sau đó dán giá trị vào Assumptions.
A4: DRIVER / THÔNG SỐ | B4: 🐻 BEAR (Pessimistic) | C4: 📊 BASE (Most Likely) | D4: 🐂 BULL (Optimistic) | E4: UNIT ĐƠN VỊ | F4: IMPACT TÁC ĐỘNG
A5: REVENUE DRIVERS / DT
A6: Avg spend / Giá 1 xuất (VNĐ) | B6: 80000 | C6: 100000 | D6: 130000 | E6: VNĐ | F6: HIGH ⬆⬆
A7: Target covers/day / KH/ngày | B7: 400 | C7: 600 | D7: 900 | E7: khách | F7: HIGH ⬆⬆
A8: Price growth YoY / Tăng giá | B8: 5% | C8: 10% | D8: 15% | E8: %/year | F8: MED ⬆
A9: Seasonal peak mult. / Hệ số cao điểm | B9: 1.10x | C9: 1.20x | D9: 1.35x | E9: x | F9: LOW ⬆
A10: COST DRIVERS / CHI PHÍ
A11: Food cost % / % CP thực phẩm | B11: 38% | C11: 30% | D11: 25% | E11: % rev | F11: HIGH ⬆⬆
A12: Input inflation / Lạm phát TP YoY | B12: 15% | C12: 10% | D12: 5% | E12: %/year | F12: MED ⬆
A13: Monthly rent / Thuê tháng (VNĐ) | B13: High | C13: Mid | D13: Low | E13: VNĐ | F13: HIGH ⬆⬆
A14: Payroll growth YoY / Tăng lương | B14: 15% | C14: 10% | D14: 8% | E14: %/year | F14: MED ⬆
A15: CAPEX & FINANCING
A16: Total capex / Tổng đầu tư | B16: +20% | C16: Base | D16: -10% | E16: % of base | F16: HIGH ⬆⬆
A17: Interest rate / Lãi suất | B17: 12% | C17: 9% | D17: 7% | E17: %/year | F17: MED ⬆
A18: Loan % of capex / % vốn vay | B18: 70% | C18: 50% | D18: 30% | E18: % capex | F18: MED ⬆
A19: MARKET CONDITIONS / THỊ TRƯỜNG
A20: Ramp-up speed / Tốc độ ramp-up | B20: Slow (18M) | C20: Normal (12M) | D20: Fast (6M) | F20: HIGH ⬆⬆
A21: Competitive pressure / CT cạnh tranh | B21: High | C21: Medium | D21: Low | F21: MED ⬆
A22: Economic climate / Kinh tế vĩ mô | B22: Downturn | C22: Stable | D22: Growth | F22: MED ⬆
A24: EXPECTED OUTPUT KPIs / KẾT QUẢ DỰ KIẾN TỪNG KỊCH BẢN
A25: KPI | B25: BEAR Y1 | C25: BASE Y1 | D25: BULL Y1 | E25: BASE Y2 | F25: BASE Y3
A26: Net Revenue / DT Thuần (VNĐ) | C26: =SUM('📊 P&L Detail'!C8:N8) -> 2424571875 | D26: =SUM('📊 P&L Detail'!O8:Z8) -> 4900696875 | E26: =SUM('📊 P&L Detail'!AA8:AL8) -> 5221800000
A27: Gross Profit / LN Gộp (VNĐ) | C27: =SUM('📊 P&L Detail'!C12:N12) -> 1782476100 | D27: =SUM('📊 P&L Detail'!O12:Z12) -> 3698426700 | E27: =SUM('📊 P&L Detail'!AA12:AL12) -> 3999742200
A28: Gross Margin % | C28: =IFERROR(AVERAGE('📊 P&L Detail'!C13:N13),"-") -> 0.7344 | D28: =IFERROR(AVERAGE('📊 P&L Detail'!O13:Z13),"-") -> 0.754 | E28: =IFERROR(AVERAGE('📊 P&L Detail'!AA13:AL13),"-") -> 0.766
A29: EBITDA (VNĐ) | C29: =SUM('📊 P&L Detail'!C26:N26) -> 3.3915028e+08 | D29: =SUM('📊 P&L Detail'!O26:Z26) -> 1.8833535e+09 | E29: =SUM('📊 P&L Detail'!AA26:AL26) -> 2100050280
A30: EBITDA Margin % | C30: =IFERROR(AVERAGE('📊 P&L Detail'!C27:N27),"-") -> 0.1131537 | D30: =IFERROR(AVERAGE('📊 P&L Detail'!O27:Z27),"-") -> 0.38000086 | E30: =IFERROR(AVERAGE('📊 P&L Detail'!AA27:AL27),"-") -> 0.39840106
A31: NPAT / LNST (VNĐ) | C31: =SUM('📊 P&L Detail'!C32:N32) -> 1.9591384e+08 | D31: =SUM('📊 P&L Detail'!O32:Z32) -> 1.6210441e+09 | E31: =SUM('📊 P&L Detail'!AA32:AL32) -> 1.8287433e+09
A32: Net Margin % | C32: =IFERROR(AVERAGE('📊 P&L Detail'!C33:N33),"-") -> 0.059328853 | D32: =IFERROR(AVERAGE('📊 P&L Detail'!O33:Z33),"-") -> 0.32655499 | E32: =IFERROR(AVERAGE('📊 P&L Detail'!AA33:AL33),"-") -> 0.34662861
A34: 💡 TIP: To run a scenario → copy Bear/Bull values from column B/D above into the Assumptions sheet (blue cells), then note outputs. Use Ctrl+Z to revert. / Để chạy kịch bản → copy giá trị Bear/Bull vào sheet Assumptions (ô xanh), ghi lại kết quả. Ctrl+Z để hoàn tác.

Sheet Sheet13

Sheet 🏦 Loan Schedule
A1: LOAN SCHEDULE / LỊCH VAY & TRẢ NỢ
A3: PARAMETER / THÔNG SỐ | B3: VALUE / GIÁ TRỊ | C3: NOTES / GHI CHÚ
A4: Financed? (Vay/ Không vay) | B4: Yes/ Có
A5: Tỷ lệ vay | B5: 0.7
A6: Loan amount / Số tiền vay (VNĐ) | B6: =IF($B$4="No/ Không",0,'⚙️ Assumptions'!$B$18*B5) -> 451500000 | C6: ← Enter value / Nhập giá trị
A7: Annual interest rate / Lãi suất năm (%) | B7: 0.09 | C7: ← Enter value / Nhập giá trị
A8: Loan term / Thời hạn (months) | B8: 36 | C8: ← Enter value / Nhập giá trị
A9: Grace period / Ân hạn (months) | B9: 0 | C9: ← Enter value / Nhập giá trị
A10: Drawdown month / Tháng giải ngân | B10: M01 | C10: ← Enter value / Nhập giá trị
A11: Loan type / Loại vay | B11: Annuity | C11: ← Enter value / Nhập giá trị
A13: PERIOD KỲ | B13: MONTH THÁNG | C13: OPENING BALANCE DƯ NỢ ĐẦU KỲ | D13: INTEREST LÃI VAY | E13: PRINCIPAL GỐC TRẢ | F13: TOTAL PAYMENT TỔNG TRẢ | G13: CLOSING BALANCE DƯ NỢ CUỐI KỲ
A14: 1 | B14: ='⚙️ Assumptions'!B6 -> 46661 | C14: =B6 -> 451500000 | D14: =C14*(B7/12) -> 3386250 | E14: =IF(1<=0,0,MAX(0,(-PMT(B7/12,B8-B9,B6))-D14)) -> 10971329 | F14: =D14+E14 -> 14357579 | G14: =MAX(0,C14-E14) -> 4.4052867e+08
A15: 2 | B15: =EDATE($B$14,A14) -> 46692 | C15: =G14 -> 4.4052867e+08 | D15: =C15*(B7/12) -> 3303965 | E15: =IF(2<=0,0,MAX(0,(-PMT(B7/12,B8-B9,B6))-D15)) -> 11053614 | F15: =D15+E15 -> 14357579 | G15: =MAX(0,C15-E15) -> 4.2947506e+08
A16: 3 | B16: =EDATE($B$14,A15) -> 46722 | C16: =G15 -> 4.2947506e+08 | D16: =C16*(B7/12) -> 3221062.9 | E16: =IF(3<=0,0,MAX(0,(-PMT(B7/12,B8-B9,B6))-D16)) -> 11136516 | F16: =D16+E16 -> 14357579 | G16: =MAX(0,C16-E16) -> 4.1833854e+08
A17: 4 | B17: =EDATE($B$14,A16) -> 46753 | C17: =G16 -> 4.1833854e+08 | D17: =C17*(B7/12) -> 3137539.1 | E17: =IF(4<=0,0,MAX(0,(-PMT(B7/12,B8-B9,B6))-D17)) -> 11220040 | F17: =D17+E17 -> 14357579 | G17: =MAX(0,C17-E17) -> 4.071185e+08
A18: 5 | B18: =EDATE($B$14,A17) -> 46784 | C18: =G17 -> 4.071185e+08 | D18: =C18*(B7/12) -> 3053388.7 | E18: =IF(5<=0,0,MAX(0,(-PMT(B7/12,B8-B9,B6))-D18)) -> 11304191 | F18: =D18+E18 -> 14357579 | G18: =MAX(0,C18-E18) -> 3.9581431e+08
A19: 6 | B19: =EDATE($B$14,A18) -> 46813 | C19: =G18 -> 3.9581431e+08 | D19: =C19*(B7/12) -> 2968607.3 | E19: =IF(6<=0,0,MAX(0,(-PMT(B7/12,B8-B9,B6))-D19)) -> 11388972 | F19: =D19+E19 -> 14357579 | G19: =MAX(0,C19-E19) -> 3.8442534e+08
A20: 7 | B20: =EDATE($B$14,A19) -> 46844 | C20: =G19 -> 3.8442534e+08 | D20: =C20*(B7/12) -> 2883190 | E20: =IF(7<=0,0,MAX(0,(-PMT(B7/12,B8-B9,B6))-D20)) -> 11474389 | F20: =D20+E20 -> 14357579 | G20: =MAX(0,C20-E20) -> 3.7295095e+08
A21: 8 | B21: =EDATE($B$14,A20) -> 46874 | C21: =G20 -> 3.7295095e+08 | D21: =C21*(B7/12) -> 2797132.1 | E21: =IF(8<=0,0,MAX(0,(-PMT(B7/12,B8-B9,B6))-D21)) -> 11560447 | F21: =D21+E21 -> 14357579 | G21: =MAX(0,C21-E21) -> 3.613905e+08
A22: 9 | B22: =EDATE($B$14,A21) -> 46905 | C22: =G21 -> 3.613905e+08 | D22: =C22*(B7/12) -> 2710428.8 | E22: =IF(9<=0,0,MAX(0,(-PMT(B7/12,B8-B9,B6))-D22)) -> 11647151 | F22: =D22+E22 -> 14357579 | G22: =MAX(0,C22-E22) -> 3.4974335e+08
A23: 10 | B23: =EDATE($B$14,A22) -> 46935 | C23: =G22 -> 3.4974335e+08 | D23: =C23*(B7/12) -> 2623075.1 | E23: =IF(10<=0,0,MAX(0,(-PMT(B7/12,B8-B9,B6))-D23)) -> 11734504 | F23: =D23+E23 -> 14357579 | G23: =MAX(0,C23-E23) -> 3.3800885e+08
A24: 11 | B24: =EDATE($B$14,A23) -> 46966 | C24: =G23 -> 3.3800885e+08 | D24: =C24*(B7/12) -> 2535066.3 | E24: =IF(11<=0,0,MAX(0,(-PMT(B7/12,B8-B9,B6))-D24)) -> 11822513 | F24: =D24+E24 -> 14357579 | G24: =MAX(0,C24-E24) -> 3.2618633e+08
A25: 12 | B25: =EDATE($B$14,A24) -> 46997 | C25: =G24 -> 3.2618633e+08 | D25: =C25*(B7/12) -> 2446397.5 | E25: =IF(12<=0,0,MAX(0,(-PMT(B7/12,B8-B9,B6))-D25)) -> 11911182 | F25: =D25+E25 -> 14357579 | G25: =MAX(0,C25-E25) -> 3.1427515e+08
A26: 13 | B26: =EDATE($B$14,A25) -> 47027 | C26: =G25 -> 3.1427515e+08 | D26: =C26*(B7/12) -> 2357063.6 | E26: =IF(13<=0,0,MAX(0,(-PMT(B7/12,B8-B9,B6))-D26)) -> 12000516 | F26: =D26+E26 -> 14357579 | G26: =MAX(0,C26-E26) -> 3.0227464e+08
A27: 14 | B27: =EDATE($B$14,A26) -> 47058 | C27: =G26 -> 3.0227464e+08 | D27: =C27*(B7/12) -> 2267059.8 | E27: =IF(14<=0,0,MAX(0,(-PMT(B7/12,B8-B9,B6))-D27)) -> 12090520 | F27: =D27+E27 -> 14357579 | G27: =MAX(0,C27-E27) -> 2.9018412e+08
A28: 15 | B28: =EDATE($B$14,A27) -> 47088 | C28: =G27 -> 2.9018412e+08 | D28: =C28*(B7/12) -> 2176380.9 | E28: =IF(15<=0,0,MAX(0,(-PMT(B7/12,B8-B9,B6))-D28)) -> 12181198 | F28: =D28+E28 -> 14357579 | G28: =MAX(0,C28-E28) -> 2.7800292e+08
A29: 16 | B29: =EDATE($B$14,A28) -> 47119 | C29: =G28 -> 2.7800292e+08 | D29: =C29*(B7/12) -> 2085021.9 | E29: =IF(16<=0,0,MAX(0,(-PMT(B7/12,B8-B9,B6))-D29)) -> 12272557 | F29: =D29+E29 -> 14357579 | G29: =MAX(0,C29-E29) -> 2.6573036e+08
A30: 17 | B30: =EDATE($B$14,A29) -> 47150 | C30: =G29 -> 2.6573036e+08 | D30: =C30*(B7/12) -> 1992977.7 | E30: =IF(17<=0,0,MAX(0,(-PMT(B7/12,B8-B9,B6))-D30)) -> 12364602 | F30: =D30+E30 -> 14357579 | G30: =MAX(0,C30-E30) -> 2.5336576e+08
A31: 18 | B31: =EDATE($B$14,A30) -> 47178 | C31: =G30 -> 2.5336576e+08 | D31: =C31*(B7/12) -> 1900243.2 | E31: =IF(18<=0,0,MAX(0,(-PMT(B7/12,B8-B9,B6))-D31)) -> 12457336 | F31: =D31+E31 -> 14357579 | G31: =MAX(0,C31-E31) -> 2.4090842e+08
A32: 19 | B32: =EDATE($B$14,A31) -> 47209 | C32: =G31 -> 2.4090842e+08 | D32: =C32*(B7/12) -> 1806813.2 | E32: =IF(19<=0,0,MAX(0,(-PMT(B7/12,B8-B9,B6))-D32)) -> 12550766 | F32: =D32+E32 -> 14357579 | G32: =MAX(0,C32-E32) -> 2.2835766e+08
A33: 20 | B33: =EDATE($B$14,A32) -> 47239 | C33: =G32 -> 2.2835766e+08 | D33: =C33*(B7/12) -> 1712682.4 | E33: =IF(20<=0,0,MAX(0,(-PMT(B7/12,B8-B9,B6))-D33)) -> 12644897 | F33: =D33+E33 -> 14357579 | G33: =MAX(0,C33-E33) -> 2.1571276e+08
A34: 21 | B34: =EDATE($B$14,A33) -> 47270 | C34: =G33 -> 2.1571276e+08 | D34: =C34*(B7/12) -> 1617845.7 | E34: =IF(21<=0,0,MAX(0,(-PMT(B7/12,B8-B9,B6))-D34)) -> 12739734 | F34: =D34+E34 -> 14357579 | G34: =MAX(0,C34-E34) -> 2.0297303e+08
A35: 22 | B35: =EDATE($B$14,A34) -> 47300 | C35: =G34 -> 2.0297303e+08 | D35: =C35*(B7/12) -> 1522297.7 | E35: =IF(22<=0,0,MAX(0,(-PMT(B7/12,B8-B9,B6))-D35)) -> 12835282 | F35: =D35+E35 -> 14357579 | G35: =MAX(0,C35-E35) -> 1.9013774e+08
A36: 23 | B36: =EDATE($B$14,A35) -> 47331 | C36: =G35 -> 1.9013774e+08 | D36: =C36*(B7/12) -> 1426033.1 | E36: =IF(23<=0,0,MAX(0,(-PMT(B7/12,B8-B9,B6))-D36)) -> 12931546 | F36: =D36+E36 -> 14357579 | G36: =MAX(0,C36-E36) -> 1.772062e+08
A37: 24 | B37: =EDATE($B$14,A36) -> 47362 | C37: =G36 -> 1.772062e+08 | D37: =C37*(B7/12) -> 1329046.5 | E37: =IF(24<=0,0,MAX(0,(-PMT(B7/12,B8-B9,B6))-D37)) -> 13028533 | F37: =D37+E37 -> 14357579 | G37: =MAX(0,C37-E37) -> 1.6417767e+08
A38: 25 | B38: =EDATE($B$14,A37) -> 47392 | C38: =G37 -> 1.6417767e+08 | D38: =C38*(B7/12) -> 1231332.5 | E38: =IF(25<=0,0,MAX(0,(-PMT(B7/12,B8-B9,B6))-D38)) -> 13126247 | F38: =D38+E38 -> 14357579 | G38: =MAX(0,C38-E38) -> 1.5105142e+08
A39: 26 | B39: =EDATE($B$14,A38) -> 47423 | C39: =G38 -> 1.5105142e+08 | D39: =C39*(B7/12) -> 1132885.6 | E39: =IF(26<=0,0,MAX(0,(-PMT(B7/12,B8-B9,B6))-D39)) -> 13224694 | F39: =D39+E39 -> 14357579 | G39: =MAX(0,C39-E39) -> 1.3782672e+08
A40: 27 | B40: =EDATE($B$14,A39) -> 47453 | C40: =G39 -> 1.3782672e+08 | D40: =C40*(B7/12) -> 1033700.4 | E40: =IF(27<=0,0,MAX(0,(-PMT(B7/12,B8-B9,B6))-D40)) -> 13323879 | F40: =D40+E40 -> 14357579 | G40: =MAX(0,C40-E40) -> 1.2450285e+08
A41: 28 | B41: =EDATE($B$14,A40) -> 47484 | C41: =G40 -> 1.2450285e+08 | D41: =C41*(B7/12) -> 933771.35 | E41: =IF(28<=0,0,MAX(0,(-PMT(B7/12,B8-B9,B6))-D41)) -> 13423808 | F41: =D41+E41 -> 14357579 | G41: =MAX(0,C41-E41) -> 1.1107904e+08
A42: 29 | B42: =EDATE($B$14,A41) -> 47515 | C42: =G41 -> 1.1107904e+08 | D42: =C42*(B7/12) -> 833092.79 | E42: =IF(29<=0,0,MAX(0,(-PMT(B7/12,B8-B9,B6))-D42)) -> 13524487 | F42: =D42+E42 -> 14357579 | G42: =MAX(0,C42-E42) -> 97554552
A43: 30 | B43: =EDATE($B$14,A42) -> 47543 | C43: =G42 -> 97554552 | D43: =C43*(B7/12) -> 731659.14 | E43: =IF(30<=0,0,MAX(0,(-PMT(B7/12,B8-B9,B6))-D43)) -> 13625920 | F43: =D43+E43 -> 14357579 | G43: =MAX(0,C43-E43) -> 83928632
A44: 31 | B44: =EDATE($B$14,A43) -> 47574 | C44: =G43 -> 83928632 | D44: =C44*(B7/12) -> 629464.74 | E44: =IF(31<=0,0,MAX(0,(-PMT(B7/12,B8-B9,B6))-D44)) -> 13728115 | F44: =D44+E44 -> 14357579 | G44: =MAX(0,C44-E44) -> 70200517
A45: 32 | B45: =EDATE($B$14,A44) -> 47604 | C45: =G44 -> 70200517 | D45: =C45*(B7/12) -> 526503.88 | E45: =IF(32<=0,0,MAX(0,(-PMT(B7/12,B8-B9,B6))-D45)) -> 13831075 | F45: =D45+E45 -> 14357579 | G45: =MAX(0,C45-E45) -> 56369442
A46: 33 | B46: =EDATE($B$14,A45) -> 47635 | C46: =G45 -> 56369442 | D46: =C46*(B7/12) -> 422770.81 | E46: =IF(33<=0,0,MAX(0,(-PMT(B7/12,B8-B9,B6))-D46)) -> 13934808 | F46: =D46+E46 -> 14357579 | G46: =MAX(0,C46-E46) -> 42434633
A47: 34 | B47: =EDATE($B$14,A46) -> 47665 | C47: =G46 -> 42434633 | D47: =C47*(B7/12) -> 318259.75 | E47: =IF(34<=0,0,MAX(0,(-PMT(B7/12,B8-B9,B6))-D47)) -> 14039320 | F47: =D47+E47 -> 14357579 | G47: =MAX(0,C47-E47) -> 28395313
A48: 35 | B48: =EDATE($B$14,A47) -> 47696 | C48: =G47 -> 28395313 | D48: =C48*(B7/12) -> 212964.85 | E48: =IF(35<=0,0,MAX(0,(-PMT(B7/12,B8-B9,B6))-D48)) -> 14144614 | F48: =D48+E48 -> 14357579 | G48: =MAX(0,C48-E48) -> 14250699
A49: 36 | B49: =EDATE($B$14,A48) -> 47727 | C49: =G48 -> 14250699 | D49: =C49*(B7/12) -> 106880.24 | E49: =IF(36<=0,0,MAX(0,(-PMT(B7/12,B8-B9,B6))-D49)) -> 14250699 | F49: =D49+E49 -> 14357579 | G49: =MAX(0,C49-E49) -> 0
A50: TOTAL | C50: =C14 -> 451500000 | D50: =SUM(D14:D49) -> 65372855 | E50: =SUM(E14:E49) -> 451500000 | F50: =SUM(F14:F49) -> 5.1687285e+08 | G50: =G49 -> 0

Sheet ⚙️ Other Assumptions
A1: ASSUMPTIONS & DRIVERS / GIẢ ĐỊNH & THÔNG SỐ ĐẦU VÀO
A4: Yes/ Có
A5: No/ Không
A7: Phân khúc | B7: Avg Price/m2
A8: Main Area – close to sword lake (Lê Thái Tổ, Đinh Tiên Hoàng, Hàng Khay, Tràng Tiền) | B8: =(1.7*10^6 + 3.5*10^6)/2 -> 2600000
A9: Old Quarters(Hàng Đào, Lý Quốc Sư, Lý Thái Tổ) | B9: =(1 + 2.7)/2*10^6 -> 1850000
A10: Nearby Area(Cửa Nam, Nguyễn Hữu Huân, Triệu Việt Vương) | B10: =(0.8+1.5)/2*10^6 -> 1150000
A14: Index | B14: 1 | C14: 2 | D14: 3 | E14: 4 | F14: 5 | G14: 6 | H14: 7 | I14: 8 | J14: 9 | K14: 10 | L14: 11 | M14: 12 | N14: 13 | O14: 14 | P14: 15 | Q14: 16 | R14: 17 | S14: 18 | T14: 19 | U14: 20 | V14: 21 | W14: 22 | X14: 23 | Y14: 24 | Z14: 25 | AA14: 26 | AB14: 27 | AC14: 28 | AD14: 29 | AE14: 30 | AF14: 31 | AG14: 32 | AH14: 33 | AI14: 34 | AJ14: 35 | AK14: 36
A15: Hot months (Hệ số điều chỉnh tiêu thụ điện các tháng trong năm) | B15: 0.9 | C15: 1 | D15: 1 | E15: 1 | F15: 1 | G15: 1.5 | H15: 1.5 | I15: 1.5 | J15: 1.5 | K15: 1.5 | L15: 0.9 | M15: 0.9
A16: Holidays (Hệ số điều chỉnh vụ mùa các dịp lễ) | B16: 1.2 | C16: 0.85 | D16: 0.95 | E16: 1.15 | F16: 1.05 | G16: 1.2 | H16: 1.15 | I16: 1 | J16: 0.95 | K16: 0.95 | L16: 1.05 | M16: 1.2
A17: Ramp-up Pesimistic | B17: 0 | C17: 0 | D17: 0.15 | E17: 0.2 | F17: 0.3 | G17: 0.4 | H17: 0.45 | I17: 0.5 | J17: 0.5 | K17: 0.6 | L17: 0.6 | M17: 0.65 | N17: 0.65 | O17: 0.7 | P17: 0.8 | Q17: 0.8 | R17: 1 | S17: 1 | T17: 1 | U17: 1 | V17: 1 | W17: 1 | X17: 1 | Y17: 1 | Z17: 1 | AA17: 1 | AB17: 1 | AC17: 1 | AD17: 1 | AE17: 1 | AF17: 1 | AG17: 1 | AH17: 1 | AI17: 1 | AJ17: 1 | AK17: 1
A18: Ramp-up Neutral | B18: 0 | C18: 0 | D18: 0.3 | E18: 0.3 | F18: 0.5 | G18: 0.5 | H18: 0.75 | I18: 0.75 | J18: 0.8 | K18: 0.9 | L18: 0.9 | M18: 0.95 | N18: 0.95 | O18: 1 | P18: 1 | Q18: 1 | R18: 1 | S18: 1 | T18: 1 | U18: 1 | V18: 1 | W18: 1 | X18: 1.2 | Y18: 1.2 | Z18: 1.2 | AA18: 1.2 | AB18: 1.2 | AC18: 1.2 | AD18: 1.2 | AE18: 1.2 | AF18: 1.2 | AG18: 1.2 | AH18: 1.2 | AI18: 1.2 | AJ18: 1.2 | AK18: 1.2
A19: Ramp-up Optimistic | B19: 0 | C19: 0 | D19: 0.45 | E19: 0.6 | F19: 0.7 | G19: 0.8 | H19: 0.9 | I19: 1 | J19: 1 | K19: 1 | L19: 1 | M19: 1 | N19: 1 | O19: 1 | P19: 1 | Q19: 1 | R19: 1.2 | S19: 1.2 | T19: 1.2 | U19: 1.2 | V19: 1.2 | W19: 1.2 | X19: 1.2 | Y19: 1.2 | Z19: 1.2 | AA19: 1.2 | AB19: 1.2 | AC19: 1.2 | AD19: 1.2 | AE19: 1.2 | AF19: 1.2 | AG19: 1.2 | AH19: 1.2 | AI19: 1.2 | AJ19: 1.2 | AK19: 1.2
A20: Marketing Cots (% of Rev) | B20: 0 | C20: 0 | D20: 0.2 | E20: 0.2 | F20: 0.2 | G20: 0.08 | H20: 0.08 | I20: 0.08 | J20: 0.08 | K20: 0.08 | L20: 0.04 | M20: 0.04 | N20: 0.04 | O20: 0.04 | P20: 0.03 | Q20: 0.03 | R20: 0.03 | S20: 0.03 | T20: 0.03 | U20: 0.03 | V20: 0.03 | W20: 0.03 | X20: 0.03 | Y20: 0.03 | Z20: 0.03 | AA20: 0.03 | AB20: 0.03 | AC20: 0.03 | AD20: 0.03 | AE20: 0.03 | AF20: 0.03 | AG20: 0.03 | AH20: 0.03 | AI20: 0.03 | AJ20: 0.03 | AK20: 0.03
A23: Default Marketing Cost (% of Rev) | B23: 0.03
A24: Ramp-up Pesimistic | B24: =MAX(C17:AJ17) -> 1
A25: Ramp-up Neutral | B25: =MAX(C18:AJ18) -> 1.2
A26: Ramp-up Optimistic | B26: =MAX(C19:AJ19) -> 1.2
